Workbook

Sheet Datos Originales
A1: Empresa | B1: Sucursal | C1: Proveedor | D1: Factura | E1: Fecha Factura | F1: Fecha Poliza | G1: Fecha Envío | H1: Total | I1: Moneda | J1: Tipo Cambio | K1: Total MX | L1: Insumo | M1: Cantidad | N1: Precio | O1: Descuento | P1: Total | Q1: Total MX | R1: Tipo | S1: Familia | T1: SubFamilia | U1: Folio | V1: OC | W1: REQ | X1: SC | Y1: Departamento | Z1: Solicitante | AA1: Grupo Centro de Costo | AB1: Centro Costo | AC1: K.M. | AD1: Colaborador | AE1: Estatus | AF1: CC OC | AG1: Observaciones OC | AH1: Subtotal OC | AI1: Descuento OC | AJ1: IVA OC | AK1: Gastos Envío OC | AL1: Total OC | AM1: Cuenta Contable 1 | AN1: Cuenta Contable 2 | AO1: Cuenta Contable 3 | AP1: Cuenta Contable 4 | AQ1: Cuenta Contable 5 | AR1: Cuenta Contable 6 | AS1: Cuenta Contable 7 | AT1: Cuenta Contable 8 | AU1: Cuenta Contable 9 | AV1: Cuenta Contable 10 | AW1: Cuenta Contable 11 | AX1: Cuenta Contable 12 | AY1: Cuenta Contable 13 | AZ1: Cuenta Contable 14 | BA1: Cuenta Contable 15 | BB1: Cuenta Contable 16 | BC1: Cuenta Contable 17
A2: PETROPLAZAS | B2: Alamos | C2: FORMULA 100 SA DE CV | D2: A4860 | E2: 01/06/2026 | F2: 01/06/2026 | G2: 01/06/2026 | H2: 288.84 | I2: Pesos (MXN) | J2: 1 | K2: 288.84 | L2: SERVICIO DE RENTA AVANZADO DISPOSITIVO 3NW | M2: 1 | N2: 249 | P2: 249 | Q2: 249 | R2: SERVICIO | S2: Servicios | T2: Servicios | U2: SRV0000068 | V2: 73114 | W2: 66408 | X2: 60214 | Y2: ADMINISTRACION | Z2: CRISTOBAL IBARRA MANZANO | AA2: ES_Alamos | AB2: AUTOMOVIL - AU-151 | AE2: PAGADA | AF2: AUTOMOVIL - AU-151 | AG2: Movimiento generado en automático por sistema. Proceso de Carga Masiva de Facturas | AH2: 249.00 | AI2: 0.00 | AJ2: 39.84 | AK2: 0.00 | AL2: 288.84 | AM2: 50299040046 | AN2: 12101030000 | AO2: 20101021500
A3: PETROPLAZAS | B3: Petroplazas Corporativo | C3: ARK 21 | D3: 64F6E70 | E3: 01/06/2026 | F3: 01/06/2026 | G3: 01/06/2026 | H3: 836484.95 | I3: Pesos (MXN) | J3: 1 | K3: 836484.95 | L3: CONSTRUCCION - SERVICIO DE CONSTRUCCION | M3: 0.045860264 | N3: 15724020.1 | P3: 721107.7129273064 | Q3: 721107.712927 | R3: SERVICIO | S3: Servicios | T3: Servicios | U3: SRV0005503 | V3: 70783 | W3: 63973 | X3: 58132 | Y3: COMPRAS | Z3: HUGO JAIME LIZARRAGA CARRILLO | AA3: ES_Corporativo | AB3: CC ADMINISTRACION | AC3: 0 | AE3: PAGADA | AF3: CC ADMINISTRACION | AG3: PROYECTO DE CONSTRUCCION DE ESTACION COLON. CFDI I01 CONSTRUCCION | AH3: 15,724,020.10 | AI3: 0.00 | AJ3: 2,515,843.22 | AK3: 0.00 | AL3: 18,239,863.32 | AM3: _CUA-DRE--000000 | AN3: 12101030000 | AO3: 20101021500
A4: PETROPLAZAS | B4: Rosario | C4: Equipos Industriales del Noroeste SA de CV | D4: FA23246 | E4: 01/06/2026 | F4: 01/06/2026 | G4: 01/06/2026 | H4: 4572.86 | I4: Pesos (MXN) | J4: 1 | K4: 4572.86 | L4: PISTOLA AUTOMATICA OPW 3/4" NEGRO | N4: 1656.06 | R4: ALMACEN | S4: Herramientas y Utiles | T4: Accesorios | U4: E000000121 | V4: 73208 | X4: 60217 | Z4: Maria Isabel Vega Gaxiola | AE4: PAGADA | AF4: Estatus Surtido | AG4: COMPRA POR MATERIAL PARA STOK APOYOA DISPENSARIOS ESTACION ROSARIO, MAYO 2026. Nota; Facturar a inicios de junio por favor. ENTREGAR EN CEDIS MAZATLAN CON ISABLE VEGA. | AH4: 3,942.12 | AI4: 0.00 | AJ4: 630.74 | AK4: 0.00 | AL4: 4,572.86 | AM4: 20101021501 | AN4: 12101030000 | AO4: 20101021500
A5: PETROPLAZAS | B5: Fatima | C5: FORMULA 100 SA DE CV | D5: A4861 | E5: 01/06/2026 | F5: 01/06/2026 | G5: 01/06/2026 | H5: 288.84 | I5: Pesos (MXN) | J5: 1 | K5: 288.84 | L5: SERVICIO DE RENTA AVANZADO DISPOSITIVO 3NW | M5: 1 | N5: 249 | P5: 249 | Q5: 249 | R5: SERVICIO | S5: Servicios | T5: Servicios | U5: SRV0000040 | V5: 73115 | W5: 66409 | X5: 60215 | Y5: ADMINISTRACION | Z5: CRISTOBAL IBARRA MANZANO | AA5: ES_Fatima | AB5: AUTOMOVIL AU-131 | AE5: PAGADA | AF5: AUTOMOVIL AU-131 | AG5: Movimiento generado en automático por sistema. Proceso de Carga Masiva de Facturas | AH5: 249.00 | AI5: 0.00 | AJ5: 39.84 | AK5: 0.00 | AL5: 288.84 | AM5: 50299040046 | AN5: 12101030000 | AO5: 20101021500
A6: PETROPLAZAS | B6: Escuinapa | C6: Equipos Industriales del Noroeste SA de CV | D6: FA23247 | E6: 01/06/2026 | F6: 01/06/2026 | G6: 01/06/2026 | H6: 3842.06 | I6: Pesos (MXN) | J6: 1 | K6: 3842.06 | L6: PISTOLA AUTOMATICA OPW 3/4" NEGRO | N6: 1656.06 | R6: ALMACEN | S6: Herramientas y Utiles | T6: Accesorios | U6: E000000182 | V6: 73121 | X6: 60211 | Z6: Maria Isabel Vega Gaxiola | AE6: PAGADA | AF6: Estatus Surtido | AG6: COMPRA POR PISTOLA PARA DESP. GASOL. NEGRA DE 3/4" 11-B OPW SOLICTADAS PARA ESTACION ESCUINAPA, MAYO 2026. Nota, Facturar a inicios de junio ENTREGAR EN CEDIS MAZATLAN CON ISABEL VEGA. | AH6: 3,312.12 | AI6: 0.00 | AJ6: 529.94 | AK6: 0.00 | AL6: 3,842.06 | AM6: 20101021501 | AN6: 12101030000 | AO6: 20101021500
A7: PETROPLAZAS | B7: AEROPUERTO | C7: Electrica Valdez SA de CV | D7: M00646230 | E7: 01/06/2026 | F7: 01/06/2026 | G7: 01/06/2026 | H7: 1293.86 | I7: Pesos (MXN) | J7: 1 | K7: 1293.86 | L7: TUBO LED T8 18W BASE ALUMINIO | N7: 33 | R7: ALMACEN | S7: Ferreteria | T7: Varios | U7: E000000282 | V7: 73287 | W7: 66290 | X7: 60221 | Y7: OPERACIONES | Z7: Maria Isabel Vega Gaxiola | AA7: ES_Aeropuerto | AB7: ESTACION AEROPUERTO | AE7: PAGADA | AF7: ESTACION AEROPUERTO | AG7: COMPRA POR 6 TUBO LED 36W T8 Y Y 10 TUBO LED 18W T8 120cm SOLICITADOS PARA ESTACION AEROPUERTO, JUNIO 2026. ENTREGAR EN CEDIS MAZATLAN CON ISABEL VEGA. | AH7: 1,115.40 | AI7: 0.00 | AJ7: 178.46 | AK7: 0.00 | AL7: 1,293.86 | AM7: 20101021501 | AN7: 12101030000 | AO7: 20101021500
A8: PETROPLAZAS | B8: La Colorada | C8: COMERCIALIZADORA SANITARIA, S.A. DE C.V. | D8: MAZ4892 | E8: 02/06/2026 | F8: 02/06/2026 | G8: 02/06/2026 | H8: 4582 | I8: Pesos (MXN) | J8: 1 | K8: 4582 | L8: JABON LIQUIDO PARA MANOS | N8: 41.4 | R8: ALMACEN | S8: Artículos de Limpieza | T8: Artículos de Limpieza | U8: E000000183 | V8: 73302 | W8: 66420 | X8: 60331 | Y8: OPERACIONES GASOLINERAS | Z8: Diego Alejandro Estrada Ramos | AA8: ES_LA_COLORADA | AB8: BAÑOS PARA COLABORADORES. | AE8: PAGADA | AF8: OFICINAS ADMINISTRATIVAS. | AG8: FAVOR DE ENTREGAR EN ESTACION LA COLORADA CON EL SUPERVISOR AL DOMICILIO CALLE LATERAL CARRETERA SN, COL. NUEVO HERMOSILLO, HERMOSILLO, SONORA, CP. 83296. MATERIAL DE LIMPIEZA DEL MES DE JUNIO 2026. | AH8: 3,950.00 | AI8: 0.00 | AJ8: 632.00 | AK8: 0.00 | AL8: 4,582.00 | AM8: 20101021501 | AN8: 12101030000 | AO8: 20101021500
A9: PETROPLAZAS | B9: Fatima | C9: FRANCISCO JAVIER RAMIREZ HERNANDEZ | D9: A6054 | E9: 01/06/2026 | F9: 02/06/2026 | G9: 02/06/2026 | H9: 2673.65 | I9: Pesos (MXN) | J9: 1 | K9: 2673.65 | L9: CAMARA DE SEGURIDAD PARA INTERIOR | N9: 768.29 | R9: ALMACEN | S9: Equipo de Computo | T9: Camaras | U9: E000000119 | V9: 73327 | W9: 66383 | X9: 60354 | Y9: OPERACIONES GASOLINERAS | Z9: Diego Alejandro Estrada Ramos | AA9: ES_Fatima | AB9: Estacion Fatima | AE9: PAGADA | AF9: Estacion Fatima | AG9: CORRESPONDE A LA FACTURA A6054. CAMARA DE SEGURIDAD Y ADITAMIENTO EN ESTACION FATIMA. | AH9: 2,304.87 | AI9: 0.00 | AJ9: 368.78 | AK9: 0.00 | AL9: 2,673.65 | AM9: 20101021501 | AN9: 12101030000 | AO9: 20101021500
A10: PETROPLAZAS | B10: Petroplazas Corporativo | C10: Aguilar Hernandez Ana Guadalupe | D10: F701219 | E10: 01/06/2026 | F10: 02/06/2026 | G10: 02/06/2026 | H10: 206025.46 | I10: Pesos (MXN) | J10: 1 | K10: 206025.46 | L10: PRESTACION DE SERVICIOS | M10: 1 | N10: 216110.7 | P10: 216110.7 | Q10: 216110.7 | R10: SERVICIO | S10: Servicios | T10: Servicios | U10: SRV0005507 | V10: 73376 | W10: 66548 | X10: 60376 | Y10: CONTABILIDAD | Z10: ELIZABETH GUADALUPE ARROYO PERAZA | AA10: ES_Corporativo | AB10: GASTOS GENERALES | AE10: PAGADA | AF10: GASTOS GENERALES | AG10: PAGO DE LA FACT. 19 POR EL ARRENDAMIENTO DE TERRENO DE ESTACION EL DIEZ, (LA O.C. SE HIZO POR 12 MESES, LOS CUALES SE IRAN PAGANDO MES A MES). PROGRAMAR A PAGO PARA EL 04/06/2026. | AH10: 2,593,328.40 | AI10: 0.00 | AJ10: 414,932.54 | AK10: 0.00 | AL10: 2,472,305.54 | AM10: 50299040023 | AN10: 12101030000 | AO10: 22201050000 | AP10: 22201020000 | AQ10: 20101021500
A11: PETROPLAZAS | B11: CEDIS Mazatlán | C11: JOSHUA ALBERTO TIRADO ROMERO | D11: 462FC | E11: 02/06/2026 | F11: 02/06/2026 | G11: 02/06/2026 | H11: 78648 | I11: Pesos (MXN) | J11: 1 | K11: 78648 | L11: SERVICIO DE INTERNET | M11: 1 | N11: 2900 | P11: 2900 | Q11: 2900 | R11: SERVICIO | S11: Servicios | T11: Servicios | U11: SRV0000604 | V11: 73381 | W11: 66558 | X11: 60379 | Y11: INFRAESTRUCTURA TECNOLOGICA | Z11: JUAN CARLOS MORENO OSUNA | AA11: EST_EL_CONCHI | AB11: ES_El_Conchi | AE11: PAGADA | AF11: Escuinapa | AG11: SERVICIO RED JOSHUA SITIO MAZATLAN, JUNIO 2026 | AH11: 67,800.00 | AI11: 0.00 | AJ11: 10,848.00 | AK11: 0.00 | AL11: 78,648.00 | AM11: 50299040042 | AN11: 12101030000 | AO11: 20101021500
A12: PETROPLAZAS | B12: Petroplazas Corporativo | C12: Juan Pablo Ramos Velarde | D12: I40 | E12: 01/06/2026 | F12: 02/06/2026 | G12: 02/06/2026 | H12: 11475 | I12: Pesos (MXN) | J12: 1 | K12: 11475 | L12: SERVICIO DE DESARROLLO DE SOFTWARE | M12: 1 | N12: 10000 | P12: 10000 | Q12: 10000 | R12: SERVICIO | S12: Servicios | T12: Servicios | U12: SRV0005504 | V12: 73329 | W12: 66518 | X12: 60356 | Y12: COMPRAS | Z12: HUGO JAIME LIZARRAGA CARRILLO | AA12: ES_Corporativo | AB12: CC ADMINISTRACION | AC12: 0 | AE12: PAGADA | AF12: CC ADMINISTRACION | AG12: CORRESPONDE A LA FACTURA 40. SERVICIO DE MANTENIMIENTO Y DESARROLLO DE SOFTWARE DE CORPORATIVO DIVISION GASOLINERAS. | AH12: 10,000.00 | AI12: 0.00 | AJ12: 1,600.00 | AK12: 0.00 | AL12: 11,475.00 | AM12: 50299040021 | AN12: 12101030000 | AO12: 22201210000 | AP12: 20101021500
A13: PETROPLAZAS | B13: CEDIS Culiacán | C13: GABRIELA DE JESUS RAMIREZ LOAIZA | D13: E018C998 | E13: 01/06/2026 | F13: 02/06/2026 | G13: 02/06/2026 | H13: 13936.94 | I13: Pesos (MXN) | J13: 1 | K13: 13936.94 | L13: PANTALON PARA DESPACHADORES AZUL 32 | N13: 357.22 | R13: ALMACEN | S13: Uniformes | T13: PANTALONES | U13: E000000270 | V13: 73174 | X13: 60046 | Z13: Diego Alejandro Estrada Ramos | AE13: PAGADA | AF13: Estatus Surtido | AG13: FAVOR DE ENTREGAR EN CEDIS CULIACAN CON DIEGO. PANTALON DESPACHADOR AZUL PARA STOCK DE ZONA CLN, ANGOSTURA Y NORTE. | AH13: 12,145.48 | AI13: 0.00 | AJ13: 1,943.28 | AK13: 0.00 | AL13: 13,936.94 | AM13: 20101021501 | AN13: 12101030000 | AO13: 22201020000 | AP13: 20101021500
A14: PETROPLAZAS | B14: CEDIS Culiacán | C14: GABRIELA DE JESUS RAMIREZ LOAIZA | D14: B0C2F997 | E14: 01/06/2026 | F14: 02/06/2026 | G14: 02/06/2026 | H14: 13238.48 | I14: Pesos (MXN) | J14: 1 | K14: 13238.48 | L14: PANTALON PARA DESPACHADORES AZUL 40 | N14: 384.56 | R14: ALMACEN | S14: Uniformes | T14: PANTALONES | U14: E000000271 | V14: 73179 | X14: 60048 | Z14: Diego Alejandro Estrada Ramos | AE14: PAGADA | AF14: Estatus Surtido | AG14: FAVOR DE ENTREGAR EN CEDIS CULIACAN CON DIEGO. PANTALON DESPACHADOR AZUL PARA STOCK DE ZONA CLN, ANGOSTURA Y NORTE. | AH14: 11,536.80 | AI14: 0.00 | AJ14: 1,845.89 | AK14: 0.00 | AL14: 13,238.48 | AM14: 20101021501 | AN14: 12101030000 | AO14: 22201020000 | AP14: 20101021500
A15: PETROPLAZAS | B15: Revolucion | C15: ARTURO TRINIDAD SANDOVAL GONZALEZ | D15: A1549 | E15: 02/06/2026 | F15: 03/06/2026 | G15: 03/06/2026 | H15: 2366.4 | I15: Pesos (MXN) | J15: 1 | K15: 2366.4 | L15: JALADOR DE AGUA DE PISO | N15: 185 | R15: ALMACEN | S15: Artículos de Limpieza | T15: Artículos de Limpieza | U15: E000000153 | V15: 73297 | W15: 66450 | X15: 60303 | Y15: OPERACIONES GASOLINERAS | Z15: Diego Alejandro Estrada Ramos | AA15: ES_Revolucion | AB15: Baños publicos | AE15: PAGADA | AF15: Baños publicos | AG15: FAVOR DE ENTREGAR EN ESTACION REVOLUCION CON EL SUPERVISOR AL DOMICILIO BLVD. LUIS DONAL. COLOSIO NO. 615, COL. REVOLUCION MEXICANA, GUASAVE, SINALOA, C.P. 81016. MATERIAL DE LIMPIEZA DEL MES DE JUNIO 2026. | AH15: 2,040.00 | AI15: 0.00 | AJ15: 326.40 | AK15: 0.00 | AL15: 2,366.40 | AM15: 20101021501 | AN15: 12101030000 | AO15: 20101021500
A16: PETROPLAZAS | B16: CEDIS Culiacán | C16: JOSHUA ALBERTO TIRADO ROMERO | D16: CCCEC | E16: 03/06/2026 | F16: 03/06/2026 | G16: 03/06/2026 | H16: 19200 | I16: Pesos (MXN) | J16: 1 | K16: 19200 | L16: SERVICIO DE INTERNET | M16: 1 | N16: 4137.93 | P16: 4137.93 | Q16: 4137.93 | R16: SERVICIO | S16: Servicios | T16: Servicios | U16: SRV0000460 | V16: 73405 | W16: 66616 | X16: 60423 | Y16: INFRAESTRUCTURA TECNOLOGICA | Z16: JUAN CARLOS MORENO OSUNA | AA16: PERICOS | AB16: PERICOS | AE16: PAGADA | AF16: CUAUHTEMOC | AG16: SERVICIO RED JOSHUA SITIO CULIACAN, JUNIO 2026 | AH16: 16,551.72 | AI16: 0.00 | AJ16: 2,648.28 | AK16: 0.00 | AL16: 19,200.00 | AM16: 50299040042 | AN16: 12101030000 | AO16: 20101021500
A17: PETROPLAZAS | B17: La Colorada | C17: PETRO SMART COMBUSTIBLES, S.A. DE C.V. | D17: GHMO004237 | E17: 01/06/2026 | F17: 03/06/2026 | G17: 03/06/2026 | H17: 1277.48 | I17: Pesos (MXN) | J17: 1 | K17: 1277.48 | L17: GAS LP | M17: 115.4002 | N17: 9.5431 | P17: 1101.27564862 | Q17: 1101.275649 | R17: SERVICIO | S17: Gastos diversos | T17: Varios (Gastos Diversos) | U17: SRV0000194 | V17: 73339 | W17: 66537 | X17: 60372 | Y17: COMPRAS | Z17: HUGO JAIME LIZARRAGA CARRILLO | AA17: ES_LA_COLORADA | AB17: ESTACION LA COLORADA | AE17: PAGADA | AF17: ESTACION LA COLORADA | AG17: CORRESPONDE A LA FACTURA GHMO004237. SERVICIO DE GAS LP PARA AREA DE PENSION DE ESTACION LA COLORADA. | AH17: 1,101.28 | AI17: 0.00 | AJ17: 176.20 | AK17: 0.00 | AL17: 1,277.48 | AM17: 50299040017 | AN17: 12101030000 | AO17: 20101021500
A18: PETROPLAZAS | B18: Forjadores | C18: JOSHUA ALBERTO TIRADO ROMERO | D18: 72C4F | E18: 03/06/2026 | F18: 03/06/2026 | G18: 03/06/2026 | H18: 4800 | I18: Pesos (MXN) | J18: 1 | K18: 4800 | L18: SERVICIO DE INTERNET | M18: 1 | N18: 4137.93 | P18: 4137.93 | Q18: 4137.93 | R18: SERVICIO | S18: Servicios | T18: Servicios | U18: SRV0000296 | V18: 73407 | W18: 66620 | X18: 60427 | Y18: INFRAESTRUCTURA TECNOLOGICA | Z18: JUAN CARLOS MORENO OSUNA | AA18: ES_FORJADORES | AB18: D. ADMINISTRACION | AE18: PAGADA | AF18: D. ADMINISTRACION | AG18: SERVICIO RED JOSHUA SITIO PAZ, JUNIO 2026 | AH18: 4,137.93 | AI18: 0.00 | AJ18: 662.07 | AK18: 0.00 | AL18: 4,800.00 | AM18: 50299040042 | AN18: 12101030000 | AO18: 20101021500
A19: PETROPLAZAS | B19: SANTA ROSA | C19: Operadora Polar SA de CV | D19: MZF445034 | E19: 01/06/2026 | F19: 03/06/2026 | G19: 03/06/2026 | H19: 676.05 | I19: Pesos (MXN) | J19: 1 | K19: 676.05 | L19: BOLSA TRANSPARENTE 18 CMS X 26 CMS (CAPACIDAD 1 KG) | N19: 59 | R19: ALMACEN | S19: Gastos diversos | T19: Varios (Gastos Diversos) | U19: E000000138 | V19: 73250 | W19: 66217 | X19: 60174 | Y19: OPERACIONES GASOLINERAS | Z19: Maria Isabel Vega Gaxiola | AA19: ES_SANTA_ROSA | AB19: BAÑOS AL PÚBLICO | AE19: PAGADA | AF19: BAÑOS AL PÚBLICO | AG19: FAVOR DE ENTREGAR EN ESTACION SANTA ROSA CON EL SUPERVISOR. MATERIAL DE LIMPIEZA DEL MES DE JUNIO 2026. | AH19: 582.80 | AI19: 0.00 | AJ19: 93.25 | AK19: 0.00 | AL19: 676.05 | AM19: 50299040042 | AN19: 12101030000 | AO19: 20101021500
A20: PETROPLAZAS | B20: CEDIS Mazatlán | C20: DIANA ANGELICA LOPEZ MACHADO | D20: 20251611 | E20: 01/06/2026 | F20: 03/06/2026 | G20: 03/06/2026 | H20: 17121.6 | I20: Pesos (MXN) | J20: 1 | K20: 17121.6 | L20: PANTALON DE VESTIR CABALLERO 36 X 32 | N20: 369 | R20: ALMACEN | S20: Uniformes | T20: PANTALONES | U20: E000000461 | V20: 73167 | X20: 59973 | Z20: Maria Isabel Vega Gaxiola | AE20: PAGADA | AF20: Estatus Surtido | AG20: FAVOR DE ENTREGAR EN CEDIS MAZATLAN CON ISABEL. PANTALON DE VESTIR CABALLERO AZUL MARINO PARA STOCK DE CEDIS MAZATLAN. | AH20: 14,760.00 | AI20: 0.00 | AJ20: 2,361.60 | AK20: 0.00 | AL20: 17,121.60 | AM20: 20101021501 | AN20: 12101030000 | AO20: 20101021500
A21: PETROPLAZAS | B21: CEDIS Mazatlán | C21: HEAT COMMERCIAL S.A. DE C.V. | D21: F68961 | E21: 03/06/2026 | F21: 03/06/2026 | G21: 03/06/2026 | H21: 3990.4 | I21: Pesos (MXN) | J21: 1 | K21: 3990.4 | L21: GORRA AMARILLA/REY PARA DESPACHADORES (LOGO REDPETROIL) | N21: 43 | R21: ALMACEN | S21: Uniformes | T21: Gorra | U21: E000000462 | V21: 73372 | X21: 59972 | Z21: Maria Isabel Vega Gaxiola | AE21: PAGADA | AF21: Estatus Surtido | AG21: FAVOR DE ENTREGAR EN CEDIS MAZATLAN CON ISABEL AL DOMICILIO AZALEA NO. 4901, COL. RICARDO FLORES MAGON, C.P. 82190, MAZATLAN, SINALOA. GORRA ACRILANA AMARILLO / REY C/BORDADO FTE REDPETROIL PARA STOCK DE CEDIS MAZATLAN PARA ESTACIONES SABALO, AEROPUERTO, CONCORDIA, HABAL, 12 DE MAYO, FORESTA, URBIVILLA, GRIJALVA, ROSARIO Y ESCUINAPA. | AH21: 3,440.00 | AI21: 0.00 | AJ21: 550.40 | AK21: 0.00 | AL21: 3,990.40 | AM21: 20101021501 | AN21: 12101030000 | AO21: 20101021500
A22: PETROPLAZAS | B22: SANTA ROSA | C22: JORGE LUIS LIZARRAGA GARATE | D22: BCR672 | E22: 01/06/2026 | F22: 03/06/2026 | G22: 03/06/2026 | H22: 503.11 | I22: Pesos (MXN) | J22: 1 | K22: 503.11 | L22: AROMATIZANTE PARA PISO | N22: 13.2145 | R22: ALMACEN | S22: Artículos de Limpieza | T22: Artículos de Limpieza | U22: E000000139 | V22: 73252 | W22: 66217 | X22: 60174 | Y22: OPERACIONES GASOLINERAS | Z22: Maria Isabel Vega Gaxiola | AA22: ES_SANTA_ROSA | AB22: BAÑOS AL PÚBLICO | AE22: PAGADA | AF22: BAÑOS AL PÚBLICO | AG22: FAVOR DE ENTREGAR EN ESTACION SANTA ROSA CON EL SUPERVISOR. MATERIAL DE LIMPIEZA DEL MES DE JUNIO 2026. | AH22: 438.44 | AI22: 0.00 | AJ22: 70.15 | AK22: 0.00 | AL22: 503.11 | AM22: 20101021501 | AN22: 12101030000 | AO22: 22201020000 | AP22: 20101021500
A23: PETROPLAZAS | B23: Alamos | C23: Jose Carmen Montaño Aramburo | D23: FDF0430176 | E23: 01/06/2026 | F23: 03/06/2026 | G23: 03/06/2026 | H23: 636.84 | I23: Pesos (MXN) | J23: 1 | K23: 636.84 | L23: CARGADOR PARA LAPTOP | N23: 549 | R23: ALMACEN | S23: Equipo de Computo | T23: Accesorios de cómputo | U23: E000000128 | V23: 73301 | W23: 65562 | X23: 59484 | Y23: OPERACIONES | Z23: Diego Alejandro Estrada Ramos | AA23: CC Empleados | AB23: CC Jose Carlos Valdez Nuñez | AE23: PAGADA | AF23: CC Jose Carlos Valdez Nuñez | AG23: FAVOR DE ENTREGAR EN CEDIS MAZATLAN CON ISABEL. CARGADOR LENOVO ADL45WCC PARA LAPTOP LENOVO IDEAPAD 320 DE ING. JOSE CARLOS JEFE DE PISO ZONA NORTE. | AH23: 549.00 | AI23: 0.00 | AK23: 0.00 | AL23: 549.00 | AM23: 20101021501 | AN23: 12101030000 | AO23: 20101021500
A24: PETROPLAZAS | B24: Sabalo | C24: Electrica Valdez SA de CV | D24: M00646285 | E24: 01/06/2026 | F24: 03/06/2026 | G24: 03/06/2026 | H24: 4654.85 | I24: Pesos (MXN) | J24: 1 | K24: 4654.85 | L24: CABLE USO RUDO 3 X 12 | N24: 40.128 | R24: ALMACEN | S24: Herramientas y Utiles | T24: Cables | U24: E000000207 | V24: 73337 | W24: 66527 | X24: 60358 | Y24: COMPRAS | Z24: Maria Isabel Vega Gaxiola | AA24: ES_Sabalo | AB24: CC OPERACIONES | AC24: 0 | AE24: PAGADA | AF24: CC OPERACIONES | AG24: CORRESPONDE A LA FACTURA M-00646285. MATERIAL ELECTRICO PARA ESTACION SABALO. | AH24: 4,012.80 | AI24: 0.00 | AJ24: 642.05 | AK24: 0.00 | AL24: 4,654.85 | AM24: 20101021501 | AN24: 12101030000 | AO24: 20101021500
A25: PETROPLAZAS | B25: SANTA ROSA | C25: Operadora Polar SA de CV | D25: MZF445096 | E25: 02/06/2026 | F25: 03/06/2026 | G25: 03/06/2026 | H25: 435 | I25: Pesos (MXN) | J25: 1 | K25: 435 | L25: EMPLAYE TRANSPARENTE | N25: 125 | R25: ALMACEN | S25: Ferreteria | T25: Ferreteria | U25: E000000141 | V25: 73377 | W25: 66553 | X25: 60378 | Y25: OPERACIONES GASOLINERAS | Z25: Maria Isabel Vega Gaxiola | AA25: ES_SANTA_ROSA | AB25: CC OPERACIONES | AC25: 0 | AE25: PAGADA | AF25: CC OPERACIONES | AG25: CORRESPONDE A LA FACTURA MZF445096. EMPLAYE PARA ESTACION SANTA ROSA. | AH25: 375.00 | AI25: 0.00 | AJ25: 60.00 | AK25: 0.00 | AL25: 435.00 | AM25: 20101021501 | AN25: 12101030000 | AO25: 20101021500
A26: PETROPLAZAS | B26: La Foresta | C26: Operadora Polar SA de CV | D26: MZF445025 | E26: 01/06/2026 | F26: 03/06/2026 | G26: 03/06/2026 | H26: 1912.61 | I26: Pesos (MXN) | J26: 1 | K26: 1912.61 | L26: BOLSA DE CAMISETA JUMBO | N26: 41 | R26: ALMACEN | S26: Artículos de Limpieza | T26: Artículos de Limpieza | U26: E000000180 | V26: 73253 | W26: 66249 | X26: 60165 | Y26: OPERACIONES | Z26: Maria Isabel Vega Gaxiola | AA26: ES_La Foresta | AB26: CC OPERACIONES | AC26: 0 | AE26: PAGADA | AF26: CC OPERACIONES | AG26: FAVOR DE ENTREGAR EN ESTACION FORESTA CON EL SUPERVISOR. MATERIAL DE LIMPIEZA DEL MES DE JUNIO 2026. | AH26: 1,648.80 | AI26: 0.00 | AJ26: 263.81 | AK26: 0.00 | AL26: 1,912.61 | AM26: 20101021501 | AN26: 12101030000 | AO26: 20101021500
A27: PETROPLAZAS | B27: Fatima | C27: ARTURO TRINIDAD SANDOVAL GONZALEZ | D27: A1551 | E27: 02/06/2026 | F27: 03/06/2026 | G27: 03/06/2026 | H27: 2619.28 | I27: Pesos (MXN) | J27: 1 | K27: 2619.28 | L27: AROMATIZANTE PARA PISO | N27: 19.5 | R27: ALMACEN | S27: Artículos de Limpieza | T27: Artículos de Limpieza | U27: E000000123 | V27: 73293 | W27: 66451 | X27: 60306 | Y27: OPERACIONES GASOLINERAS | Z27: Diego Alejandro Estrada Ramos | AA27: ES_Fatima | AB27: Baños publicos | AE27: PAGADA | AF27: Baños publicos | AG27: FAVOR DE ENTREGAR EN ESTACION FATIMA CON EL SUPERVISOR AL DOMICILIO ANGEL FLORES NTE. 983 COL. CENTRO, AHOME LOS MOCHIS, SINALOA, C.P. 81200. MATERIAL DE LIMPIEZA DEL MES DE JUNIO 2026. | AH27: 2,258.00 | AI27: 0.00 | AJ27: 361.28 | AK27: 0.00 | AL27: 2,619.28 | AM27: 20101021501 | AN27: 12101030000 | AO27: 20101021500
A28: PETROPLAZAS | B28: Alamos | C28: ARTURO TRINIDAD SANDOVAL GONZALEZ | D28: A1550 | E28: 02/06/2026 | F28: 03/06/2026 | G28: 03/06/2026 | H28: 2729.48 | I28: Pesos (MXN) | J28: 1 | K28: 2729.48 | L28: PAPEL HIGIENICO JUMBO BLANCO | N28: 32 | R28: ALMACEN | S28: Artículos de Limpieza | T28: Artículos de Limpieza | U28: E000000130 | V28: 73289 | W28: 66435 | X28: 60257 | Y28: OPERACIONES GASOLINERAS | Z28: Diego Alejandro Estrada Ramos | AA28: ES_Alamos | AB28: Baños publicos | AE28: PAGADA | AF28: Baños publicos | AG28: FAVOR DE ENTREGAR EN ESTACION ALAMOS CON EL SUPERVISOR AL DOMICILIO BLVD. MACARIO GAXIOLA NO. 1500 SUR, FRACC. LOS ALAMOS 1, AHOME LOS MOCHIS, SINALOA, C.P. 81280. MATERIAL DE LIMPIEZA DEL MES DE JUNIO 2026. | AH28: 2,353.00 | AI28: 0.00 | AJ28: 376.48 | AK28: 0.00 | AL28: 2,729.48 | AM28: 20101021501 | AN28: 12101030000 | AO28: 20101021500
A29: PETROPLAZAS | B29: Petroplazas Corporativo | C29: JOSHUA ALBERTO TIRADO ROMERO | D29: 2C6A1 | E29: 03/06/2026 | F29: 03/06/2026 | G29: 03/06/2026 | H29: 3712 | I29: Pesos (MXN) | J29: 1 | K29: 3712 | L29: SERVICIO DE INTERNET | M29: 1 | N29: 3200 | P29: 3200 | Q29: 3200 | R29: SERVICIO | S29: Servicios | T29: Servicios | U29: SRV0005508 | V29: 73406 | W29: 66619 | X29: 60426 | Y29: INFRAESTRUCTURA TECNOLOGICA | Z29: JUAN CARLOS MORENO OSUNA | AA29: ES_Corporativo | AB29: CC Administracion | AE29: PAGADA | AF29: CC Administracion | AG29: SERVICIO RED JOSHUA SITIO NAS, JUNIO 2026 | AH29: 3,200.00 | AI29: 0.00 | AJ29: 512.00 | AK29: 0.00 | AL29: 3,712.00 | AM29: 50299040042 | AN29: 12101030000 | AO29: 20101021500
A30: PETROPLAZAS | B30: ALHUEY1 | C30: Equipos Industriales del Noroeste SA de CV | D30: FC26295 | E30: 02/06/2026 | F30: 03/06/2026 | G30: 03/06/2026 | H30: 1025.97 | I30: Pesos (MXN) | J30: 1 | K30: 1025.97 | L30: Palanca de mecanismo | N30: 294.82 | R30: ALMACEN | S30: Gastos diversos | T30: Varios (Gastos Diversos) | U30: E000000195 | V30: 73211 | W30: 61685 | X30: 56134 | Y30: OPERACIONES | Z30: Diego Alejandro Estrada Ramos | AA30: ES_ALHUEY1 | AB30: Estacion Alhuey 1 | AE30: PAGADA | AF30: Estacion Alhuey 1 | AG30: COMPRA DE 3 PATITAS (FUSIBLE) PARA VALVULA SHUT OFF PARA ESTACION ALHUEY 1. (ENTREGAR EN ALMACEN DE REFACCIONES DE CAMPO EL DIEZ). Y FACTURAR CON 1 DE JUNIO. | AH30: 884.46 | AI30: 0.00 | AJ30: 141.51 | AK30: 0.00 | AL30: 1,025.97 | AM30: 20101021501 | AN30: 12101030000 | AO30: 20101021500
A31: PETROPLAZAS | B31: Dos Valles | C31: ARTURO TRINIDAD SANDOVAL GONZALEZ | D31: A1548 | E31: 02/06/2026 | F31: 03/06/2026 | G31: 03/06/2026 | H31: 1137.96 | I31: Pesos (MXN) | J31: 1 | K31: 1137.96 | L31: CEPILLO PARA WC CON BASE | N31: 85 | R31: ALMACEN | S31: Artículos de Limpieza | T31: Artículos de Limpieza | U31: E000000131 | V31: 73295 | W31: 66415 | X31: 60262 | Y31: OPERACIONES | Z31: Diego Alejandro Estrada Ramos | AA31: ES_Dos Valles | AB31: Baños publicos | AE31: PAGADA | AF31: Baños publicos | AG31: FAVOR DE ENTREGAR EN ESTACION DOS VALLE CON EL SUPERVISOR AL DOMICILIO BLVD. LUIS DONALDO COLOSIO NO. 264, COL. OCORO, GUASAVE, SINALOA, C.P. 81010. MATERIAL DE LIMPIEZA DEL MES DE JUNIO 2026. | AH31: 981.00 | AI31: 0.00 | AJ31: 156.96 | AK31: 0.00 | AL31: 1,137.96 | AM31: 20101021501 | AN31: 12101030000 | AO31: 20101021500
A32: PETROPLAZAS | B32: Fatima | C32: GISELA AGGLAE MARQUEZ VILLEGAS | D32: 7659F | E32: 02/06/2026 | F32: 03/06/2026 | G32: 03/06/2026 | H32: 5612.5 | I32: Pesos (MXN) | J32: 1 | K32: 5612.5 | L32: BLACKVIEW BV5500 PLUS | N32: 4838.36 | R32: ALMACEN | S32: Equipo de Computo | T32: Accesorios Comunicaciones | U32: E000000121 | V32: 73163 | W32: 66140 | X32: 60268 | Y32: OPERACIONES GASOLINERAS | Z32: Diego Alejandro Estrada Ramos | AA32: ES_Fatima | AB32: Zona de despacho | AE32: PAGADA | AF32: Zona de despacho | AG32: FAVOR DE ENTREGAR EN CEDIS MAZATLAN CON ISABEL. EQUIPO CUBOT KINGKONG PARA ESTACION FATIMA. | AH32: 4,838.36 | AI32: 0.00 | AJ32: 774.14 | AK32: 0.00 | AL32: 5,612.50 | AM32: 20101021501 | AN32: 12101030000 | AO32: 20101021500
A33: PETROPLAZAS | B33: CERRITOS | C33: Jose Carmen Montaño Aramburo | D33: A62F830168 | E33: 01/06/2026 | F33: 03/06/2026 | G33: 03/06/2026 | H33: 1738.84 | I33: Pesos (MXN) | J33: 1 | K33: 1738.84 | L33: Abanico | N33: 1499 | R33: ALMACEN | S33: Equipo de Transporte | T33: Sistema de Enfriamiento | U33: E000000197 | V33: 73145 | W33: 66214 | X33: 60158 | Y33: OPERACIONES | Z33: Maria Isabel Vega Gaxiola | AA33: ES_Cerritos | AB33: A. BAÑOS AL PUBLICO | AE33: PAGADA | AF33: A. BAÑOS AL PUBLICO | AG33: COMPRA POR VENTILADOR MYTEK DE PARED 20” SOLICITADO PARA ESTACION CERRITOS Nota: Facturar a inicios de junio y Uso de cfdi gastos en general. ENTREGAR EN CEDIS MAZATLAN CON ISABEL VEGA. | AH33: 1,499.00 | AI33: 0.00 | AJ33: 239.84 | AK33: 0.00 | AL33: 1,738.84 | AM33: 20101021501 | AN33: 12101030000 | AO33: 20101021500
A34: PETROPLAZAS | B34: AEROPUERTO | C34: JOHAN AGUILAR VIZCARRA | D34: A16653 | E34: 01/06/2026 | F34: 03/06/2026 | G34: 03/06/2026 | H34: 16646 | I34: Pesos (MXN) | J34: 1 | K34: 16646 | L34: BLUE HD ANTICONTAMINANTE PARA MOTOR DIESEL | N34: 287 | R34: ALMACEN | S34: Aceite y Lubricantes | T34: Aceite | U34: E000000284 | V34: 73360 | W34: 66511 | X34: 60350 | Y34: OPERACIONES | Z34: Maria Isabel Vega Gaxiola | AA34: ES_Aeropuerto | AB34: ESTACION AEROPUERTO | AE34: PAGADA | AF34: ESTACION AEROPUERTO | AG34: PAGO A FACT. A 16653 POR 50 KIT DE UREAS SOLICITADOS PAR PUNTO DE VENTA ESTACION AEROPUERTO, JUNIO 2026. PROGRAMAR A PAGO EL 04/06/2026 | AH34: 14,350.00 | AI34: 0.00 | AJ34: 2,296.00 | AK34: 0.00 | AL34: 16,646.00 | AM34: 20101021501 | AN34: 12101030000 | AO34: 20101021500
A35: PETROPLAZAS | B35: MUNICH II | C35: GISELA AGGLAE MARQUEZ VILLEGAS | D35: 62932 | E35: 02/06/2026 | F35: 03/06/2026 | G35: 03/06/2026 | H35: 5612.5 | I35: Pesos (MXN) | J35: 1 | K35: 5612.5 | L35: BLACKVIEW BV5500 PLUS | N35: 4838.36 | R35: ALMACEN | S35: Equipo de Computo | T35: Accesorios Comunicaciones | U35: E000000175 | V35: 73148 | W35: 66248 | X35: 60251 | Y35: OPERACIONES GASOLINERAS | Z35: Maria Isabel Vega Gaxiola | AA35: ES_MunichII | AB35: A. ZONA DE DESPACHO | AE35: PAGADA | AF35: A. ZONA DE DESPACHO | AG35: FAVOR DE ENTREGAR EN CEDIS MAZATLAN CON ISABEL. EQUIPO CUBOT KINGKONG ES 3 PARA ESTACION MUNICH II. | AH35: 4,838.36 | AI35: 0.00 | AJ35: 774.14 | AK35: 0.00 | AL35: 5,612.50 | AM35: 20101021501 | AN35: 12101030000 | AO35: 20101021500
A36: PETROPLAZAS | B36: Sabalo | C36: Kuroda Plomeria y Azulejos SA de CV | D36: FIA177489 | E36: 01/06/2026 | F36: 03/06/2026 | G36: 03/06/2026 | H36: 1099 | I36: Pesos (MXN) | J36: 1 | K36: 1099 | L36: TAZA DE BAÑO WC CON TANQUE | N36: 947.41 | R36: ALMACEN | S36: Gastos diversos | T36: Varios (Gastos Diversos) | U36: E000000204 | V36: 73286 | W36: 65500 | X36: 60233 | Y36: OPERACIONES GASOLINERAS | Z36: Maria Isabel Vega Gaxiola | AA36: ES_Sabalo | AB36: CC OPERACIONES | AC36: 0 | AE36: PAGADA | AF36: CC OPERACIONES | AG36: COMPRA POR WC BLANCO AHORRADOR REDONDO MODELO ECO ACUACER SOLICITADO PARA ESTACION SABALO, JUNIO 2026. ENTREGAR EN CEDIS MAZATLAN (almacen flores magon) CON ISABEL VEGA. | AH36: 947.41 | AI36: 0.00 | AJ36: 151.59 | AK36: 0.00 | AL36: 1,099.00 | AM36: 20101021501 | AN36: 12101030000 | AO36: 20101021500
A37: PETROPLAZAS | B37: Sabalo | C37: Jose Carmen Montaño Aramburo | D37: B5E1530167 | E37: 01/06/2026 | F37: 03/06/2026 | G37: 03/06/2026 | H37: 3477.68 | I37: Pesos (MXN) | J37: 1 | K37: 3477.68 | L37: Abanico | N37: 1499 | R37: ALMACEN | S37: Equipo de Transporte | T37: Sistema de Enfriamiento | U37: E000000203 | V37: 73142 | X37: 60249 | Z37: Maria Isabel Vega Gaxiola | AE37: PAGADA | AF37: Estatus Surtido | AG37: COMPRA POR 2 VENTILADORES MYTEK DE PARED 20” SOLICITADOS PARA ESTACION SABALO, Nota, facturar a inicios de junio y uso de cfdi gastos en general. ENTREGAR EN CEDIS MAZATLAN CON ISABEL VEGA. | AH37: 2,998.00 | AI37: 0.00 | AJ37: 479.68 | AK37: 0.00 | AL37: 3,477.68 | AM37: 20101021501 | AN37: 12101030000 | AO37: 20101021500
A38: PETROPLAZAS | B38: URBIVILLA | C38: JORGE LUIS LIZARRAGA GARATE | D38: BCR674 | E38: 01/06/2026 | F38: 04/06/2026 | G38: 04/06/2026 | H38: 721.87 | I38: Pesos (MXN) | J38: 1 | K38: 721.87 | L38: BOLSA NEGRA JUMBO | N38: 35.84 | R38: ALMACEN | S38: Artículos de Limpieza | T38: Artículos de Limpieza | U38: E000000083 | V38: 73264 | W38: 66215 | X38: 60177 | Y38: OPERACIONES GASOLINERAS | Z38: Maria Isabel Vega Gaxiola | AA38: URBIVILLA | AB38: ESTACION URBIVILLA | AE38: PAGADA | AF38: ESTACION URBIVILLA | AG38: FAVOR DE ENTREGAR EN ESTACION URBIVILLA CON EL SUPERVISOR. MATERIAL DE LIMPIEZA DEL MES DE JUNIO 2026. AROMATIZANTE BRISA DE MAR | AH38: 629.08 | AI38: 0.00 | AJ38: 100.65 | AK38: 0.00 | AL38: 721.87 | AM38: 20101021501 | AN38: 12101030000 | AO38: 22201020000 | AP38: 20101021500
A39: PETROPLAZAS | B39: 12 de Mayo | C39: Operadora Polar SA de CV | D39: MZF445030 | E39: 01/06/2026 | F39: 04/06/2026 | G39: 04/06/2026 | H39: 1995.43 | I39: Pesos (MXN) | J39: 1 | K39: 1995.43 | L39: PASTILLA AROMATIZANTE PARA BAÑO | N39: 10.8 | R39: ALMACEN | S39: Artículos de Limpieza | T39: Artículos de Limpieza | U39: E000000168 | V39: 73257 | W39: 66301 | X39: 60151 | Y39: OPERACIONES | Z39: Maria Isabel Vega Gaxiola | AA39: ES_12 de Mayo | AB39: BAÑOS ESTACION | AE39: PAGADA | AF39: BAÑOS ESTACION | AG39: FAVOR DE ENTREGAR EN ESTACION 12 DE MAYO CON EL SUPERVISOR. MATERIAL DE LIMPIEZA DEL MES DE JUNIO 2026. | AH39: 1,720.20 | AI39: 0.00 | AJ39: 275.23 | AK39: 0.00 | AL39: 1,995.43 | AM39: 20101021501 | AN39: 12101030000 | AO39: 20101021500
A40: PETROPLAZAS | B40: URBIVILLA | C40: Operadora Polar SA de CV | D40: MZF445026 | E40: 01/06/2026 | F40: 04/06/2026 | G40: 04/06/2026 | H40: 1004.79 | I40: Pesos (MXN) | J40: 1 | K40: 1004.79 | L40: PAPEL HIGIENICO JUMBO BLANCO | N40: 26.4333 | R40: ALMACEN | S40: Artículos de Limpieza | T40: Artículos de Limpieza | U40: E000000082 | V40: 73263 | W40: 66215 | X40: 60177 | Y40: OPERACIONES GASOLINERAS | Z40: Maria Isabel Vega Gaxiola | AA40: URBIVILLA | AB40: ESTACION URBIVILLA | AE40: PAGADA | AF40: ESTACION URBIVILLA | AG40: FAVOR DE ENTREGAR EN ESTACION URBIVILLA CON EL SUPERVISOR. MATERIAL DE LIMPIEZA DEL MES DE JUNIO 2026. | AH40: 866.20 | AI40: 0.00 | AJ40: 138.59 | AK40: 0.00 | AL40: 1,004.79 | AM40: 20101021501 | AN40: 12101030000 | AO40: 20101021500
A41: PETROPLAZAS | B41: Flores Magon | C41: Operadora Polar SA de CV | D41: MZF445027 | E41: 01/06/2026 | F41: 04/06/2026 | G41: 04/06/2026 | H41: 2052.97 | I41: Pesos (MXN) | J41: 1 | K41: 2052.97 | L41: PASTILLA AROMATIZANTE PARA BAÑO | N41: 10.8 | R41: ALMACEN | S41: Artículos de Limpieza | T41: Artículos de Limpieza | U41: E000000436 | V41: 73255 | W41: 66199 | X41: 60161 | Y41: OPERACIONES GASOLINERAS | Z41: Maria Isabel Vega Gaxiola | AA41: ES_Flores Magon | AB41: BAÑOS ESTACION | AE41: PAGADA | AF41: BAÑOS ESTACION | AG41: FAVOR DE ENTREGAR EN ESTACION FLORES MAGON CON EL SUPERVISOR. MATERIAL DE LIMPIEZA DEL MES DE JUNIO 2026. | AH41: 1,769.80 | AI41: 0.00 | AJ41: 283.17 | AK41: 0.00 | AL41: 2,052.97 | AM41: 20101021501 | AN41: 12101030000 | AO41: 20101021500
A42: PETROPLAZAS | B42: GRIJALVA | C42: Operadora Polar SA de CV | D42: MZF445032 | E42: 01/06/2026 | F42: 04/06/2026 | G42: 04/06/2026 | H42: 1025.44 | I42: Pesos (MXN) | J42: 1 | K42: 1025.44 | L42: CLORO | N42: 9 | R42: ALMACEN | S42: Artículos de Limpieza | T42: Artículos de Limpieza | U42: E000000156 | V42: 73272 | W42: 66305 | X42: 60224 | Y42: OPERACIONES GASOLINERAS | Z42: Maria Isabel Vega Gaxiola | AA42: GRIJALVA | AB42: ESTACION GRIJAVA | AE42: PAGADA | AF42: ESTACION GRIJAVA | AG42: FAVOR DE ENTREGAR EN ESTACION GRIJALVA CON EL SUPERVISOR. MATERIAL DE LIMPIEZA DEL MES DE JUNIO 2026. | AH42: 884.00 | AI42: 0.00 | AJ42: 141.44 | AK42: 0.00 | AL42: 1,025.44 | AM42: 20101021501 | AN42: 12101030000 | AO42: 20101021500
A43: PETROPLAZAS | B43: 12 de Mayo | C43: JORGE LUIS LIZARRAGA GARATE | D43: BCR673 | E43: 01/06/2026 | F43: 04/06/2026 | G43: 04/06/2026 | H43: 1644.17 | I43: Pesos (MXN) | J43: 1 | K43: 1644.17 | L43: CLORO | N43: 9.94 | R43: ALMACEN | S43: Artículos de Limpieza | T43: Artículos de Limpieza | U43: E000000169 | V43: 73258 | W43: 66301 | X43: 60151 | Y43: OPERACIONES | Z43: Maria Isabel Vega Gaxiola | AA43: ES_12 de Mayo | AB43: BAÑOS ESTACION | AE43: PAGADA | AF43: BAÑOS ESTACION | AG43: FAVOR DE ENTREGAR EN ESTACION 12 DE MAYO CON EL SUPERVISOR. MATERIAL DE LIMPIEZA DEL MES DE JUNIO 2026. | AH43: 1,432.82 | AI43: 0.00 | AJ43: 229.25 | AK43: 0.00 | AL43: 1,644.16 | AM43: 20101021501 | AN43: 12101030000 | AO43: 22201020000 | AP43: 20101021500
A44: PETROPLAZAS | B44: Madero | C44: Uriarte Equipamento Gasolinero, S.a. de C.v. | D44: FAC51010416 | E44: 03/06/2026 | F44: 04/06/2026 | G44: 04/06/2026 | H44: 4700.97 | I44: Pesos (MXN) | J44: 1 | K44: 4700.97 | L44: MANGUERA DE 4" X 4 METROS PARA DESCARGA DE COMBUSTIBLE CON CONEXIONES | N44: 4052.56 | R44: ALMACEN | S44: Conexiones Rapidas | T44: Mangueras | U44: E000000104 | V44: 73213 | W44: 66445 | X44: 60297 | Y44: OPERACIONES | Z44: Diego Alejandro Estrada Ramos | AA44: ES_MADERO | AB44: ZONA DE DESPACHO | AE44: PAGADA | AF44: ZONA DE DESPACHO | AG44: COMPRA DE MANGUERA PARA DESCARGA DE COMBUSTIBLE DE LA ESTACION MADERO. ENTREGAR EN LA ESTACION (BLVD. FRANCISCO I. MADERO 693 PTE. COL. CENTRO, CULIACAN, SIN. C.P. 80000. | AH44: 4,052.56 | AI44: 0.00 | AJ44: 648.41 | AK44: 0.00 | AL44: 4,700.97 | AM44: 20101021501 | AN44: 12101030000 | AO44: 20101021500
A45: PETROPLAZAS | B45: Bellavista | C45: GUADALUPE CARDENAS MANJARREZ | D45: AA10863 | E45: 03/06/2026 | F45: 04/06/2026 | G45: 04/06/2026 | H45: 614.8 | I45: Pesos (MXN) | J45: 1 | K45: 614.8 | L45: PINTURA ESMALTE NEGRO | N45: 265 | R45: ALMACEN | S45: Pinturas y Solventes | T45: Pinturas | U45: E000000094 | V45: 73355 | W45: 65963 | X45: 60261 | Y45: OPERACIONES | Z45: Diego Alejandro Estrada Ramos | AA45: ES_Bellavista | AB45: Estacion BellaVista | AE45: PAGADA | AF45: Estacion BellaVista | AG45: COMPRA DE PINTURA PARA EL MTTO. DE LAS REJILLAS DE TRAMPAS DE LA ESTACION BELLAVISTA. (ENTREGAR EN LA ESTACION EL PAPALOTE, CON UN PAPEL QUE DIGA QUE ES DE BELLAVISTA). | AH45: 530.00 | AI45: 0.00 | AJ45: 84.80 | AK45: 0.00 | AL45: 614.80 | AM45: 20101021501 | AN45: 12101030000 | AO45: 20101021500
A46: PETROPLAZAS | B46: Bellavista | C46: DESARROLLADORA DE PROYECTOS DE GENERACION | D46: 9AD76853 | E46: 02/06/2026 | F46: 04/06/2026 | G46: 04/06/2026 | H46: 8944.04 | I46: Pesos (MXN) | J46: 1 | K46: 8944.04 | L46: SERVICIO/DE PLANTA DE EMERGENCIA | M46: 1 | N46: 7710.38 | P46: 7710.38 | Q46: 7710.38 | R46: SERVICIO | S46: Servicios | T46: Servicios | U46: SRV0000057 | V46: 73060 | W46: 66298 | X46: 60126 | Y46: OPERACIONES | Z46: Pablo Daniel Villa Ortega | AA46: ES_Bellavista | AB46: CUARTO DE MÁQUINAS | AE46: PAGADA | AF46: CUARTO DE MÁQUINAS | AG46: PAGO POR SERVICIO DE MANTENIMIENTO PREVENTIVO A PLANTA DE EMERGENCIA DE ESTACION BELLAVISTA. | AH46: 7,710.38 | AI46: 0.00 | AJ46: 1,233.66 | AK46: 0.00 | AL46: 8,944.04 | AM46: 50299030002 | AN46: 12101030000 | AO46: 20101021500
A47: PETROPLAZAS | B47: Petroplazas Corporativo | C47: JUAN AISPURO INDA | D47: B4765 | E47: 03/06/2026 | F47: 04/06/2026 | G47: 04/06/2026 | H47: 1183.2 | I47: Pesos (MXN) | J47: 1 | K47: 1183.2 | L47: SERVICIO DE IMPRESION | M47: 7 | N47: 145.7143 | P47: 1020.0001 | Q47: 1020.0001 | R47: SERVICIO | S47: Servicios | T47: Servicios | U47: SRV0005509 | V47: 73398 | W47: 66556 | X47: 60415 | Y47: COMPRAS | Z47: HUGO JAIME LIZARRAGA CARRILLO | AA47: ES_Corporativo | AB47: GASTOS GENERALES | AE47: PAGADA | AF47: GASTOS GENERALES | AG47: SERVICIO DE IMPRESION DE ETIQUETAS MAGNA Y PREMIUM PARA ESTACION SANTA MONICA. | AH47: 1,020.00 | AI47: 0.00 | AJ47: 163.20 | AK47: 0.00 | AL47: 1,183.20 | AM47: 50299040036 | AN47: 12101030000 | AO47: 20101021500
A48: PETROPLAZAS | B48: Playas | C48: COMPAÑIA SINALOENSE DE LUBRICANTES, S.A. DE C.V. | D48: MAZAFA600048339 | E48: 01/06/2026 | F48: 04/06/2026 | G48: 04/06/2026 | H48: 36968.23 | I48: Pesos (MXN) | J48: 1 | K48: 36968.23 | L48: ACEITE MULTIGRADO SEMISINTETICO SAE 5W-20 QUAKER STATE XTRA PRO 946 ML. (QS-21210209-1/16) | N48: 106.4513 | R48: ALMACEN | S48: Aceite y Lubricantes | T48: Aceite | U48: E000000230 | V48: 73343 | W48: 66493 | X48: 60373 | Y48: OPERACIONES | Z48: Maria Isabel Vega Gaxiola | AA48: ES_PLAYAS | AB48: CC OPERACIONES | AC48: 0 | AE48: PAGADA | AF48: CC OPERACIONES | AG48: CORRESPONDE A LA FACTURA MAZAFA600048339. ACEITE PARA PUNTO DE VENTA EN ESTACION PLAYAS. | AH48: 31,869.16 | AI48: 0.00 | AJ48: 5,099.07 | AK48: 0.00 | AL48: 36,968.23 | AM48: 20101021501 | AN48: 12101030000 | AO48: 20101021500
A49: PETROPLAZAS | B49: JUAN CARRASCO | C49: JORGE LUIS LIZARRAGA GARATE | D49: BCR679 | E49: 01/06/2026 | F49: 04/06/2026 | G49: 04/06/2026 | H49: 604.84 | I49: Pesos (MXN) | J49: 1 | K49: 604.84 | L49: TAPETE ANTISALPICADURAS PARA MINGITORIO | N49: 41.8 | R49: ALMACEN | S49: Artículos de Limpieza | T49: Artículos de Limpieza | U49: E000000106 | V49: 73275 | W49: 66216 | X49: 60163 | Y49: OPERACIONES GASOLINERAS | Z49: Maria Isabel Vega Gaxiola | AA49: ES_Juan_Carrasco | AB49: A. CUARTO DE LIMPIOS | AE49: PAGADA | AF49: A. CUARTO DE LIMPIOS | AG49: FAVOR DE ENTREGAR EN ESTACION JUAN CARRASCO CON EL SUPERVISOR. MATERIAL DE LIMPIEZA DEL MES DE JUNIO 2026. | AH49: 527.09 | AI49: 0.00 | AJ49: 84.33 | AK49: 0.00 | AL49: 604.83 | AM49: 20101021501 | AN49: 12101030000 | AO49: 22201020000 | AP49: 20101021500
A50: PETROPLAZAS | B50: Fatima | C50: Goldenstar de Mexico, SA de CV | D50: TME357349 | E50: 02/06/2026 | F50: 04/06/2026 | G50: 04/06/2026 | H50: 1174.5 | I50: Pesos (MXN) | J50: 1 | K50: 1174.5 | L50: ROLLO TERMICO BLANCO 80 MM X 70 MM | N50: 13.5 | R50: ALMACEN | S50: PAPELERIA OPERATIVA | T50: PAPELERIA OPERATIVA | U50: E000000125 | V50: 73317 | W50: 66449 | X50: 60307 | Y50: OPERACIONES GASOLINERAS | Z50: Diego Alejandro Estrada Ramos | AA50: ES_Fatima | AB50: Zona de despacho | AE50: PAGADA | AF50: Zona de despacho | AG50: FAVOR DE ENTREGAR EN ESTACION FATIMA CON EL SUPERVISOR AL DOMICILIO ANGEL FLORES NTE. 983 COL. CENTRO, AHOME LOS MOCHIS, SINALOA C.P. 81200. 75 ROLLOS TERMICOS 80X70 DEL MES DE JUNIO 2026 DE ESTACION FATIMA. | AH50: 1,012.50 | AI50: 0.00 | AJ50: 162.00 | AK50: 0.00 | AL50: 1,174.50 | AM50: 20101021501 | AN50: 12101030000 | AO50: 20101021500
A51: PETROPLAZAS | B51: Alamos | C51: Rocio del Carmen Salazar Lopez | D51: CF8052300 | E51: 03/06/2026 | F51: 04/06/2026 | G51: 04/06/2026 | H51: 2293.85 | I51: Pesos (MXN) | J51: 1 | K51: 2293.85 | L51: SILLA EJECUTIVA | N51: 1999 | R51: ALMACEN | S51: Mobiliario y equipo | T51: Mobiliario y equipo | U51: E000000132 | V51: 73009 | W51: 65893 | X51: 59750 | Y51: OPERACIONES GASOLINERAS | Z51: Diego Alejandro Estrada Ramos | AA51: ES_Alamos | AB51: Cuarto de cortes | AE51: PAGADA | AF51: Cuarto de cortes | AG51: FAVOR DE ENTREGAR EN ESTACION ALAMOS CON EL SUPERVISOR AL DOMICILIO AZALEA NO. 4901, COL. RICARDO FLORES MAGON, C.P. 82190, MAZATLAN, SINALOA. SILLA EJECUTIVA PARA CUARTO DE CORTES DE ESTACION ALAMOS. | AH51: 1,999.00 | AI51: 0.00 | AJ51: 319.84 | AK51: 0.00 | AL51: 2,293.85 | AM51: 20101021501 | AN51: 12101030000 | AO51: 22201020000 | AP51: 20101021500
A52: PETROPLAZAS | B52: JUAN CARRASCO | C52: Operadora Polar SA de CV | D52: MZF445033 | E52: 01/06/2026 | F52: 04/06/2026 | G52: 04/06/2026 | H52: 1363.46 | I52: Pesos (MXN) | J52: 1 | K52: 1363.46 | L52: BOLSA DE CAMISETA JUMBO | N52: 41 | R52: ALMACEN | S52: Artículos de Limpieza | T52: Artículos de Limpieza | U52: E000000105 | V52: 73274 | W52: 66216 | X52: 60163 | Y52: OPERACIONES GASOLINERAS | Z52: Maria Isabel Vega Gaxiola | AA52: ES_Juan_Carrasco | AB52: A. CUARTO DE LIMPIOS | AE52: PAGADA | AF52: A. CUARTO DE LIMPIOS | AG52: FAVOR DE ENTREGAR EN ESTACION JUAN CARRASCO CON EL SUPERVISOR. MATERIAL DE LIMPIEZA DEL MES DE JUNIO 2026. | AH52: 1,175.40 | AI52: 0.00 | AJ52: 188.06 | AK52: 0.00 | AL52: 1,363.46 | AM52: 20101021501 | AN52: 12101030000 | AO52: 20101021500
A53: PETROPLAZAS | B53: CEDIS Mazatlán | C53: GIPROSSA SA DE CV | D53: A851A3268 | E53: 02/06/2026 | F53: 04/06/2026 | G53: 04/06/2026 | H53: 6496 | I53: Pesos (MXN) | J53: 1 | K53: 6496 | L53: SERVICIO/DE CONSULTORIA Y ELABORACION DOCUMENTAL EN MATERIA DE LA STPS | M53: 1 | N53: 1400 | P53: 1400 | Q53: 1400 | R53: SERVICIO | S53: Gastos diversos | T53: Varios (Gastos Diversos) | U53: SRV0000605 | V53: 73400 | W53: 66587 | X53: 60406 | Y53: COMPRAS | Z53: Isabel Cristina Chavez Ovalle | AA53: Concordia | AB53: Concordia | AE53: PAGADA | AF53: Aeropuerto 1 | AG53: PAGO A FACT. 3268 POR SERVICIO DE CONSULTORIA Y ELABORACION DOCUMENTAL EN MATERIA DE LA STPS ESTACION HABAL, CARDONES, AEROPUERTO Y CONCORDIA, JUNIO 2026. PROGRAMAR A PAGO EL 11/06/2026 | AH53: 5,600.00 | AI53: 0.00 | AJ53: 896.00 | AK53: 0.00 | AL53: 6,496.00 | AM53: 50299040025 | AN53: 12101030000 | AO53: 20101021500
A54: PETROPLAZAS | B54: El Delfin | C54: ALTA PRECISION Y DISEÑO M&N | D54: 96C8B806 | E54: 03/06/2026 | F54: 04/06/2026 | G54: 04/06/2026 | H54: 14372.4 | I54: Pesos (MXN) | J54: 1 | K54: 14372.4 | L54: CONSTRUCCION - SERVICIO DE CONSTRUCCION | M54: 0.038422 | N54: 322465.28 | P54: 12389.76098816 | Q54: 12389.760988 | R54: SERVICIO | S54: Servicios | T54: Servicios | U54: SRV0000043 | V54: 69796 | W54: 63066 | X54: 57286 | Y54: COMPRAS | Z54: HUGO JAIME LIZARRAGA CARRILLO | AA54: ES_El_Delfin | AB54: CONSTRUCCIÓN INTEGRAL INICIAL DE LA ESTACIÓN DE SERVICIO | AE54: PAGADA | AF54: CONSTRUCCIÓN INTEGRAL INICIAL DE LA ESTACIÓN DE SERVICIO | AG54: SERVICIO DE CONSTRUCCION DE PASILLO EN ESTACION EL DELFIN. CFDI I01 CONSTRUCCION | AH54: 322,465.28 | AI54: 0.00 | AJ54: 51,594.44 | AK54: 0.00 | AL54: 374,059.72 | AM54: _CUA-DRE--000000 | AN54: 12101030000 | AO54: 20101021500 | AP54: 50229040022
A55: PETROPLAZAS | B55: EQUIPO DE COMPUTO | C55: Jose Carmen Montaño Aramburo | D55: E816030178 | E55: 02/06/2026 | F55: 04/06/2026 | G55: 04/06/2026 | H55: 15074.2 | I55: Pesos (MXN) | J55: 1 | K55: 15074.2 | L55: LAPTOP | N55: 12995 | R55: ALMACEN | S55: Equipo de Computo | T55: Equipo de cómputo | U55: E000000184 | V55: 73120 | X55: 60206 | Z55: JUAN CARLOS MORENO OSUNA | AE55: PAGADA | AF55: Estatus Surtido | AG55: FAVOR DE ENTREGAR EN CORPORATIVO CENTRO CON CARLITOS DE SISTEMAS. LAPTOP ASUS EXPERTBOOK P1403CVA-158G512- P1 CORE I5 13420H 16GB 512GB 2280 SSD PANTALLA DE 14.0" WIN11 PRO BLACK WI-FI 6E GARANTIA 3 AÑOS Y DAÑOS ACCIDENTALES INCLUYE 1 MOUSE LOGITECH M170 DE REGALO. CFDI I04. | AH55: 12,995.00 | AI55: 0.00 | AJ55: 2,079.20 | AK55: 0.00 | AL55: 15,074.20 | AM55: 20101021501 | AN55: 12101030000 | AO55: 20101021500
A56: PETROPLAZAS | B56: CEDIS Mazatlán | C56: EL MAYOREO GRANADOS SA DE CV | D56: GZ0002684 | E56: 04/06/2026 | F56: 05/06/2026 | G56: 05/06/2026 | H56: 17613.44 | I56: Pesos (MXN) | J56: 1 | K56: 17613.44 | L56: PANTALON DE VESTIR DAMA 34/M/7 | N56: 292 | R56: ALMACEN | S56: Uniformes | T56: PANTALONES | U56: E000000465 | V56: 73166 | X56: 59974 | Z56: Maria Isabel Vega Gaxiola | AE56: PAGADA | AF56: Estatus Surtido | AG56: FAVOR DE ENTREGAR EN CEDIS MAZATLAN CON ISABEL. PANTALON DE VESTIR DAMA AZUL MARINO PARA STOCK DE CEDIS MAZATLAN. | AH56: 15,184.00 | AI56: 0.00 | AJ56: 2,429.44 | AK56: 0.00 | AL56: 17,613.44 | AM56: 20101021501 | AN56: 12101030000 | AO56: 20101021500
A57: PETROPLAZAS | B57: Playas | C57: ARMSTRONG ARMORED DE MEXICO SA DE CV | D57: 028800542831 | E57: 03/06/2026 | F57: 05/06/2026 | G57: 05/06/2026 | H57: 17063.12 | I57: Pesos (MXN) | J57: 1 | K57: 17063.12 | L57: SERVICIO DE RECOLECCION DE VALORES | M57: 1 | N57: 14869.92 | P57: 14869.92 | Q57: 14869.92 | R57: SERVICIO | S57: Servicios | T57: Servicios | U57: SRV0000107 | V57: 73430 | W57: 66598 | X57: 60400 | Y57: COMPRAS | Z57: Isabel Cristina Chavez Ovalle | AA57: ES_PLAYAS | AB57: ESTACION PLAYAS | AE57: PAGADA | AF57: ESTACION PLAYAS | AG57: PAGO A FACT. 028800542831 POR 22 SERVICIOS DE RECOLECCION DE VALORES, PROCESO DE EFECTIVO POR CADA MIL, RENTA DE CAJA SMART Y CUOTA DE RIESGOPOR MILES TRASLADADOS ESTACION PLAYAS, MAYO 2026. PROGRAMAR A PAGO EL 11/06/2026 | AH57: 14,869.92 | AI57: 0.00 | AJ57: 2,379.19 | AK57: 0.00 | AL57: 17,063.12 | AM57: 50299040051 | AN57: 12101030000 | AO57: 22201060000 | AP57: 20101021500
A58: PETROPLAZAS | B58: JUAN CARRASCO | C58: ARMSTRONG ARMORED DE MEXICO SA DE CV | D58: 028800542829 | E58: 03/06/2026 | F58: 05/06/2026 | G58: 05/06/2026 | H58: 16023.76 | I58: Pesos (MXN) | J58: 1 | K58: 16023.76 | L58: SERVICIO A CAJA FUERTE | M58: 1 | N58: 8806.22 | P58: 8806.22 | Q58: 8806.22 | R58: SERVICIO | S58: Servicios | T58: Servicios | U58: SRV0000102 | V58: 73499 | W58: 66674 | X58: 60446 | Y58: COMPRAS | Z58: HUGO JAIME LIZARRAGA CARRILLO | AA58: ES_Juan_Carrasco | AB58: CC ADMINISTRACION | AC58: 0 | AE58: PAGADA | AF58: CC ADMINISTRACION | AG58: CORRESPONDE A LA FACTURA 28800542829. SERVICIO DE RECOLECCION DE VALORES, PROCESO DE EFECTIVO Y CAJERO DEL MES DE MAYO 2026 DE ESTACION JUAN CARRASCO. | AH58: 13,973.92 | AI58: 0.00 | AJ58: 2,235.83 | AK58: 0.00 | AL58: 16,023.76 | AM58: 50299030001 | AN58: 50299040051 | AO58: 12101030000 | AP58: 22201060000 | AQ58: 20101021500
A59: PETROPLAZAS | B59: Playas | C59: Comercios Unidos SA de CV | D59: MZ225564 | E59: 04/06/2026 | F59: 05/06/2026 | G59: 05/06/2026 | H59: 484.87 | I59: Pesos (MXN) | J59: 1 | K59: 484.87 | L59: ENGRAPADORA SENCILLA | N59: 48 | R59: ALMACEN | S59: Papeleria y articulos de oficina | T59: Papeleria y articulos de oficina | U59: E000000234 | V59: 73267 | W59: 66224 | X59: 60171 | Y59: OPERACIONES | Z59: Maria Isabel Vega Gaxiola | AA59: ES_PLAYAS | AB59: CC OPERACIONES | AC59: 0 | AE59: PAGADA | AF59: CC OPERACIONES | AG59: MATERIAL DE PAPELERIA SOLICITADO PARA ESTACION PLAYAS, JUNIO 2026. ENTREGAR ENE STACION PLAYAS CON SUPERVISOR EN TURNO. | AH59: 417.99 | AI59: 0.00 | AJ59: 66.88 | AK59: 0.00 | AL59: 484.87 | AM59: 20101021501 | AN59: 12101030000 | AO59: 20101021500
A60: PETROPLAZAS | B60: CEDIS Culiacán | C60: Imprenta y Papeleria Moreno SA de CV | D60: AA43839 | E60: 04/06/2026 | F60: 05/06/2026 | G60: 05/06/2026 | H60: 2598.4 | I60: Pesos (MXN) | J60: 1 | K60: 2598.4 | L60: SERVICIO DE IMPRESION | M60: 1333 | N60: 0.56 | P60: 746.48 | Q60: 746.48 | R60: SERVICIO | S60: Servicios | T60: Servicios | U60: SRV0000461 | V60: 73528 | W60: 66743 | X60: 60532 | Y60: MERCADOTECNIA | Z60: Jose Miguel Candelaria Palafox | AA60: CUAUHTEMOC | AB60: CUAUHTEMOC | AE60: PAGADA | AF60: REVOLUCION | AG60: CORRESPONDE A LA FACTURA AA43839. SERVICIO DE IMPRESION DE CUPONERAS CITICINEMAS DE JUNIO 2026 DE ESTACION DOS VALLE, REVOLUCION Y CUAUHTEMOC. | AH60: 2,240.00 | AI60: 0.00 | AJ60: 358.40 | AK60: 0.00 | AL60: 2,598.40 | AM60: 50299040036 | AN60: 12101030000 | AO60: 20101021500
A61: PETROPLAZAS | B61: CEDIS Mazatlán | C61: GIPROSSA SA DE CV | D61: 02FF93270 | E61: 02/06/2026 | F61: 05/06/2026 | G61: 05/06/2026 | H61: 9744 | I61: Pesos (MXN) | J61: 1 | K61: 9744 | L61: SERVICIO/DE CONSULTORIA Y ELABORACION DOCUMENTAL EN MATERIA DE LA STPS | M61: 1 | N61: 1400 | P61: 1400 | Q61: 1400 | R61: SERVICIO | S61: Gastos diversos | T61: Varios (Gastos Diversos) | U61: SRV0000606 | V61: 73502 | W61: 66677 | X61: 60443 | Y61: COMPRAS | Z61: HUGO JAIME LIZARRAGA CARRILLO | AA61: Colosio | AB61: Colosio | AE61: PAGADA | AF61: Foresta | AG61: CORRESPONDE A LA FACTURA 3270. CONSULTORIA Y ELABORACION DOCUMENTAL DE LA STPS DEL MES DE JUNIO 2026 ZONA MZT 3. | AH61: 8,400.00 | AI61: 0.00 | AJ61: 1,344.00 | AK61: 0.00 | AL61: 9,744.00 | AM61: 50299040025 | AN61: 12101030000 | AO61: 20101021500
A62: PETROPLAZAS | B62: Forjadores | C62: GIPROSSA SA DE CV | D62: EC59F3277 | E62: 02/06/2026 | F62: 05/06/2026 | G62: 05/06/2026 | H62: 2320 | I62: Pesos (MXN) | J62: 1 | K62: 2320 | L62: SERVICIO/DE CONSULTORIA Y ELABORACION DOCUMENTAL EN MATERIA DE LA STPS | M62: 1 | N62: 2000 | P62: 2000 | Q62: 2000 | R62: SERVICIO | S62: Gastos diversos | T62: Varios (Gastos Diversos) | U62: SRV0000297 | V62: 73506 | W62: 66680 | X62: 60440 | Y62: COMPRAS | Z62: HUGO JAIME LIZARRAGA CARRILLO | AA62: ES_FORJADORES | AB62: D. ADMINISTRACION | AE62: PAGADA | AF62: D. ADMINISTRACION | AG62: CORRESPONDE A LA FACTURA 3277. CONSULTORIA Y ELABORACION DOCUMENTAL DE LA STPS DEL MES DE JUNIO 2026 PARA ESTACION FORJADORES. | AH62: 2,000.00 | AI62: 0.00 | AJ62: 320.00 | AK62: 0.00 | AL62: 2,320.00 | AM62: 50299040025 | AN62: 12101030000 | AO62: 20101021500
A63: PETROPLAZAS | B63: Playas | C63: Tecnologia Administrativa Mexicana SA de CV | D63: Z92186 | E63: 03/06/2026 | F63: 05/06/2026 | G63: 05/06/2026 | H63: 3132 | I63: Pesos (MXN) | J63: 1 | K63: 3132 | L63: ROLLO TERMICO BLANCO 80 MM X 70 MM | N63: 18 | R63: ALMACEN | S63: PAPELERIA OPERATIVA | T63: PAPELERIA OPERATIVA | U63: E000000232 | V63: 73309 | W63: 66224 | X63: 60171 | Y63: OPERACIONES | Z63: Maria Isabel Vega Gaxiola | AA63: ES_PLAYAS | AB63: CC OPERACIONES | AC63: 0 | AE63: PAGADA | AF63: CC OPERACIONES | AG63: 2 CAJAS DE ROLLOS TERMICOS SOLICITADOS PARA ESTACION PLAYAS, JUNIO 2026. ENTREGAR EB ESTACION PLAYAS CON SUPERVISOR EN TURNO. | AH63: 2,700.00 | AI63: 0.00 | AJ63: 432.00 | AK63: 0.00 | AL63: 3,132.00 | AM63: 20101021501 | AN63: 12101030000 | AO63: 20101021500
A64: PETROPLAZAS | B64: LAS HABAS | C64: ARMSTRONG ARMORED DE MEXICO SA DE CV | D64: 028800542827 | E64: 03/06/2026 | F64: 05/06/2026 | G64: 05/06/2026 | H64: 17840.32 | I64: Pesos (MXN) | J64: 1 | K64: 17840.32 | L64: SERVICIO DE RECOLECCION DE VALORES | M64: 1 | N64: 15539.92 | P64: 15539.92 | Q64: 15539.92 | R64: SERVICIO | S64: Servicios | T64: Servicios | U64: SRV0000105 | V64: 73429 | W64: 66599 | X64: 60399 | Y64: COMPRAS | Z64: Isabel Cristina Chavez Ovalle | AA64: ES_LAS_HABAS | AB64: ESTACION LAS HABAS | AE64: PAGADA | AF64: ESTACION LAS HABAS | AG64: PAGO A FACT. 028800542827 POR 22 SERVICIO DE RECOLECCION DE VALORES, PROCESOS DE EFECTIVO POR CADA MIL, RENTA DE CAJA SMART Y CUOTA DE RIESGO ESTACION HABAS, MAYO 2026. PROGRAMAR A PAGO EL 11/06/2026 | AH64: 15,539.92 | AI64: 0.00 | AJ64: 2,486.39 | AK64: 0.00 | AL64: 17,840.32 | AM64: 50299040051 | AN64: 12101030000 | AO64: 22201060000 | AP64: 20101021500
A65: PETROPLAZAS | B65: SANTA ROSA | C65: Comercios Unidos SA de CV | D65: MZ225565 | E65: 04/06/2026 | F65: 05/06/2026 | G65: 05/06/2026 | H65: 210.73 | I65: Pesos (MXN) | J65: 1 | K65: 210.73 | L65: CINTA ADHESIVA TRASPARENTE DE 3/4 x 33m | N65: 5.64 | R65: ALMACEN | S65: Papeleria y articulos de oficina | T65: Papeleria y articulos de oficina | U65: E000000144 | V65: 73303 | W65: 66218 | X65: 60175 | Y65: OPERACIONES GASOLINERAS | Z65: Maria Isabel Vega Gaxiola | AA65: ES_SANTA_ROSA | AB65: CUARTO DE CORTES | AE65: PAGADA | AF65: CUARTO DE CORTES | AG65: FAVOR DE ENTREGAR EN ESTACION SANTA ROSA CON EL SUPERVISOR. PAPELERIA DEL MES DE JUNIO 2026. | AH65: 181.66 | AI65: 0.00 | AJ65: 29.07 | AK65: 0.00 | AL65: 210.73 | AM65: 20101021501 | AN65: 12101030000 | AO65: 20101021500
A66: PETROPLAZAS | B66: CEDIS Mazatlán | C66: GIPROSSA SA DE CV | D66: BAE1E3271 | E66: 02/06/2026 | F66: 05/06/2026 | G66: 05/06/2026 | H66: 4872 | I66: Pesos (MXN) | J66: 1 | K66: 4872 | L66: SERVICIO/DE CONSULTORIA Y ELABORACION DOCUMENTAL EN MATERIA DE LA STPS | M66: 1 | N66: 1400 | P66: 1400 | Q66: 1400 | R66: SERVICIO | S66: Gastos diversos | T66: Varios (Gastos Diversos) | U66: SRV0000607 | V66: 73503 | W66: 66678 | X66: 60442 | Y66: COMPRAS | Z66: HUGO JAIME LIZARRAGA CARRILLO | AA66: Grijalva | AB66: Grijalva | AE66: PAGADA | AF66: Juan Carrasco | AG66: CORRESPONDE A LA FACTURA 3271. CONSULTORIA Y ELABORACION DOCUMENTAL DE LA STPS DEL MES DE JUNIO 2026 ZONA MZT 4. | AH66: 4,200.00 | AI66: 0.00 | AJ66: 672.00 | AK66: 0.00 | AL66: 4,872.00 | AM66: 50299040025 | AN66: 12101030000 | AO66: 20101021500
A67: PETROPLAZAS | B67: Pericos centro | C67: Goldenstar de Mexico, SA de CV | D67: TME357591 | E67: 03/06/2026 | F67: 05/06/2026 | G67: 05/06/2026 | H67: 1174.5 | I67: Pesos (MXN) | J67: 1 | K67: 1174.5 | L67: ROLLO TERMICO BLANCO 80 MM X 70 MM | N67: 13.5 | R67: ALMACEN | S67: PAPELERIA OPERATIVA | T67: PAPELERIA OPERATIVA | U67: E000000099 | V67: 73388 | W67: 66348 | X67: 60274 | Y67: OPERACIONES | Z67: Diego Alejandro Estrada Ramos | AA67: ES_PERICOS_CENTRO | AB67: CC ADMINISTRACION | AC67: 0 | AE67: PAGADA | AF67: CC ADMINISTRACION | AG67: COMPRA DE ROLLO TERMICO (80X70) PARA DISPENSARIOS DE LA ESTACION PERICOS CENTRO. ENTREGAR EN: BLVD. ENRIQUE FELIX CASTRO PTE. 3029, COL. INFONAVIT HUMAYA, CULIACAN, SINALOA, C.P. 80020. CON NOTA DE QUE ES DE "PERICOS CENTRO". | AH67: 1,012.50 | AI67: 0.00 | AJ67: 162.00 | AK67: 0.00 | AL67: 1,174.50 | AM67: 20101021501 | AN67: 12101030000 | AO67: 20101021500
A68: PETROPLAZAS | B68: SANTA ROSA | C68: ARMSTRONG ARMORED DE MEXICO SA DE CV | D68: 028800542821 | E68: 03/06/2026 | F68: 05/06/2026 | G68: 05/06/2026 | H68: 16448.25 | I68: Pesos (MXN) | J68: 1 | K68: 16448.25 | L68: VERIFICACION DEPOSITO ESTANDAR M.N. O DLLS. | M68: 544 | N68: 2 | P68: 1088 | Q68: 1088 | R68: SERVICIO | S68: Servicios | T68: Servicios | U68: SRV0000082 | V68: 73501 | W68: 66676 | X68: 60444 | Y68: COMPRAS | Z68: HUGO JAIME LIZARRAGA CARRILLO | AA68: ES_SANTA_ROSA | AB68: CC ADMINISTRACION | AC68: 0 | AE68: PAGADA | AF68: CC ADMINISTRACION | AG68: CORRESPONDE A LA FACTURA 28800542821. SERVICIO DE RECOLECCION DE VALORES, PROCESO DE EFECTIVO Y CAJERO DEL MES DE MAYO 2026 DE ESTACION SANTA ROSA. | AH68: 14,332.57 | AI68: 0.00 | AJ68: 2,293.21 | AK68: 0.00 | AL68: 16,448.25 | AM68: 50299030001 | AN68: 50299040051 | AO68: 12101030000 | AP68: 22201060000 | AQ68: 20101021500
A69: PETROPLAZAS | B69: COLOSIO | C69: JORGE LUIS LIZARRAGA GARATE | D69: BCR675 | E69: 01/06/2026 | F69: 05/06/2026 | G69: 05/06/2026 | H69: 1092.89 | I69: Pesos (MXN) | J69: 1 | K69: 1092.89 | L69: BOLSA NEGRA JUMBO | N69: 35.84 | R69: ALMACEN | S69: Artículos de Limpieza | T69: Artículos de Limpieza | U69: E000000152 | V69: 73261 | W69: 66200 | X69: 60160 | Y69: OPERACIONES GASOLINERAS | Z69: Maria Isabel Vega Gaxiola | AA69: ES_Colosio | AB69: CC GERENCIA DE OPERACIONES | AC69: 0 | AE69: PAGADA | AF69: CC GERENCIA DE OPERACIONES | AG69: FAVOR DE ENTREGAR EN ESTACION COLOSIO CON EL SUPERVISOR. MATERIAL DE LIMPIEZA DEL MES DE JUNIO 2026. AROMATIZANTE LIMA LIMON. | AH69: 952.40 | AI69: 0.00 | AJ69: 152.38 | AK69: 0.00 | AL69: 1,092.88 | AM69: 20101021501 | AN69: 12101030000 | AO69: 22201020000 | AP69: 20101021500
A70: PETROPLAZAS | B70: El Diez | C70: Goldenstar de Mexico, SA de CV | D70: TME357583 | E70: 03/06/2026 | F70: 05/06/2026 | G70: 05/06/2026 | H70: 1174.5 | I70: Pesos (MXN) | J70: 1 | K70: 1174.5 | L70: ROLLO TERMICO BLANCO 80 MM X 70 MM | N70: 13.5 | R70: ALMACEN | S70: PAPELERIA OPERATIVA | T70: PAPELERIA OPERATIVA | U70: E000000427 | V70: 73384 | W70: 66332 | X70: 60265 | Y70: OPERACIONES | Z70: Diego Alejandro Estrada Ramos | AA70: ES_El_Diez | AB70: Estacion el Diez | AE70: PAGADA | AF70: Estacion el Diez | AG70: COMPRA DE ROLLO TERMICO (80X70) PARA DISPENSARIOS DE LA ESTACION EL DIEZ. ENTREGAR EN: CARRET. EL DORADO NO. 11101 SUR, CAMPO EL DIEZ, CULIACAN, SINALOA, C.P. 80300. | AH70: 1,012.50 | AI70: 0.00 | AJ70: 162.00 | AK70: 0.00 | AL70: 1,174.50 | AM70: 20101021501 | AN70: 12101030000 | AO70: 20101021500
A71: PETROPLAZAS | B71: EL CONCHI | C71: Soto Cruz Ramón Alberto | D71: M0001912 | E71: 04/06/2026 | F71: 05/06/2026 | G71: 05/06/2026 | H71: 4640 | I71: Pesos (MXN) | J71: 1 | K71: 4640 | L71: REPARACION SONDA DE MEDICION | M71: 1 | N71: 4000 | P71: 4000 | Q71: 4000 | R71: SERVICIO | S71: Servicios | T71: Servicios | U71: SRV0000029 | V71: 73508 | W71: 66732 | X71: 60522 | Y71: OPERACIONES GASOLINERAS | Z71: HUGO JAIME LIZARRAGA CARRILLO | AA71: ES_El_Conchi | AB71: OPERACIONES | AE71: PAGADA | AF71: OPERACIONES | AG71: CORRESPONDE A LA FACTURA M0001912. SERVICIO DE CORREGIR FALLA EN COMUNICACION DE SONDA DE MAGNA Y MATERIAL PARA TAPAR RANURAS DE ESTACION EL CONCHI. | AH71: 4,000.00 | AI71: 0.00 | AJ71: 640.00 | AK71: 0.00 | AL71: 4,640.00
A72: PETROPLAZAS | B72: GRIJALVA | C72: Comercios Unidos SA de CV | D72: MZ225582 | E72: 04/06/2026 | F72: 05/06/2026 | G72: 05/06/2026 | H72: 914.47 | I72: Pesos (MXN) | J72: 1 | K72: 914.47 | L72: CINTA ADHESIVA TRASPARENTE DE 3/4 x 33m | N72: 5.64 | R72: ALMACEN | S72: Papeleria y articulos de oficina | T72: Papeleria y articulos de oficina | U72: E000000158 | V72: 73312 | X72: 60319 | Z72: Maria Isabel Vega Gaxiola | AE72: PAGADA | AF72: Estatus Surtido | AG72: FAVOR DE ENTREGAR EN ESTACION GRIJALVA CON EL SUPERVISOR. PAPELERIA DEL MES DE JUNIO 2026. | AH72: 788.34 | AI72: 0.00 | AJ72: 126.13 | AK72: 0.00 | AL72: 914.47 | AM72: 20101021501 | AN72: 12101030000 | AO72: 20101021500
A73: PETROPLAZAS | B73: El Papalote | C73: Goldenstar de Mexico, SA de CV | D73: TME357587 | E73: 03/06/2026 | F73: 05/06/2026 | G73: 05/06/2026 | H73: 1174.5 | I73: Pesos (MXN) | J73: 1 | K73: 1174.5 | L73: ROLLO TERMICO BLANCO 80 MM X 70 MM | N73: 13.5 | R73: ALMACEN | S73: PAPELERIA OPERATIVA | T73: PAPELERIA OPERATIVA | U73: E000000109 | V73: 73396 | W73: 66341 | X73: 60292 | Y73: OPERACIONES | Z73: Diego Alejandro Estrada Ramos | AA73: ES_El_Papalote | AB73: Estacion El Papalote | AE73: PAGADA | AF73: Estacion El Papalote | AG73: COMPRA DE ROLLO TERMICO (80X70) PARA DISPENSARIOS DE LA ESTACION EL PAPALOTE. ENTREGAR EN: AV. ALVARO OBREGON NO. 3742, COL. 6 DE ENERO, CULIACAN, SIN., C.P. 80010. | AH73: 1,012.50 | AI73: 0.00 | AJ73: 162.00 | AK73: 0.00 | AL73: 1,174.50 | AM73: 20101021501 | AN73: 12101030000 | AO73: 20101021500
A74: PETROPLAZAS | B74: COLOSIO | C74: Operadora Polar SA de CV | D74: MZF445024 | E74: 01/06/2026 | F74: 05/06/2026 | G74: 05/06/2026 | H74: 1528.42 | I74: Pesos (MXN) | J74: 1 | K74: 1528.42 | L74: PAPEL HIGIENICO JUMBO BLANCO | N74: 26.4333 | R74: ALMACEN | S74: Artículos de Limpieza | T74: Artículos de Limpieza | U74: E000000153 | V74: 73260 | W74: 66200 | X74: 60160 | Y74: OPERACIONES GASOLINERAS | Z74: Maria Isabel Vega Gaxiola | AA74: ES_Colosio | AB74: CC GERENCIA DE OPERACIONES | AC74: 0 | AE74: PAGADA | AF74: CC GERENCIA DE OPERACIONES | AG74: FAVOR DE ENTREGAR EN ESTACION COLOSIO CON EL SUPERVISOR. MATERIAL DE LIMPIEZA DEL MES DE JUNIO 2026. | AH74: 1,317.60 | AI74: 0.00 | AJ74: 210.82 | AK74: 0.00 | AL74: 1,528.42 | AM74: 20101021501 | AN74: 12101030000 | AO74: 20101021500
A75: PETROPLAZAS | B75: La Foresta | C75: JORGE LUIS LIZARRAGA GARATE | D75: BCR677 | E75: 01/06/2026 | F75: 05/06/2026 | G75: 05/06/2026 | H75: 1190.04 | I75: Pesos (MXN) | J75: 1 | K75: 1190.04 | L75: PASTILLA AROMATIZANTE PARA BAÑO | N75: 16.85 | R75: ALMACEN | S75: Artículos de Limpieza | T75: Artículos de Limpieza | U75: E000000182 | V75: 73254 | W75: 66249 | X75: 60165 | Y75: OPERACIONES | Z75: Maria Isabel Vega Gaxiola | AA75: ES_La Foresta | AB75: CC OPERACIONES | AC75: 0 | AE75: PAGADA | AF75: CC OPERACIONES | AG75: FAVOR DE ENTREGAR EN ESTACION FORESTA CON EL SUPERVISOR. MATERIAL DE LIMPIEZA DEL MES DE JUNIO 2026. | AH75: 1,037.06 | AI75: 0.00 | AJ75: 165.93 | AK75: 0.00 | AL75: 1,190.03 | AM75: 20101021501 | AN75: 12101030000 | AO75: 22201020000 | AP75: 20101021500
A76: PETROPLAZAS | B76: AEROPUERTO | C76: Comercios Unidos SA de CV | D76: MZ225562 | E76: 04/06/2026 | F76: 05/06/2026 | G76: 05/06/2026 | H76: 685.56 | I76: Pesos (MXN) | J76: 1 | K76: 685.56 | L76: HOJA BLANCA TAMAÑO CARTA PAQUETE 500 HOJAS | N76: 59.1 | R76: ALMACEN | S76: Papeleria y articulos de oficina | T76: Papeleria y articulos de oficina | U76: E000000286 | V76: 73279 | W76: 66306 | X76: 60153 | Y76: OPERACIONES | Z76: Maria Isabel Vega Gaxiola | AA76: ES_Aeropuerto | AB76: ESTACION AEROPUERTO | AE76: PAGADA | AF76: ESTACION AEROPUERTO | AG76: CAJA DE HOJAS BLANCAS SOLITADAS PARA ESTACION AEROPUERTO, JUNIO 2026. ENTREGAR EN CEDIS MAZATLAN CON ISABEL VEGA. | AH76: 591.00 | AI76: 0.00 | AJ76: 94.56 | AK76: 0.00 | AL76: 685.56 | AM76: 20101021501 | AN76: 12101030000 | AO76: 20101021500
A77: PETROPLAZAS | B77: MUNICH II | C77: Operadora Polar SA de CV | D77: MZF445023 | E77: 01/06/2026 | F77: 05/06/2026 | G77: 05/06/2026 | H77: 1183.43 | I77: Pesos (MXN) | J77: 1 | K77: 1183.43 | L77: PAPEL HIGIENICO JUMBO BLANCO | N77: 26.4333 | R77: ALMACEN | S77: Artículos de Limpieza | T77: Artículos de Limpieza | U77: E000000177 | V77: 73268 | X77: 60321 | Z77: Maria Isabel Vega Gaxiola | AE77: PAGADA | AF77: Estatus Surtido | AG77: FAVOR DE ENTREGAR EN ESTACION MUNICH II CON EL SUPERVISOR. MATERIAL DE LIMPIEZA DEL MES DE JUNIO 2026. | AH77: 1,020.20 | AI77: 0.00 | AJ77: 163.23 | AK77: 0.00 | AL77: 1,183.43 | AM77: 20101021501 | AN77: 12101030000 | AO77: 20101021500
A78: PETROPLAZAS | B78: Flores Magon | C78: Comercios Unidos SA de CV | D78: MZ225568 | E78: 04/06/2026 | F78: 05/06/2026 | G78: 05/06/2026 | H78: 847.17 | I78: Pesos (MXN) | J78: 1 | K78: 847.17 | L78: HOJA BLANCA TAMAÑO CARTA PAQUETE 500 HOJAS | N78: 59.1 | R78: ALMACEN | S78: Papeleria y articulos de oficina | T78: Papeleria y articulos de oficina | U78: E000000441 | V78: 73305 | W78: 66201 | X78: 60162 | Y78: OPERACIONES GASOLINERAS | Z78: Maria Isabel Vega Gaxiola | AA78: ES_Flores Magon | AB78: OFICINAS ADMINISTRATIVAS | AE78: PAGADA | AF78: OFICINAS ADMINISTRATIVAS | AG78: FAVOR DE ENTREGAR EN ESTACION FLORES MAGON CON EL SUPERVISOR. PAPELERIA DEL MES DE JUNIO 2026. | AH78: 730.32 | AI78: 0.00 | AJ78: 116.85 | AK78: 0.00 | AL78: 847.17 | AM78: 20101021501 | AN78: 12101030000 | AO78: 20101021500
A79: PETROPLAZAS | B79: La Marina | C79: Comercios Unidos SA de CV | D79: MZ225573 | E79: 04/06/2026 | F79: 05/06/2026 | G79: 05/06/2026 | H79: 672.68 | I79: Pesos (MXN) | J79: 1 | K79: 672.68 | L79: POST IT MINI CUBO NEON 400H | N79: 21.3 | R79: ALMACEN | S79: Papeleria y articulos de oficina | T79: Papeleria y articulos de oficina | U79: E000000231 | V79: 73265 | W79: 66258 | X79: 60167 | Y79: OPERACIONES GASOLINERAS | Z79: Maria Isabel Vega Gaxiola | AA79: ES_La Marina | AB79: CC OPERACIONES | AC79: 0 | AE79: PAGADA | AF79: CC OPERACIONES | AG79: MATERIAL DE PAPELERIA SOLICITADO PARA ESTACION LA MARINA, JUNIO 2026. ENTREGAR EN ESTACION MARINA CON SUPERVUSOR EN TURNO. | AH79: 579.90 | AI79: 0.00 | AJ79: 92.78 | AK79: 0.00 | AL79: 672.68 | AM79: 20101021501 | AN79: 12101030000 | AO79: 20101021500
A80: PETROPLAZAS | B80: Flores Magon | C80: JORGE LUIS LIZARRAGA GARATE | D80: BCR676 | E80: 01/06/2026 | F80: 05/06/2026 | G80: 05/06/2026 | H80: 1187.39 | I80: Pesos (MXN) | J80: 1 | K80: 1187.39 | L80: AROMATIZANTE PARA PISO | N80: 13.2145 | R80: ALMACEN | S80: Artículos de Limpieza | T80: Artículos de Limpieza | U80: E000000437 | V80: 73256 | W80: 66199 | X80: 60161 | Y80: OPERACIONES GASOLINERAS | Z80: Maria Isabel Vega Gaxiola | AA80: ES_Flores Magon | AB80: BAÑOS ESTACION | AE80: PAGADA | AF80: BAÑOS ESTACION | AG80: FAVOR DE ENTREGAR EN ESTACION FLORES MAGON CON EL SUPERVISOR. MATERIAL DE LIMPIEZA DEL MES DE JUNIO 2026. AROMA BRISA DE MAR | AH80: 1,034.75 | AI80: 0.00 | AJ80: 165.56 | AK80: 0.00 | AL80: 1,187.38 | AM80: 20101021501 | AN80: 12101030000 | AO80: 22201020000 | AP80: 20101021500
A81: PETROPLAZAS | B81: MUNICH II | C81: ARMSTRONG ARMORED DE MEXICO SA DE CV | D81: 028800542832 | E81: 03/06/2026 | F81: 05/06/2026 | G81: 05/06/2026 | H81: 5390.72 | I81: Pesos (MXN) | J81: 1 | K81: 5390.72 | L81: SERVICIO DE RECOLECCION DE VALORES | M81: 19 | N81: 211.35 | P81: 4015.65 | Q81: 4015.65 | R81: SERVICIO | S81: Servicios | T81: Servicios | U81: SRV0000077 | V81: 73500 | W81: 66675 | X81: 60445 | Y81: COMPRAS | Z81: HUGO JAIME LIZARRAGA CARRILLO | AA81: ES_MunichII | AB81: CC ADMINISTRACION | AC81: 0 | AE81: PAGADA | AF81: CC ADMINISTRACION | AG81: CORRESPONDE A LA FACTURA 28800542832. SERVICIO DE RECOLECCION DE VALORES, PROCESO DE EFECTIVO DEL MES DE MAYO 2026 DE ESTACION MUNICH II. | AH81: 4,785.65 | AI81: 0.00 | AJ81: 765.70 | AK81: 0.00 | AL81: 5,390.72 | AM81: 50299040051 | AN81: 12101030000 | AO81: 22201060000 | AP81: 20101021500
A82: PETROPLAZAS | B82: La Foresta | C82: Comercios Unidos SA de CV | D82: MZ225566 | E82: 04/06/2026 | F82: 05/06/2026 | G82: 05/06/2026 | H82: 1012.15 | I82: Pesos (MXN) | J82: 1 | K82: 1012.15 | L82: BLOCK POST-IT CHICO | N82: 4.92 | R82: ALMACEN | S82: Papeleria y articulos de oficina | T82: Papeleria y articulos de oficina | U82: E000000183 | V82: 73304 | W82: 66250 | X82: 60166 | Y82: OPERACIONES | Z82: Maria Isabel Vega Gaxiola | AA82: ES_La Foresta | AB82: CC OPERACIONES | AC82: 0 | AE82: PAGADA | AF82: CC OPERACIONES | AG82: FAVOR DE ENTREGAR EN ESTACION FORESTA CON EL SUPERVISOR. PAPELERIA DEL MES DE JUNIO 2026. | AH82: 872.54 | AI82: 0.00 | AJ82: 139.61 | AK82: 0.00 | AL82: 1,012.15 | AM82: 20101021501 | AN82: 12101030000 | AO82: 20101021500
A83: PETROPLAZAS | B83: MUNICH II | C83: Goldenstar de Mexico, SA de CV | D83: TME357497 | E83: 03/06/2026 | F83: 05/06/2026 | G83: 05/06/2026 | H83: 2349 | I83: Pesos (MXN) | J83: 1 | K83: 2349 | L83: ROLLO TERMICO BLANCO 80 MM X 70 MM | N83: 13.5 | R83: ALMACEN | S83: PAPELERIA OPERATIVA | T83: PAPELERIA OPERATIVA | U83: E000000178 | V83: 73311 | X83: 60322 | Z83: Maria Isabel Vega Gaxiola | AE83: PAGADA | AF83: Estatus Surtido | AG83: FAVOR DE ENTREGAR EN ESTACION MUNICH II CON EL SUPERVISOR AL DOMICILIO AV. MUICH II, 2402, LIDERES UNIDOS, MAZATLAN, SINALOA, CP. 82134. 02 CAJAS DE 75 C/U. DE ROLLOS TERMICOS 80X70 DEL MES DE JUNIO 2026. | AH83: 2,025.00 | AI83: 0.00 | AJ83: 324.00 | AK83: 0.00 | AL83: 2,349.00 | AM83: 20101021501 | AN83: 12101030000 | AO83: 20101021500
A84: PETROPLAZAS | B84: La Marina | C84: ALTYA SA DE CV | D84: C9031 | E84: 03/06/2026 | F84: 05/06/2026 | G84: 05/06/2026 | H84: 13484.1 | I84: Pesos (MXN) | J84: 1 | K84: 13484.1 | L84: SERVICIO DE RECOLECCION DE BASURA | M84: 1 | N84: 11624.22 | P84: 11624.22 | Q84: 11624.22 | R84: SERVICIO | S84: Servicios | T84: Servicios | U84: SRV0000163 | V84: 73509 | W84: 66644 | X84: 60473 | Y84: COMPRAS | Z84: Isabel Cristina Chavez Ovalle | AA84: ES_La Marina | AB84: Estacion La Marina | AE84: PAGADA | AF84: Estacion La Marina | AG84: PAGO A FACT. C 9031 POR SERVICIO DE RECOLECCION DE BASURA ESTACION MARINA, JUNIO 2026. PROGRAMAR A PAGO EL 09/06/2026 | AH84: 11,624.22 | AI84: 0.00 | AJ84: 1,859.88 | AK84: 0.00 | AL84: 13,484.10 | AM84: 50299040004 | AN84: 12101030000 | AO84: 20101021500
A85: PETROPLAZAS | B85: ALHUEY2 | C85: Goldenstar de Mexico, SA de CV | D85: TME357624 | E85: 03/06/2026 | F85: 05/06/2026 | G85: 05/06/2026 | H85: 1174.5 | I85: Pesos (MXN) | J85: 1 | K85: 1174.5 | L85: ROLLO TERMICO BLANCO 80 MM X 70 MM | N85: 13.5 | R85: ALMACEN | S85: PAPELERIA OPERATIVA | T85: PAPELERIA OPERATIVA | U85: E000000131 | V85: 73399 | W85: 66387 | X85: 60260 | Y85: OPERACIONES | Z85: Diego Alejandro Estrada Ramos | AA85: ALHUEY 2 | AB85: ESTACION | AE85: PAGADA | AF85: ESTACION | AG85: COMPRA DE ROLLO TERMICO (80X70) PARA DISPENSARIOS DE LA ESTACION ALHUEY 2. ENTREGAR EN: AUTOPISTA CULIACAN-LOS MOCHIS KM. 110.5, ALHUEY, ANGOSTURA, SINALOA, C.P. 81610. | AH85: 1,012.50 | AI85: 0.00 | AJ85: 162.00 | AK85: 0.00 | AL85: 1,174.50 | AM85: 20101021501 | AN85: 12101030000 | AO85: 20101021500
A86: PETROPLAZAS | B86: REAL DEL VALLE | C86: Comercios Unidos SA de CV | D86: MZ225563 | E86: 04/06/2026 | F86: 05/06/2026 | G86: 05/06/2026 | H86: 934.74 | I86: Pesos (MXN) | J86: 1 | K86: 934.74 | L86: HOJA BLANCA TAMAÑO CARTA PAQUETE 500 HOJAS | N86: 59.1 | R86: ALMACEN | S86: Papeleria y articulos de oficina | T86: Papeleria y articulos de oficina | U86: E000000169 | V86: 73270 | W86: 66364 | X86: 60230 | Y86: OPERACIONES GASOLINERAS | Z86: Maria Isabel Vega Gaxiola | AA86: REAL DE VALLE | AB86: ESTACION REAL DEL VALLE | AE86: PAGADA | AF86: ESTACION REAL DEL VALLE | AG86: MATERIAL DE PAPELERIA SOLICITADO PARA ESTACION REAL DEL VALLE, JUNIO 2026. ENTREGAR EN ESTACION REAL DEL VALLE CON SUPERVISOR EN TURNO. | AH86: 805.81 | AI86: 0.00 | AJ86: 128.93 | AK86: 0.00 | AL86: 934.74 | AM86: 20101021501 | AN86: 12101030000 | AO86: 20101021500
A87: PETROPLAZAS | B87: CARDONES | C87: KARLA LIZETTE ARELLANO GUZMAN | D87: A19123 | E87: 02/06/2026 | F87: 05/06/2026 | G87: 05/06/2026 | H87: 660.7 | I87: Pesos (MXN) | J87: 1 | K87: 660.7 | L87: BROCHA 3" | N87: 33.88 | R87: ALMACEN | S87: Pinturas y Solventes | T87: Accesorios y materiales | U87: E000000226 | V87: 73402 | W87: 66560 | X87: 60419 | Y87: MANTENIMIENTO | Z87: Maria Isabel Vega Gaxiola | AA87: ES_Cardones | AB87: CC OPERACIONES | AC87: 0 | AE87: PAGADA | AF87: CC OPERACIONES | AG87: CORRESPONDE A LA FACTURA AB2275D6. MATERIAL PARA DISPENSARIOS DE AIRE DE ESTACION CARDONES. | AH87: 569.56 | AI87: 0.00 | AJ87: 91.13 | AK87: 0.00 | AL87: 660.69 | AM87: 20101021501 | AN87: 12101030000 | AO87: 20101021500 | AP87: 50229040022
A88: PETROPLAZAS | B88: CERRITOS | C88: ARMSTRONG ARMORED DE MEXICO SA DE CV | D88: 028800542822 | E88: 03/06/2026 | F88: 05/06/2026 | G88: 05/06/2026 | H88: 16812.49 | I88: Pesos (MXN) | J88: 1 | K88: 16812.49 | L88: SERVICIO DE RECOLECCION DE VALORES | M88: 1 | N88: 14646.57 | P88: 14646.57 | Q88: 14646.57 | R88: SERVICIO | S88: Servicios | T88: Servicios | U88: SRV0000070 | V88: 73428 | W88: 66600 | X88: 60398 | Y88: COMPRAS | Z88: Isabel Cristina Chavez Ovalle | AA88: ES_Cerritos | AB88: ESTACION CERRITOS | AE88: PAGADA | AF88: ESTACION CERRITOS | AG88: PAGO A FACT. 028800542822 POR 21 SERVICIO DE RECOLECCION DE VALORES, PROCESOS DE EFECTIVO POR CADA MIL, RENTA DE CAJA SMART Y CUOTA DE RIESGO ESTACION CERRITOS, MAYO 2026. PROGRAMAR A PAGO EL 11/06/2026 | AH88: 14,646.57 | AI88: 0.00 | AJ88: 2,343.45 | AK88: 0.00 | AL88: 16,812.49 | AM88: 50299040051 | AN88: 12101030000 | AO88: 22201060000 | AP88: 20101021500
A89: PETROPLAZAS | B89: La Marina | C89: ARMSTRONG ARMORED DE MEXICO SA DE CV | D89: 028800542830 | E89: 03/06/2026 | F89: 05/06/2026 | G89: 05/06/2026 | H89: 16561.64 | I89: Pesos (MXN) | J89: 1 | K89: 16561.64 | L89: SERVICIO DE RECOLECCION DE VALORES | M89: 1 | N89: 14401.17 | P89: 14401.17 | Q89: 14401.17 | R89: SERVICIO | S89: Servicios | T89: Servicios | U89: SRV0000162 | V89: 73436 | W89: 66594 | X89: 60403 | Y89: COMPRAS | Z89: Isabel Cristina Chavez Ovalle | AA89: ES_La Marina | AB89: Estacion La Marina | AE89: PAGADA | AF89: Estacion La Marina | AG89: PAGO A FACT. 028800542830 POR 17 SERVICIOS DE RECOLECCION DE VALORES, PROCESO DE EFECTIVO POR CADA MIL, RENTA DE CAJA SMART Y CUOTA DE RIESGO MILES TRASLADADOS ESTACION MARINA, MAYO 2026. PROGRAMAR A PAGO EL 11/06/2026 | AH89: 14,401.17 | AI89: 0.00 | AJ89: 2,304.19 | AK89: 0.00 | AL89: 16,561.64 | AM89: 50299040051 | AN89: 12101030000 | AO89: 22201060000 | AP89: 20101021500
A90: PETROPLAZAS | B90: CERRITOS | C90: Comercios Unidos SA de CV | D90: MZ225575 | E90: 04/06/2026 | F90: 05/06/2026 | G90: 05/06/2026 | H90: 1096.66 | I90: Pesos (MXN) | J90: 1 | K90: 1096.66 | L90: HOJA BLANCA TAMAÑO CARTA PAQUETE 500 HOJAS | N90: 59.1 | R90: ALMACEN | S90: Papeleria y articulos de oficina | T90: Papeleria y articulos de oficina | U90: E000000199 | V90: 73259 | W90: 66213 | X90: 60157 | Y90: OPERACIONES | Z90: Maria Isabel Vega Gaxiola | AA90: ES_Cerritos | AB90: A. CUARTO DE CORTES | AE90: PAGADA | AF90: A. CUARTO DE CORTES | AG90: COMPRA POR PAPELERIA SOLICITADA PARA ESTACION CERRITOS, JUNIO 2026. ENTREGAR EN ESTACION CERRITOS CON SUPERV ISOR EN TURNO. | AH90: 945.40 | AI90: 0.00 | AJ90: 151.26 | AK90: 0.00 | AL90: 1,096.66 | AM90: 20101021501 | AN90: 12101030000 | AO90: 20101021500
A91: PETROPLAZAS | B91: Bellavista | C91: Goldenstar de Mexico, SA de CV | D91: TME357590 | E91: 03/06/2026 | F91: 05/06/2026 | G91: 05/06/2026 | H91: 1174.5 | I91: Pesos (MXN) | J91: 1 | K91: 1174.5 | L91: ROLLO TERMICO BLANCO 80 MM X 70 MM | N91: 13.5 | R91: ALMACEN | S91: PAPELERIA OPERATIVA | T91: PAPELERIA OPERATIVA | U91: E000000096 | V91: 73392 | W91: 66210 | X91: 60289 | Y91: OPERACIONES | Z91: Diego Alejandro Estrada Ramos | AA91: ES_Bellavista | AB91: Estacion BellaVista | AE91: PAGADA | AF91: Estacion BellaVista | AG91: COMPRA DE ROLLO TERMICO (80X70) PARA DISPENSARIOS DE LA ESTACION BELLAVISTA. ENTREGAR EN: CARRETERA A CULIACANCITO NO. 11000 PTE., BELLAVISA, CULIACAN, SINALOA, C.P. 80301. | AH91: 1,012.50 | AI91: 0.00 | AJ91: 162.00 | AK91: 0.00 | AL91: 1,174.50 | AM91: 20101021501 | AN91: 12101030000 | AO91: 20101021500
A92: PETROPLAZAS | B92: Sabalo | C92: Comercios Unidos SA de CV | D92: MZ225574 | E92: 04/06/2026 | F92: 05/06/2026 | G92: 05/06/2026 | H92: 1077.59 | I92: Pesos (MXN) | J92: 1 | K92: 1077.59 | L92: CAJA PARA ARCHIVO MUERTO DE PLASTICO TAMAÑO CARTA | N92: 62.9 | R92: ALMACEN | S92: Papeleria y articulos de oficina | T92: Papeleria y articulos de oficina | U92: E000000209 | V92: 73262 | W92: 66149 | X92: 60173 | Y92: OPERACIONES GASOLINERAS | Z92: Maria Isabel Vega Gaxiola | AA92: ES_Sabalo | AB92: CC OPERACIONES | AC92: 0 | AE92: PAGADA | AF92: CC OPERACIONES | AG92: MATERIAL DE PAPELERIA SOLICITADO PARA ESTACION SABALO, JUNIO 2026. ENTREGAR EN CEDIS MAZATLAN CON ISAB EL VEGA. | AH92: 928.96 | AI92: 0.00 | AJ92: 148.63 | AK92: 0.00 | AL92: 1,077.59 | AM92: 20101021501 | AN92: 12101030000 | AO92: 20101021500
A93: PETROPLAZAS | B93: HABAL | C93: KARLA LIZETTE ARELLANO GUZMAN | D93: A19124 | E93: 02/06/2026 | F93: 05/06/2026 | G93: 05/06/2026 | H93: 6978.46 | I93: Pesos (MXN) | J93: 1 | K93: 6978.46 | L93: MANGUERA ALTA PRESION 1/4" | N93: 146.14 | R93: ALMACEN | S93: Conexiones Rapidas | T93: Mangueras | U93: E000000193 | V93: 73403 | W93: 66561 | X93: 60420 | Y93: MANTENIMIENTO | Z93: Maria Isabel Vega Gaxiola | AA93: ES_Habal | AB93: CC OPERACIONES | AC93: 0 | AE93: PAGADA | AF93: CC OPERACIONES | AG93: CORRESPONDE A LA FACTURA A2953C14. MATERIAL PARA DISPENSARIOS DE AIRE DE ESTACION HABAL. | AH93: 6,015.90 | AI93: 0.00 | AJ93: 962.54 | AK93: 0.00 | AL93: 6,978.44 | AM93: 20101021501 | AN93: 12101030000 | AO93: 20101021500 | AP93: 50229040022
A94: PETROPLAZAS | B94: Humaya | C94: Goldenstar de Mexico, SA de CV | D94: TME357592 | E94: 03/06/2026 | F94: 05/06/2026 | G94: 05/06/2026 | H94: 1174.5 | I94: Pesos (MXN) | J94: 1 | K94: 1174.5 | L94: ROLLO TERMICO BLANCO 80 MM X 70 MM | N94: 13.5 | R94: ALMACEN | S94: PAPELERIA OPERATIVA | T94: PAPELERIA OPERATIVA | U94: E000000115 | V94: 73386 | W94: 66326 | X94: 60270 | Y94: OPERACIONES | Z94: Diego Alejandro Estrada Ramos | AA94: ES Humaya | AB94: ZONA DE DESPACHO | AE94: PAGADA | AF94: ZONA DE DESPACHO | AG94: COMPRA DE ROLLO TERMICO (80X70) PARA DISPENSARIOS DE LA ESTACION HUMAYA. ENTREGAR EN: BLVD. ENRIQUE FELIX CASTRO PTE. 3029, COL. INFONAVIT HUMAYA, CULIACAN, SINALOA, C.P. 80020. | AH94: 1,012.50 | AI94: 0.00 | AJ94: 162.00 | AK94: 0.00 | AL94: 1,174.50 | AM94: 20101021501 | AN94: 12101030000 | AO94: 20101021500
A95: PETROPLAZAS | B95: Sabalo | C95: ARMSTRONG ARMORED DE MEXICO SA DE CV | D95: 028800542835 | E95: 03/06/2026 | F95: 05/06/2026 | G95: 05/06/2026 | H95: 16290.56 | I95: Pesos (MXN) | J95: 1 | K95: 16290.56 | L95: SERVICIO DE RECOLECCION DE VALORES | M95: 1 | N95: 14203.92 | P95: 14203.92 | Q95: 14203.92 | R95: SERVICIO | S95: Servicios | T95: Servicios | U95: SRV0000110 | V95: 73432 | W95: 66596 | X95: 60402 | Y95: COMPRAS | Z95: Isabel Cristina Chavez Ovalle | AA95: ES_Sabalo | AB95: Estacion Sabalo | AE95: PAGADA | AF95: Estacion Sabalo | AG95: PAGO A FACT. 028800542835 POR 22 SERVICIOS DE RECOLECCION DE VALORES, PROCESO DE EFECTIVO POR CADA MIL, RENTA DE CAJA SMART Y CUOTA DE RIESGOPOR MILES TRASLADADOS ESTACION SABALO, MAYO 2026. PROGRAMAR A PAGO EL 11/06/2026 | AH95: 14,203.92 | AI95: 0.00 | AJ95: 2,272.63 | AK95: 0.00 | AL95: 16,290.56 | AM95: 50299040051 | AN95: 12101030000 | AO95: 22201060000 | AP95: 20101021500
A96: PETROPLAZAS | B96: Petroplazas Corporativo | C96: CALLPICKER SAPI DE CV | D96: 147E4187148 | E96: 05/06/2026 | F96: 05/06/2026 | G96: 05/06/2026 | H96: 17202.46 | I96: Pesos (MXN) | J96: 1 | K96: 17202.46 | L96: SERVICIO/SOLUCIONES DE INTERNET | M96: 22 | N96: 229 | P96: 5038 | Q96: 5038 | R96: SERVICIO | S96: Servicios | T96: Servicios | U96: SRV0005522 | V96: 73444 | W96: 66697 | X96: 60485 | Y96: INFRAESTRUCTURA TECNOLOGICA | Z96: JUAN CARLOS MORENO OSUNA | AA96: ES_Corporativo | AB96: CC ADMINISTRACION | AE96: PAGADA | AF96: CC ADMINISTRACION | AG96: SERVICIO CALLPICKER SITIO PETROPLAZAS, JUNIO 2026 | AH96: 14,829.70 | AI96: 0.00 | AJ96: 2,372.76 | AK96: 0.00 | AL96: 17,202.46 | AM96: 50299040021 | AN96: 12101030000 | AO96: 20101021500
A97: PETROPLAZAS | B97: Petroplazas Corporativo | C97: Petroplazas, s.a. de c.v. | D97: FMPC187166 | E97: 05/06/2026 | F97: 05/06/2026 | G97: 05/06/2026 | H97: 2221.5 | I97: Pesos (MXN) | J97: 1 | K97: 2221.5 | L97: SERVICIO DE CARGA DE GASOLINA PREMIUM | M97: 24.878 | N97: 25.09 | P97: 624.18902 | Q97: 624.18902 | R97: SERVICIO | S97: Servicios | T97: Servicios | U97: SRV0005521 | V97: 73445 | W97: 66700 | X97: 60486 | Y97: ADMINISTRACION | Z97: CRISTOBAL IBARRA MANZANO | AA97: ES_Corporativo | AB97: CAMIONES Y TRANSPORTES | AE97: PAGADA | AF97: CAMIONES Y TRANSPORTES | AG97: Movimiento generado en automático por sistema. Proceso de Carga Masiva de Facturas | AH97: 1,922.71 | AI97: 0.00 | AJ97: 298.79 | AK97: 0.00 | AL97: 2,221.50 | AM97: 50299040017 | AN97: 12101030000 | AO97: 20101021500
A98: PETROPLAZAS | B98: Petroplazas Corporativo | C98: Petroplazas, s.a. de c.v. | D98: FDC149142 | E98: 05/06/2026 | F98: 05/06/2026 | G98: 05/06/2026 | H98: 557.38 | I98: Pesos (MXN) | J98: 1 | K98: 557.38 | L98: SERVICIO DE CARGA DE GASOLINA MAGNA | M98: 23.234 | N98: 20.76 | P98: 482.33784 | Q98: 482.33784 | R98: SERVICIO | S98: Servicios | T98: Servicios | U98: SRV0005519 | V98: 73447 | W98: 66713 | X98: 60488 | Y98: ADMINISTRACION | Z98: CRISTOBAL IBARRA MANZANO | AA98: ES_Corporativo | AB98: CAMIONES Y TRANSPORTES | AE98: PAGADA | AF98: CAMIONES Y TRANSPORTES | AG98: Movimiento generado en automático por sistema. Proceso de Carga Masiva de Facturas | AH98: 482.40 | AI98: 0.00 | AJ98: 74.98 | AK98: 0.00 | AL98: 557.38 | AM98: 50299040017 | AN98: 12101030000 | AO98: 20101021500
A99: PETROPLAZAS | B99: Petroplazas Corporativo | C99: Petroplazas, s.a. de c.v. | D99: FAECB62168 | E99: 05/06/2026 | F99: 05/06/2026 | G99: 05/06/2026 | H99: 324.95 | I99: Pesos (MXN) | J99: 1 | K99: 324.95 | L99: SERVICIO DE CARGA DE GASOLINA MAGNA | M99: 13.545 | N99: 20.76 | P99: 281.1942 | Q99: 281.1942 | R99: SERVICIO | S99: Servicios | T99: Servicios | U99: SRV0005518 | V99: 73448 | W99: 66715 | X99: 60489 | Y99: ADMINISTRACION | Z99: CRISTOBAL IBARRA MANZANO | AA99: ES_Corporativo | AB99: CAMIONES Y TRANSPORTES | AE99: PAGADA | AF99: CAMIONES Y TRANSPORTES | AG99: Movimiento generado en automático por sistema. Proceso de Carga Masiva de Facturas | AH99: 281.23 | AI99: 0.00 | AJ99: 43.72 | AK99: 0.00 | AL99: 324.95 | AM99: 50299040017 | AN99: 12101030000 | AO99: 20101021500
A100: PETROPLAZAS | B100: Petroplazas Corporativo | C100: SERVICIO J Y J S.A. DE C.V. | D100: FMJJ109304 | E100: 05/06/2026 | F100: 05/06/2026 | G100: 05/06/2026 | H100: 1398.45 | I100: Pesos (MXN) | J100: 1 | K100: 1398.45 | L100: SERVICIO DE CARGA DE COMBUSTIBLES UTILITARIOS | M100: 38.217 | N100: 20.76 | P100: 793.38492 | Q100: 793.38492 | R100: SERVICIO | S100: Servicios | T100: Servicios | U100: SRV0005520 | V100: 73446 | W100: 66705 | X100: 60487 | Y100: ADMINISTRACION | Z100: CRISTOBAL IBARRA MANZANO | AA100: ES_Corporativo | AB100: CAMIONES Y TRANSPORTES | AE100: PAGADA | AF100: CAMIONES Y TRANSPORTES | AG100: Movimiento generado en automático por sistema. Proceso de Carga Masiva de Facturas | AH100: 1,210.16 | AI100: 0.00 | AJ100: 188.29 | AK100: 0.00 | AL100: 1,398.45 | AM100: 50299040017 | AN100: 12101030000 | AO100: 20101021500
...

Sheet Resumen
A1: RESUMEN DE COMPARACIÓN SUCURSALES
A2: Generado: 23/06/2026 14:14:48
A4: Resultado | B4: Cantidad | C4: Porcentaje | D4: Descripción
A5: MATCH ✓ | B5: 314 | C5: 68.1% | D5: 1 sucursal detectada y coincide con Grupo CC
A6: MISMATCH ✗ | B6: 11 | C6: 2.4% | D6: 1 sucursal detectada pero NO coincide con Grupo CC
A7: DISTRIBUCIÓN | B7: 115 | C7: 24.9% | D7: 2+ sucursales detectadas — el total debe distribuirse entre ellas
A8: Sin sucursal | B8: 21 | C8: 4.6% | D8: No se detectó ninguna sucursal en las observaciones
A9: TOTAL | B9: 461 | C9: 100.0% | D9: Total de registros procesados

Sheet Resumen CuentasC
A1: RESUMEN DE CONCILIACIÓN CUENTAS CONTABLES
A2: Generado: 23/06/2026 14:14:48
A4: Resultado | B4: Cantidad | C4: Porcentaje | D4: Descripción
A5: Match ✓ | B5: 1517 | C5: 329.1% | D5: Cuenta contable de SIPP encontrada en el catálogo (gastos o proveedores)
A6: Mismatch ✗ | B6: 5 | C6: 1.1% | D6: SIPP devolvió una cuenta contable pero no existe en el catálogo
A7: Cuadre | B7: 3 | C7: 0.7% | D7: Cuenta de cuadre contable (_CUA-DRE-- u otra con letras) — no se busca en catálogo
A8: Sin dato SIPP | B8: 5 | C8: 1.1% | D8: SIPP no devolvió ninguna cuenta contable para esta factura
A9: TOTAL | B9: 461 | C9: 100.0% | D9: Total de registros procesados

Sheet Por Sucursal
A1: Sucursal | B1: MATCH ✓ | C1: MISMATCH ✗ | D1: DISTRIBUCIÓN | E1: Total
A2: 12 DE MAYO | B2: 5 | C2: 0 | D2: 2 | E2: 7
A3: AEROPUERTO | B3: 14 | C3: 0 | D3: 3 | E3: 17
A4: ALHUEY 1 | B4: 7 | C4: 0 | D4: 4 | E4: 11
A5: ALHUEY 2 | B5: 6 | C5: 1 | D5: 3 | E5: 10
A6: AU-144 | B6: 0 | C6: 0 | D6: 1 | E6: 1
A7: AU-151 | B7: 0 | C7: 0 | D7: 1 | E7: 1
A8: AU-152 | B8: 0 | C8: 0 | D8: 1 | E8: 1
A9: BELLAVISTA | B9: 7 | C9: 0 | D9: 1 | E9: 8
A10: CARDONES | B10: 10 | C10: 0 | D10: 2 | E10: 12
A11: CARRASCO | B11: 8 | C11: 0 | D11: 3 | E11: 11
A12: CERRITOS | B12: 8 | C12: 0 | D12: 3 | E12: 11
A13: COLOSIO | B13: 4 | C13: 0 | D13: 2 | E13: 6
... A59: ZONA NORTE | B59: 0 | C59: 0 | D59: 4 | E59: 4

Sheet Comparación
A1: Sucursal | B1: Factura | C1: Folio | D1: Grupo Centro de Costo | E1: CC OC | F1: Observaciones OC | G1: Sucursales Detectadas | H1: Resultado | J1: ESTACION QUE DEBE CARGARSE
A2: Alamos | B2: A4860 | C2: SRV0000068 | D2: ES_Alamos | E2: AUTOMOVIL - AU-151 | F2: Movimiento generado en automático por sistema. Proceso de Carga Masiva de Facturas | G2: AU-151 | H2: DISTRIBUCIÓN (UT)
A3: Petroplazas Corporativo | B3: 64F6E70 | C3: SRV0005503 | D3: ES_Corporativo | E3: CC ADMINISTRACION | F3: PROYECTO DE CONSTRUCCION DE ESTACION COLON. CFDI I01 CONSTRUCCION | G3: ES_Corporativo | H3: DISTRIBUCIÓN (Corp)
A4: Rosario | B4: FA23246 | C4: E000000121 | E4: Estatus Surtido | F4: COMPRA POR MATERIAL PARA STOK APOYOA DISPENSARIOS ESTACION ROSARIO, MAYO 2026. Nota; Facturar a inicios de junio por favor. ENTREGAR EN CEDIS MAZATLAN CON ISABLE VEGA. | G4: ROSARIO | H4: MATCH ✓
A5: Fatima | B5: A4861 | C5: SRV0000040 | D5: ES_Fatima | E5: AUTOMOVIL AU-131 | F5: Movimiento generado en automático por sistema. Proceso de Carga Masiva de Facturas | H5: Sin sucursal | J5: FATIMA
A6: Escuinapa | B6: FA23247 | C6: E000000182 | E6: Estatus Surtido | F6: COMPRA POR PISTOLA PARA DESP. GASOL. NEGRA DE 3/4" 11-B OPW SOLICTADAS PARA ESTACION ESCUINAPA, MAYO 2026. Nota, Facturar a inicios de junio ENTREGAR EN CEDIS MAZATLAN CON ISABEL VEGA. | G6: ESCUINAPA | H6: MATCH ✓
A7: AEROPUERTO | B7: M00646230 | C7: E000000282 | D7: ES_Aeropuerto | E7: ESTACION AEROPUERTO | F7: COMPRA POR 6 TUBO LED 36W T8 Y Y 10 TUBO LED 18W T8 120cm SOLICITADOS PARA ESTACION AEROPUERTO, JUNIO 2026. ENTREGAR EN CEDIS MAZATLAN CON ISABEL VEGA. | G7: AEROPUERTO | H7: MATCH ✓
A8: La Colorada | B8: MAZ4892 | C8: E000000183 | D8: ES_LA_COLORADA | E8: OFICINAS ADMINISTRATIVAS. | F8: FAVOR DE ENTREGAR EN ESTACION LA COLORADA CON EL SUPERVISOR AL DOMICILIO CALLE LATERAL CARRETERA SN, COL. NUEVO HERMOSILLO, HERMOSILLO, SONORA, CP. 83296. MATERIAL DE LIMPIEZA DEL MES DE JUNIO 2026. | G8: LA COLORADA | H8: MATCH ✓
A9: Fatima | B9: A6054 | C9: E000000119 | D9: ES_Fatima | E9: Estacion Fatima | F9: CORRESPONDE A LA FACTURA A6054. CAMARA DE SEGURIDAD Y ADITAMIENTO EN ESTACION FATIMA. | G9: FATIMA | H9: MATCH ✓
A10: Petroplazas Corporativo | B10: F701219 | C10: SRV0005507 | D10: ES_Corporativo | E10: GASTOS GENERALES | F10: PAGO DE LA FACT. 19 POR EL ARRENDAMIENTO DE TERRENO DE ESTACION EL DIEZ, (LA O.C. SE HIZO POR 12 MESES, LOS CUALES SE IRAN PAGANDO MES A MES). PROGRAMAR A PAGO PARA EL 04/06/2026. | G10: EL DIEZ | H10: MISMATCH ✗ | J10: EL DIEZ
A11: CEDIS Mazatlán | B11: 462FC | C11: SRV0000604 | D11: EST_EL_CONCHI | E11: Escuinapa | F11: SERVICIO RED JOSHUA SITIO MAZATLAN, JUNIO 2026 | H11: Sin sucursal | J11: MAZATLAN GENERAL Y SUR
A12: Petroplazas Corporativo | B12: I40 | C12: SRV0005504 | D12: ES_Corporativo | E12: CC ADMINISTRACION | F12: CORRESPONDE A LA FACTURA 40. SERVICIO DE MANTENIMIENTO Y DESARROLLO DE SOFTWARE DE CORPORATIVO DIVISION GASOLINERAS. | G12: ES_Corporativo | H12: DISTRIBUCIÓN (Corp)
A13: CEDIS Culiacán | B13: E018C998 | C13: E000000270 | E13: Estatus Surtido | F13: FAVOR DE ENTREGAR EN CEDIS CULIACAN CON DIEGO. PANTALON DESPACHADOR AZUL PARA STOCK DE ZONA CLN, ANGOSTURA Y NORTE. | G13: ZONA CLN | H13: DISTRIBUCIÓN (1)
A14: CEDIS Culiacán | B14: B0C2F997 | C14: E000000271 | E14: Estatus Surtido | F14: FAVOR DE ENTREGAR EN CEDIS CULIACAN CON DIEGO. PANTALON DESPACHADOR AZUL PARA STOCK DE ZONA CLN, ANGOSTURA Y NORTE. | G14: ZONA CLN | H14: DISTRIBUCIÓN (1)
A15: Revolucion | B15: A1549 | C15: E000000153 | D15: ES_Revolucion | E15: Baños publicos | F15: FAVOR DE ENTREGAR EN ESTACION REVOLUCION CON EL SUPERVISOR AL DOMICILIO BLVD. LUIS DONAL. COLOSIO NO. 615, COL. REVOLUCION MEXICANA, GUASAVE, SINALOA, C.P. 81016. MATERIAL DE LIMPIEZA DEL MES DE JUNIO 2026. | G15: REVOLUCION / COLOSIO | H15: DISTRIBUCIÓN (2)
A16: CEDIS Culiacán | B16: CCCEC | C16: SRV0000460 | D16: PERICOS | E16: CUAUHTEMOC | F16: SERVICIO RED JOSHUA SITIO CULIACAN, JUNIO 2026 | H16: Sin sucursal | J16: CUAHUTEMOC, PARQUES, PERICOS Y PERICOS CENTRO
A17: La Colorada | B17: GHMO004237 | C17: SRV0000194 | D17: ES_LA_COLORADA | E17: ESTACION LA COLORADA | F17: CORRESPONDE A LA FACTURA GHMO004237. SERVICIO DE GAS LP PARA AREA DE PENSION DE ESTACION LA COLORADA. | G17: LA COLORADA | H17: MATCH ✓
A18: Forjadores | B18: 72C4F | C18: SRV0000296 | D18: ES_FORJADORES | E18: D. ADMINISTRACION | F18: SERVICIO RED JOSHUA SITIO PAZ, JUNIO 2026 | H18: Sin sucursal | J18: LA PAZ
A19: SANTA ROSA | B19: MZF445034 | C19: E000000138 | D19: ES_SANTA_ROSA | E19: BAÑOS AL PÚBLICO | F19: FAVOR DE ENTREGAR EN ESTACION SANTA ROSA CON EL SUPERVISOR. MATERIAL DE LIMPIEZA DEL MES DE JUNIO 2026. | G19: SANTA ROSA | H19: MATCH ✓
A20: CEDIS Mazatlán | B20: 20251611 | C20: E000000461 | E20: Estatus Surtido | F20: FAVOR DE ENTREGAR EN CEDIS MAZATLAN CON ISABEL. PANTALON DE VESTIR CABALLERO AZUL MARINO PARA STOCK DE CEDIS MAZATLAN. | H20: Sin sucursal | J20: MAZATLAN GENERAL
A21: CEDIS Mazatlán | B21: F68961 | C21: E000000462 | E21: Estatus Surtido | F21: FAVOR DE ENTREGAR EN CEDIS MAZATLAN CON ISABEL AL DOMICILIO AZALEA NO. 4901, COL. RICARDO FLORES MAGON, C.P. 82190, MAZATLAN, SINALOA. GORRA ACRILANA AMARILLO / REY C/BORDADO FTE REDPETROIL PARA STOCK DE CEDIS MAZATLAN PARA ESTACIONES SABALO, AEROPUERTO, CONCORDIA, HABAL, 12 DE MAYO, FORESTA, URBIVILLA, GRIJALVA, ROSARIO Y ESCUINAPA. | G21: 12 DE MAYO / AEROPUERTO / ESCUINAPA / CONCORDIA / URBIVILLA / GRIJALVA / FORESTA / ROSARIO / SABALO / HABAL | H21: DISTRIBUCIÓN (10)
A22: SANTA ROSA | B22: BCR672 | C22: E000000139 | D22: ES_SANTA_ROSA | E22: BAÑOS AL PÚBLICO | F22: FAVOR DE ENTREGAR EN ESTACION SANTA ROSA CON EL SUPERVISOR. MATERIAL DE LIMPIEZA DEL MES DE JUNIO 2026. | G22: SANTA ROSA | H22: MATCH ✓
A23: Alamos | B23: FDF0430176 | C23: E000000128 | D23: CC Empleados | E23: CC Jose Carlos Valdez Nuñez | F23: FAVOR DE ENTREGAR EN CEDIS MAZATLAN CON ISABEL. CARGADOR LENOVO ADL45WCC PARA LAPTOP LENOVO IDEAPAD 320 DE ING. JOSE CARLOS JEFE DE PISO ZONA NORTE. | G23: ZONA NORTE | H23: DISTRIBUCIÓN (1)
A24: Sabalo | B24: M00646285 | C24: E000000207 | D24: ES_Sabalo | E24: CC OPERACIONES | F24: CORRESPONDE A LA FACTURA M-00646285. MATERIAL ELECTRICO PARA ESTACION SABALO. | G24: SABALO | H24: MATCH ✓
A25: SANTA ROSA | B25: MZF445096 | C25: E000000141 | D25: ES_SANTA_ROSA | E25: CC OPERACIONES | F25: CORRESPONDE A LA FACTURA MZF445096. EMPLAYE PARA ESTACION SANTA ROSA. | G25: SANTA ROSA | H25: MATCH ✓
A26: La Foresta | B26: MZF445025 | C26: E000000180 | D26: ES_La Foresta | E26: CC OPERACIONES | F26: FAVOR DE ENTREGAR EN ESTACION FORESTA CON EL SUPERVISOR. MATERIAL DE LIMPIEZA DEL MES DE JUNIO 2026. | G26: FORESTA | H26: MATCH ✓
A27: Fatima | B27: A1551 | C27: E000000123 | D27: ES_Fatima | E27: Baños publicos | F27: FAVOR DE ENTREGAR EN ESTACION FATIMA CON EL SUPERVISOR AL DOMICILIO ANGEL FLORES NTE. 983 COL. CENTRO, AHOME LOS MOCHIS, SINALOA, C.P. 81200. MATERIAL DE LIMPIEZA DEL MES DE JUNIO 2026. | G27: FATIMA | H27: MATCH ✓
A28: Alamos | B28: A1550 | C28: E000000130 | D28: ES_Alamos | E28: Baños publicos | F28: FAVOR DE ENTREGAR EN ESTACION ALAMOS CON EL SUPERVISOR AL DOMICILIO BLVD. MACARIO GAXIOLA NO. 1500 SUR, FRACC. LOS ALAMOS 1, AHOME LOS MOCHIS, SINALOA, C.P. 81280. MATERIAL DE LIMPIEZA DEL MES DE JUNIO 2026. | G28: LOS ALAMOS | H28: MATCH ✓
A29: Petroplazas Corporativo | B29: 2C6A1 | C29: SRV0005508 | D29: ES_Corporativo | E29: CC Administracion | F29: SERVICIO RED JOSHUA SITIO NAS, JUNIO 2026 | G29: ES_Corporativo | H29: DISTRIBUCIÓN (Corp)
A30: ALHUEY1 | B30: FC26295 | C30: E000000195 | D30: ES_ALHUEY1 | E30: Estacion Alhuey 1 | F30: COMPRA DE 3 PATITAS (FUSIBLE) PARA VALVULA SHUT OFF PARA ESTACION ALHUEY 1. (ENTREGAR EN ALMACEN DE REFACCIONES DE CAMPO EL DIEZ). Y FACTURAR CON 1 DE JUNIO. | G30: ALHUEY 1 / EL DIEZ | H30: DISTRIBUCIÓN (2)
A31: Dos Valles | B31: A1548 | C31: E000000131 | D31: ES_Dos Valles | E31: Baños publicos | F31: FAVOR DE ENTREGAR EN ESTACION DOS VALLE CON EL SUPERVISOR AL DOMICILIO BLVD. LUIS DONALDO COLOSIO NO. 264, COL. OCORO, GUASAVE, SINALOA, C.P. 81010. MATERIAL DE LIMPIEZA DEL MES DE JUNIO 2026. | G31: DOS VALLES / COLOSIO | H31: DISTRIBUCIÓN (2)
A32: Fatima | B32: 7659F | C32: E000000121 | D32: ES_Fatima | E32: Zona de despacho | F32: FAVOR DE ENTREGAR EN CEDIS MAZATLAN CON ISABEL. EQUIPO CUBOT KINGKONG PARA ESTACION FATIMA. | G32: FATIMA | H32: MATCH ✓
A33: CERRITOS | B33: A62F830168 | C33: E000000197 | D33: ES_Cerritos | E33: A. BAÑOS AL PUBLICO | F33: COMPRA POR VENTILADOR MYTEK DE PARED 20” SOLICITADO PARA ESTACION CERRITOS Nota: Facturar a inicios de junio y Uso de cfdi gastos en general. ENTREGAR EN CEDIS MAZATLAN CON ISABEL VEGA. | G33: CERRITOS | H33: MATCH ✓
... A36: Sabalo | B36: FIA177489 | C36: E000000204 | D36: ES_Sabalo | E36: CC OPERACIONES | F36: COMPRA POR WC BLANCO AHORRADOR REDONDO MODELO ECO ACUACER SOLICITADO PARA ESTACION SABALO, JUNIO 2026. ENTREGAR EN CEDIS MAZATLAN (almacen flores magon) CON ISABEL VEGA. | G36: FLORES MAGON / SABALO | H36: DISTRIBUCIÓN (2)
A37: Sabalo | B37: B5E1530167 | C37: E000000203 | E37: Estatus Surtido | F37: COMPRA POR 2 VENTILADORES MYTEK DE PARED 20” SOLICITADOS PARA ESTACION SABALO, Nota, facturar a inicios de junio y uso de cfdi gastos en general. ENTREGAR EN CEDIS MAZATLAN CON ISABEL VEGA. | G37: SABALO | H37: MATCH ✓
A38: URBIVILLA | B38: BCR674 | C38: E000000083 | D38: URBIVILLA | E38: ESTACION URBIVILLA | F38: FAVOR DE ENTREGAR EN ESTACION URBIVILLA CON EL SUPERVISOR. MATERIAL DE LIMPIEZA DEL MES DE JUNIO 2026. AROMATIZANTE BRISA DE MAR | G38: URBIVILLA | H38: MATCH ✓
A39: 12 de Mayo | B39: MZF445030 | C39: E000000168 | D39: ES_12 de Mayo | E39: BAÑOS ESTACION | F39: FAVOR DE ENTREGAR EN ESTACION 12 DE MAYO CON EL SUPERVISOR. MATERIAL DE LIMPIEZA DEL MES DE JUNIO 2026. | G39: 12 DE MAYO | H39: MATCH ✓
A40: URBIVILLA | B40: MZF445026 | C40: E000000082 | D40: URBIVILLA | E40: ESTACION URBIVILLA | F40: FAVOR DE ENTREGAR EN ESTACION URBIVILLA CON EL SUPERVISOR. MATERIAL DE LIMPIEZA DEL MES DE JUNIO 2026. | G40: URBIVILLA | H40: MATCH ✓
A41: Flores Magon | B41: MZF445027 | C41: E000000436 | D41: ES_Flores Magon | E41: BAÑOS ESTACION | F41: FAVOR DE ENTREGAR EN ESTACION FLORES MAGON CON EL SUPERVISOR. MATERIAL DE LIMPIEZA DEL MES DE JUNIO 2026. | G41: FLORES MAGON | H41: MATCH ✓
A42: GRIJALVA | B42: MZF445032 | C42: E000000156 | D42: GRIJALVA | E42: ESTACION GRIJAVA | F42: FAVOR DE ENTREGAR EN ESTACION GRIJALVA CON EL SUPERVISOR. MATERIAL DE LIMPIEZA DEL MES DE JUNIO 2026. | G42: GRIJALVA | H42: MATCH ✓
A43: 12 de Mayo | B43: BCR673 | C43: E000000169 | D43: ES_12 de Mayo | E43: BAÑOS ESTACION | F43: FAVOR DE ENTREGAR EN ESTACION 12 DE MAYO CON EL SUPERVISOR. MATERIAL DE LIMPIEZA DEL MES DE JUNIO 2026. | G43: 12 DE MAYO | H43: MATCH ✓
A44: Madero | B44: FAC51010416 | C44: E000000104 | D44: ES_MADERO | E44: ZONA DE DESPACHO | F44: COMPRA DE MANGUERA PARA DESCARGA DE COMBUSTIBLE DE LA ESTACION MADERO. ENTREGAR EN LA ESTACION (BLVD. FRANCISCO I. MADERO 693 PTE. COL. CENTRO, CULIACAN, SIN. C.P. 80000. | G44: MADERO | H44: MATCH ✓
A45: Bellavista | B45: AA10863 | C45: E000000094 | D45: ES_Bellavista | E45: Estacion BellaVista | F45: COMPRA DE PINTURA PARA EL MTTO. DE LAS REJILLAS DE TRAMPAS DE LA ESTACION BELLAVISTA. (ENTREGAR EN LA ESTACION EL PAPALOTE, CON UN PAPEL QUE DIGA QUE ES DE BELLAVISTA). | G45: BELLAVISTA / PAPALOTE | H45: DISTRIBUCIÓN (2)
A46: Bellavista | B46: 9AD76853 | C46: SRV0000057 | D46: ES_Bellavista | E46: CUARTO DE MÁQUINAS | F46: PAGO POR SERVICIO DE MANTENIMIENTO PREVENTIVO A PLANTA DE EMERGENCIA DE ESTACION BELLAVISTA. | G46: BELLAVISTA | H46: MATCH ✓
A47: Petroplazas Corporativo | B47: B4765 | C47: SRV0005509 | D47: ES_Corporativo | E47: GASTOS GENERALES | F47: SERVICIO DE IMPRESION DE ETIQUETAS MAGNA Y PREMIUM PARA ESTACION SANTA MONICA. | G47: ES_Corporativo | H47: DISTRIBUCIÓN (Corp)
A48: Playas | B48: MAZAFA600048339 | C48: E000000230 | D48: ES_PLAYAS | E48: CC OPERACIONES | F48: CORRESPONDE A LA FACTURA MAZAFA600048339. ACEITE PARA PUNTO DE VENTA EN ESTACION PLAYAS. | G48: PLAYAS | H48: MATCH ✓
A49: JUAN CARRASCO | B49: BCR679 | C49: E000000106 | D49: ES_Juan_Carrasco | E49: A. CUARTO DE LIMPIOS | F49: FAVOR DE ENTREGAR EN ESTACION JUAN CARRASCO CON EL SUPERVISOR. MATERIAL DE LIMPIEZA DEL MES DE JUNIO 2026. | G49: CARRASCO | H49: MATCH ✓
... A54: El Delfin | B54: 96C8B806 | C54: SRV0000043 | D54: ES_El_Delfin | E54: CONSTRUCCIÓN INTEGRAL INICIAL DE LA ESTACIÓN DE SERVICIO | F54: SERVICIO DE CONSTRUCCION DE PASILLO EN ESTACION EL DELFIN. CFDI I01 CONSTRUCCION | G54: EL DELFIN | H54: MATCH ✓
A55: EQUIPO DE COMPUTO | B55: E816030178 | C55: E000000184 | E55: Estatus Surtido | F55: FAVOR DE ENTREGAR EN CORPORATIVO CENTRO CON CARLITOS DE SISTEMAS. LAPTOP ASUS EXPERTBOOK P1403CVA-158G512- P1 CORE I5 13420H 16GB 512GB 2280 SSD PANTALLA DE 14.0" WIN11 PRO BLACK WI-FI 6E GARANTIA 3 AÑOS Y DAÑOS ACCIDENTALES INCLUYE 1 MOUSE LOGITECH M170 DE REGALO. CFDI I04. | H55: Sin sucursal | J55: ALAMOS
A56: CEDIS Mazatlán | B56: GZ0002684 | C56: E000000465 | E56: Estatus Surtido | F56: FAVOR DE ENTREGAR EN CEDIS MAZATLAN CON ISABEL. PANTALON DE VESTIR DAMA AZUL MARINO PARA STOCK DE CEDIS MAZATLAN. | H56: Sin sucursal | J56: MAZATLAN GENERAL
A57: Playas | B57: 028800542831 | C57: SRV0000107 | D57: ES_PLAYAS | E57: ESTACION PLAYAS | F57: PAGO A FACT. 028800542831 POR 22 SERVICIOS DE RECOLECCION DE VALORES, PROCESO DE EFECTIVO POR CADA MIL, RENTA DE CAJA SMART Y CUOTA DE RIESGOPOR MILES TRASLADADOS ESTACION PLAYAS, MAYO 2026. PROGRAMAR A PAGO EL 11/06/2026 | G57: PLAYAS | H57: MATCH ✓
A58: JUAN CARRASCO | B58: 028800542829 | C58: SRV0000102 | D58: ES_Juan_Carrasco | E58: CC ADMINISTRACION | F58: CORRESPONDE A LA FACTURA 28800542829. SERVICIO DE RECOLECCION DE VALORES, PROCESO DE EFECTIVO Y CAJERO DEL MES DE MAYO 2026 DE ESTACION JUAN CARRASCO. | G58: CARRASCO | H58: MATCH ✓
A59: Playas | B59: MZ225564 | C59: E000000234 | D59: ES_PLAYAS | E59: CC OPERACIONES | F59: MATERIAL DE PAPELERIA SOLICITADO PARA ESTACION PLAYAS, JUNIO 2026. ENTREGAR ENE STACION PLAYAS CON SUPERVISOR EN TURNO. | G59: PLAYAS | H59: MATCH ✓
A60: CEDIS Culiacán | B60: AA43839 | C60: SRV0000461 | D60: CUAUHTEMOC | E60: REVOLUCION | F60: CORRESPONDE A LA FACTURA AA43839. SERVICIO DE IMPRESION DE CUPONERAS CITICINEMAS DE JUNIO 2026 DE ESTACION DOS VALLE, REVOLUCION Y CUAUHTEMOC. | G60: REVOLUCION / CUAUHTEMOC / DOS VALLES | H60: DISTRIBUCIÓN (3)
A61: CEDIS Mazatlán | B61: 02FF93270 | C61: SRV0000606 | D61: Colosio | E61: Foresta | F61: CORRESPONDE A LA FACTURA 3270. CONSULTORIA Y ELABORACION DOCUMENTAL DE LA STPS DEL MES DE JUNIO 2026 ZONA MZT 3. | G61: ZONA MZT 3 | H61: DISTRIBUCIÓN (1)
A62: Forjadores | B62: EC59F3277 | C62: SRV0000297 | D62: ES_FORJADORES | E62: D. ADMINISTRACION | F62: CORRESPONDE A LA FACTURA 3277. CONSULTORIA Y ELABORACION DOCUMENTAL DE LA STPS DEL MES DE JUNIO 2026 PARA ESTACION FORJADORES. | G62: FORJADORES | H62: MATCH ✓
A63: Playas | B63: Z92186 | C63: E000000232 | D63: ES_PLAYAS | E63: CC OPERACIONES | F63: 2 CAJAS DE ROLLOS TERMICOS SOLICITADOS PARA ESTACION PLAYAS, JUNIO 2026. ENTREGAR EB ESTACION PLAYAS CON SUPERVISOR EN TURNO. | G63: PLAYAS | H63: MATCH ✓
A64: LAS HABAS | B64: 028800542827 | C64: SRV0000105 | D64: ES_LAS_HABAS | E64: ESTACION LAS HABAS | F64: PAGO A FACT. 028800542827 POR 22 SERVICIO DE RECOLECCION DE VALORES, PROCESOS DE EFECTIVO POR CADA MIL, RENTA DE CAJA SMART Y CUOTA DE RIESGO ESTACION HABAS, MAYO 2026. PROGRAMAR A PAGO EL 11/06/2026 | G64: LAS HABAS | H64: MATCH ✓
A65: SANTA ROSA | B65: MZ225565 | C65: E000000144 | D65: ES_SANTA_ROSA | E65: CUARTO DE CORTES | F65: FAVOR DE ENTREGAR EN ESTACION SANTA ROSA CON EL SUPERVISOR. PAPELERIA DEL MES DE JUNIO 2026. | G65: SANTA ROSA | H65: MATCH ✓
A66: CEDIS Mazatlán | B66: BAE1E3271 | C66: SRV0000607 | D66: Grijalva | E66: Juan Carrasco | F66: CORRESPONDE A LA FACTURA 3271. CONSULTORIA Y ELABORACION DOCUMENTAL DE LA STPS DEL MES DE JUNIO 2026 ZONA MZT 4. | G66: ZONA MZT 4 | H66: DISTRIBUCIÓN (1)
A67: Pericos centro | B67: TME357591 | C67: E000000099 | D67: ES_PERICOS_CENTRO | E67: CC ADMINISTRACION | F67: COMPRA DE ROLLO TERMICO (80X70) PARA DISPENSARIOS DE LA ESTACION PERICOS CENTRO. ENTREGAR EN: BLVD. ENRIQUE FELIX CASTRO PTE. 3029, COL. INFONAVIT HUMAYA, CULIACAN, SINALOA, C.P. 80020. CON NOTA DE QUE ES DE "PERICOS CENTRO". | G67: PERICOS | H67: MATCH ✓
A68: SANTA ROSA | B68: 028800542821 | C68: SRV0000082 | D68: ES_SANTA_ROSA | E68: CC ADMINISTRACION | F68: CORRESPONDE A LA FACTURA 28800542821. SERVICIO DE RECOLECCION DE VALORES, PROCESO DE EFECTIVO Y CAJERO DEL MES DE MAYO 2026 DE ESTACION SANTA ROSA. | G68: SANTA ROSA | H68: MATCH ✓
... A71: EL CONCHI | B71: M0001912 | C71: SRV0000029 | D71: ES_El_Conchi | E71: OPERACIONES | F71: CORRESPONDE A LA FACTURA M0001912. SERVICIO DE CORREGIR FALLA EN COMUNICACION DE SONDA DE MAGNA Y MATERIAL PARA TAPAR RANURAS DE ESTACION EL CONCHI. | G71: EL CONCHI | H71: MATCH ✓
A72: GRIJALVA | B72: MZ225582 | C72: E000000158 | E72: Estatus Surtido | F72: FAVOR DE ENTREGAR EN ESTACION GRIJALVA CON EL SUPERVISOR. PAPELERIA DEL MES DE JUNIO 2026. | G72: GRIJALVA | H72: MATCH ✓
A73: El Papalote | B73: TME357587 | C73: E000000109 | D73: ES_El_Papalote | E73: Estacion El Papalote | F73: COMPRA DE ROLLO TERMICO (80X70) PARA DISPENSARIOS DE LA ESTACION EL PAPALOTE. ENTREGAR EN: AV. ALVARO OBREGON NO. 3742, COL. 6 DE ENERO, CULIACAN, SIN., C.P. 80010. | G73: PAPALOTE | H73: MATCH ✓
A74: COLOSIO | B74: MZF445024 | C74: E000000153 | D74: ES_Colosio | E74: CC GERENCIA DE OPERACIONES | F74: FAVOR DE ENTREGAR EN ESTACION COLOSIO CON EL SUPERVISOR. MATERIAL DE LIMPIEZA DEL MES DE JUNIO 2026. | G74: COLOSIO | H74: MATCH ✓
A75: La Foresta | B75: BCR677 | C75: E000000182 | D75: ES_La Foresta | E75: CC OPERACIONES | F75: FAVOR DE ENTREGAR EN ESTACION FORESTA CON EL SUPERVISOR. MATERIAL DE LIMPIEZA DEL MES DE JUNIO 2026. | G75: FORESTA | H75: MATCH ✓
A76: AEROPUERTO | B76: MZ225562 | C76: E000000286 | D76: ES_Aeropuerto | E76: ESTACION AEROPUERTO | F76: CAJA DE HOJAS BLANCAS SOLITADAS PARA ESTACION AEROPUERTO, JUNIO 2026. ENTREGAR EN CEDIS MAZATLAN CON ISABEL VEGA. | G76: AEROPUERTO | H76: MATCH ✓
A77: MUNICH II | B77: MZF445023 | C77: E000000177 | E77: Estatus Surtido | F77: FAVOR DE ENTREGAR EN ESTACION MUNICH II CON EL SUPERVISOR. MATERIAL DE LIMPIEZA DEL MES DE JUNIO 2026. | G77: MUNICH II | H77: MATCH ✓
A78: Flores Magon | B78: MZ225568 | C78: E000000441 | D78: ES_Flores Magon | E78: OFICINAS ADMINISTRATIVAS | F78: FAVOR DE ENTREGAR EN ESTACION FLORES MAGON CON EL SUPERVISOR. PAPELERIA DEL MES DE JUNIO 2026. | G78: FLORES MAGON | H78: MATCH ✓
A79: La Marina | B79: MZ225573 | C79: E000000231 | D79: ES_La Marina | E79: CC OPERACIONES | F79: MATERIAL DE PAPELERIA SOLICITADO PARA ESTACION LA MARINA, JUNIO 2026. ENTREGAR EN ESTACION MARINA CON SUPERVUSOR EN TURNO. | G79: MARINA | H79: MATCH ✓
A80: Flores Magon | B80: BCR676 | C80: E000000437 | D80: ES_Flores Magon | E80: BAÑOS ESTACION | F80: FAVOR DE ENTREGAR EN ESTACION FLORES MAGON CON EL SUPERVISOR. MATERIAL DE LIMPIEZA DEL MES DE JUNIO 2026. AROMA BRISA DE MAR | G80: FLORES MAGON | H80: MATCH ✓
A81: MUNICH II | B81: 028800542832 | C81: SRV0000077 | D81: ES_MunichII | E81: CC ADMINISTRACION | F81: CORRESPONDE A LA FACTURA 28800542832. SERVICIO DE RECOLECCION DE VALORES, PROCESO DE EFECTIVO DEL MES DE MAYO 2026 DE ESTACION MUNICH II. | G81: MUNICH II | H81: MATCH ✓
A82: La Foresta | B82: MZ225566 | C82: E000000183 | D82: ES_La Foresta | E82: CC OPERACIONES | F82: FAVOR DE ENTREGAR EN ESTACION FORESTA CON EL SUPERVISOR. PAPELERIA DEL MES DE JUNIO 2026. | G82: FORESTA | H82: MATCH ✓
A83: MUNICH II | B83: TME357497 | C83: E000000178 | E83: Estatus Surtido | F83: FAVOR DE ENTREGAR EN ESTACION MUNICH II CON EL SUPERVISOR AL DOMICILIO AV. MUICH II, 2402, LIDERES UNIDOS, MAZATLAN, SINALOA, CP. 82134. 02 CAJAS DE 75 C/U. DE ROLLOS TERMICOS 80X70 DEL MES DE JUNIO 2026. | G83: MUNICH II | H83: MATCH ✓
A84: La Marina | B84: C9031 | C84: SRV0000163 | D84: ES_La Marina | E84: Estacion La Marina | F84: PAGO A FACT. C 9031 POR SERVICIO DE RECOLECCION DE BASURA ESTACION MARINA, JUNIO 2026. PROGRAMAR A PAGO EL 09/06/2026 | G84: MARINA | H84: MATCH ✓
A85: ALHUEY2 | B85: TME357624 | C85: E000000131 | D85: ALHUEY 2 | E85: ESTACION | F85: COMPRA DE ROLLO TERMICO (80X70) PARA DISPENSARIOS DE LA ESTACION ALHUEY 2. ENTREGAR EN: AUTOPISTA CULIACAN-LOS MOCHIS KM. 110.5, ALHUEY, ANGOSTURA, SINALOA, C.P. 81610. | G85: ALHUEY 2 / ALHUEY 1 | H85: DISTRIBUCIÓN (2)
A86: REAL DEL VALLE | B86: MZ225563 | C86: E000000169 | D86: REAL DE VALLE | E86: ESTACION REAL DEL VALLE | F86: MATERIAL DE PAPELERIA SOLICITADO PARA ESTACION REAL DEL VALLE, JUNIO 2026. ENTREGAR EN ESTACION REAL DEL VALLE CON SUPERVISOR EN TURNO. | G86: REAL DEL VALLE | H86: MATCH ✓
A87: CARDONES | B87: A19123 | C87: E000000226 | D87: ES_Cardones | E87: CC OPERACIONES | F87: CORRESPONDE A LA FACTURA AB2275D6. MATERIAL PARA DISPENSARIOS DE AIRE DE ESTACION CARDONES. | G87: CARDONES | H87: MATCH ✓
A88: CERRITOS | B88: 028800542822 | C88: SRV0000070 | D88: ES_Cerritos | E88: ESTACION CERRITOS | F88: PAGO A FACT. 028800542822 POR 21 SERVICIO DE RECOLECCION DE VALORES, PROCESOS DE EFECTIVO POR CADA MIL, RENTA DE CAJA SMART Y CUOTA DE RIESGO ESTACION CERRITOS, MAYO 2026. PROGRAMAR A PAGO EL 11/06/2026 | G88: CERRITOS | H88: MATCH ✓
A89: La Marina | B89: 028800542830 | C89: SRV0000162 | D89: ES_La Marina | E89: Estacion La Marina | F89: PAGO A FACT. 028800542830 POR 17 SERVICIOS DE RECOLECCION DE VALORES, PROCESO DE EFECTIVO POR CADA MIL, RENTA DE CAJA SMART Y CUOTA DE RIESGO MILES TRASLADADOS ESTACION MARINA, MAYO 2026. PROGRAMAR A PAGO EL 11/06/2026 | G89: MARINA | H89: MATCH ✓
A90: CERRITOS | B90: MZ225575 | C90: E000000199 | D90: ES_Cerritos | E90: A. CUARTO DE CORTES | F90: COMPRA POR PAPELERIA SOLICITADA PARA ESTACION CERRITOS, JUNIO 2026. ENTREGAR EN ESTACION CERRITOS CON SUPERV ISOR EN TURNO. | G90: CERRITOS | H90: MATCH ✓
A91: Bellavista | B91: TME357590 | C91: E000000096 | D91: ES_Bellavista | E91: Estacion BellaVista | F91: COMPRA DE ROLLO TERMICO (80X70) PARA DISPENSARIOS DE LA ESTACION BELLAVISTA. ENTREGAR EN: CARRETERA A CULIACANCITO NO. 11000 PTE., BELLAVISA, CULIACAN, SINALOA, C.P. 80301. | G91: BELLAVISTA | H91: MATCH ✓
A92: Sabalo | B92: MZ225574 | C92: E000000209 | D92: ES_Sabalo | E92: CC OPERACIONES | F92: MATERIAL DE PAPELERIA SOLICITADO PARA ESTACION SABALO, JUNIO 2026. ENTREGAR EN CEDIS MAZATLAN CON ISAB EL VEGA. | G92: SABALO | H92: MATCH ✓
A93: HABAL | B93: A19124 | C93: E000000193 | D93: ES_Habal | E93: CC OPERACIONES | F93: CORRESPONDE A LA FACTURA A2953C14. MATERIAL PARA DISPENSARIOS DE AIRE DE ESTACION HABAL. | G93: HABAL | H93: MATCH ✓
A94: Humaya | B94: TME357592 | C94: E000000115 | D94: ES Humaya | E94: ZONA DE DESPACHO | F94: COMPRA DE ROLLO TERMICO (80X70) PARA DISPENSARIOS DE LA ESTACION HUMAYA. ENTREGAR EN: BLVD. ENRIQUE FELIX CASTRO PTE. 3029, COL. INFONAVIT HUMAYA, CULIACAN, SINALOA, C.P. 80020. | G94: HUMAYA | H94: MATCH ✓
A95: Sabalo | B95: 028800542835 | C95: SRV0000110 | D95: ES_Sabalo | E95: Estacion Sabalo | F95: PAGO A FACT. 028800542835 POR 22 SERVICIOS DE RECOLECCION DE VALORES, PROCESO DE EFECTIVO POR CADA MIL, RENTA DE CAJA SMART Y CUOTA DE RIESGOPOR MILES TRASLADADOS ESTACION SABALO, MAYO 2026. PROGRAMAR A PAGO EL 11/06/2026 | G95: SABALO | H95: MATCH ✓
... A100: Petroplazas Corporativo | B100: FMJJ109304 | C100: SRV0005520 | D100: ES_Corporativo | E100: CAMIONES Y TRANSPORTES | F100: Movimiento generado en automático por sistema. Proceso de Carga Masiva de Facturas | G100: ES_Corporativo | H100: DISTRIBUCIÓN (Corp)
A101: Rosario | B101: MZ225567 | C101: E000000122 | E101: Estatus Surtido | F101: HOJAS BLANCAS SOLICITADAS PARA ESTA CION ROSARIO, JUNIO 2026. ENTREGAR EN CEDIS MAZATLAN CON ISABEL VEGA. | G101: ROSARIO | H101: MATCH ✓
A102: Petroplazas Corporativo | B102: FMRV240415 | C102: SRV0005513 | D102: ES_Corporativo | E102: CAMIONES Y TRANSPORTES | F102: Movimiento generado en automático por sistema. Proceso de Carga Masiva de Facturas | G102: ES_Corporativo | H102: DISTRIBUCIÓN (Corp)
A103: Petroplazas Corporativo | B103: FOBR89436 | C103: SRV0005523 | D103: ES_Corporativo | E103: CAMIONES Y TRANSPORTES | F103: Movimiento generado en automático por sistema. Proceso de Carga Masiva de Facturas | G103: ES_Corporativo | H103: DISTRIBUCIÓN (Corp)
A104: Petroplazas Corporativo | B104: FMCA159015 | C104: SRV0005512 | D104: ES_Corporativo | E104: CAMIONES Y TRANSPORTES | F104: Movimiento generado en automático por sistema. Proceso de Carga Masiva de Facturas | G104: ES_Corporativo | H104: DISTRIBUCIÓN (Corp)
A105: Flores Magon | B105: Z92187 | C105: E000000438 | D105: ES_Flores Magon | E105: OFICINAS ADMINISTRATIVAS | F105: FAVOR DE ENTREGAR EN ESTACION FLORES MAGON CON EL SUPERVISOR. ROLLO TERMICO 80X70 DEL MES DE JUNIO 2026. | G105: FLORES MAGON | H105: MATCH ✓
A106: Petroplazas Corporativo | B106: NCHB83115 | C106: SRV0005516 | D106: ES_Corporativo | E106: CAMIONES Y TRANSPORTES | F106: Movimiento generado en automático por sistema. Proceso de Carga Masiva de Facturas | G106: ES_Corporativo | H106: DISTRIBUCIÓN (Corp)
A107: Petroplazas Corporativo | B107: FAMUN121252 | C107: SRV0005510 | D107: ES_Corporativo | E107: CAMIONES Y TRANSPORTES | F107: Movimiento generado en automático por sistema. Proceso de Carga Masiva de Facturas | G107: ES_Corporativo | H107: DISTRIBUCIÓN (Corp)
A108: MUNICH II | B108: BCR678 | C108: E000000179 | E108: Estatus Surtido | F108: FAVOR DE ENTREGAR EN ESTACION MUNICH II CON EL SUPERVISOR. MATERIAL DE LIMPIEZA DEL MES DE JUNIO 2026. | G108: MUNICH II | H108: MATCH ✓
A109: Madero | B109: TME357589 | C109: E000000106 | D109: ES_MADERO | E109: CUARTO DE CORTES | F109: COMPRA DE ROLLO TERMICO (80X70) PARA DISPENSARIOS DE LA ESTACION MADERO. ENTREGAR EN: BLVD. FRANCISCO I. MADERO 693 PTE. COL. CENTRO, CULIACAN, SINALOA, C.P. 80000. | G109: MADERO | H109: MATCH ✓
A110: Petroplazas Corporativo | B110: NCAA68637 | C110: SRV0005514 | D110: ES_Corporativo | E110: CAMIONES Y TRANSPORTES | F110: Movimiento generado en automático por sistema. Proceso de Carga Masiva de Facturas | G110: ES_Corporativo | H110: DISTRIBUCIÓN (Corp)
A111: Petroplazas Corporativo | B111: A006128 | C111: SRV0005524 | D111: ES_Corporativo | E111: CC Administracion | F111: PAGO DE LA FACT. 06128 POR EL SERVICIO DE HOSPEDAJE DEL C. ROLANDO TIRADO FELIX, GERENTE DE ESTACIONES DE CLN., LOS DIAS, 5 Y 6 DE MARZO 2026. PROGRAMAR A PAGO PARA EL 2026. | G111: ES_Corporativo | H111: DISTRIBUCIÓN (Corp)
A112: Sabalo | B112: D368A2220 | C112: SRV0000111 | D112: ES_Sabalo | E112: A. PUBLICIDAD Y MERCADOTECNIA, HERRAMIENTAS EN LA ESTACION | F112: Pago a fact. 2220 por Preparación Eléctrica e Instalación de Pantallas estacion sabalo, junio 2026. Programar a pago el 11/06/2026 | G112: SABALO | H112: MATCH ✓
...

Sheet Distribución
A1: Sucursal | B1: Factura | C1: Folio | D1: Grupo CC | E1: CC OC | F1: Observaciones OC | G1: Sucursales Detectadas | H1: # Estaciones
A2: Alamos | B2: A4860 | C2: SRV0000068 | D2: ES_Alamos | E2: AUTOMOVIL - AU-151 | F2: Movimiento generado en automático por sistema. Proceso de Carga Masiva de Facturas | G2: AU-151 | H2: 0
A3: Petroplazas Corporativo | B3: 64F6E70 | C3: SRV0005503 | D3: ES_Corporativo | E3: CC ADMINISTRACION | F3: PROYECTO DE CONSTRUCCION DE ESTACION COLON. CFDI I01 CONSTRUCCION | G3: ES_Corporativo | H3: 0
A4: Petroplazas Corporativo | B4: I40 | C4: SRV0005504 | D4: ES_Corporativo | E4: CC ADMINISTRACION | F4: CORRESPONDE A LA FACTURA 40. SERVICIO DE MANTENIMIENTO Y DESARROLLO DE SOFTWARE DE CORPORATIVO DIVISION GASOLINERAS. | G4: ES_Corporativo | H4: 0
A5: CEDIS Culiacán | B5: E018C998 | C5: E000000270 | E5: Estatus Surtido | F5: FAVOR DE ENTREGAR EN CEDIS CULIACAN CON DIEGO. PANTALON DESPACHADOR AZUL PARA STOCK DE ZONA CLN, ANGOSTURA Y NORTE. | G5: ZONA CLN | H5: 0
A6: CEDIS Culiacán | B6: B0C2F997 | C6: E000000271 | E6: Estatus Surtido | F6: FAVOR DE ENTREGAR EN CEDIS CULIACAN CON DIEGO. PANTALON DESPACHADOR AZUL PARA STOCK DE ZONA CLN, ANGOSTURA Y NORTE. | G6: ZONA CLN | H6: 0
A7: Revolucion | B7: A1549 | C7: E000000153 | D7: ES_Revolucion | E7: Baños publicos | F7: FAVOR DE ENTREGAR EN ESTACION REVOLUCION CON EL SUPERVISOR AL DOMICILIO BLVD. LUIS DONAL. COLOSIO NO. 615, COL. REVOLUCION MEXICANA, GUASAVE, SINALOA, C.P. 81016. MATERIAL DE LIMPIEZA DEL MES DE JUNIO 2026. | G7: REVOLUCION / COLOSIO | H7: 2
A8: CEDIS Mazatlán | B8: F68961 | C8: E000000462 | E8: Estatus Surtido | F8: FAVOR DE ENTREGAR EN CEDIS MAZATLAN CON ISABEL AL DOMICILIO AZALEA NO. 4901, COL. RICARDO FLORES MAGON, C.P. 82190, MAZATLAN, SINALOA. GORRA ACRILANA AMARILLO / REY C/BORDADO FTE REDPETROIL PARA STOCK DE CEDIS MAZATLAN PARA ESTACIONES SABALO, AEROPUERTO, CONCORDIA, HABAL, 12 DE MAYO, FORESTA, URBIVILLA, GRIJALVA, ROSARIO Y ESCUINAPA. | G8: 12 DE MAYO / AEROPUERTO / ESCUINAPA / CONCORDIA / URBIVILLA / GRIJALVA / FORESTA / ROSARIO / SABALO / HABAL | H8: 10
A9: Alamos | B9: FDF0430176 | C9: E000000128 | D9: CC Empleados | E9: CC Jose Carlos Valdez Nuñez | F9: FAVOR DE ENTREGAR EN CEDIS MAZATLAN CON ISABEL. CARGADOR LENOVO ADL45WCC PARA LAPTOP LENOVO IDEAPAD 320 DE ING. JOSE CARLOS JEFE DE PISO ZONA NORTE. | G9: ZONA NORTE | H9: 0
A10: Petroplazas Corporativo | B10: 2C6A1 | C10: SRV0005508 | D10: ES_Corporativo | E10: CC Administracion | F10: SERVICIO RED JOSHUA SITIO NAS, JUNIO 2026 | G10: ES_Corporativo | H10: 0
A11: ALHUEY1 | B11: FC26295 | C11: E000000195 | D11: ES_ALHUEY1 | E11: Estacion Alhuey 1 | F11: COMPRA DE 3 PATITAS (FUSIBLE) PARA VALVULA SHUT OFF PARA ESTACION ALHUEY 1. (ENTREGAR EN ALMACEN DE REFACCIONES DE CAMPO EL DIEZ). Y FACTURAR CON 1 DE JUNIO. | G11: ALHUEY 1 / EL DIEZ | H11: 2
A12: Dos Valles | B12: A1548 | C12: E000000131 | D12: ES_Dos Valles | E12: Baños publicos | F12: FAVOR DE ENTREGAR EN ESTACION DOS VALLE CON EL SUPERVISOR AL DOMICILIO BLVD. LUIS DONALDO COLOSIO NO. 264, COL. OCORO, GUASAVE, SINALOA, C.P. 81010. MATERIAL DE LIMPIEZA DEL MES DE JUNIO 2026. | G12: DOS VALLES / COLOSIO | H12: 2
A13: Sabalo | B13: FIA177489 | C13: E000000204 | D13: ES_Sabalo | E13: CC OPERACIONES | F13: COMPRA POR WC BLANCO AHORRADOR REDONDO MODELO ECO ACUACER SOLICITADO PARA ESTACION SABALO, JUNIO 2026. ENTREGAR EN CEDIS MAZATLAN (almacen flores magon) CON ISABEL VEGA. | G13: FLORES MAGON / SABALO | H13: 2
A14: Bellavista | B14: AA10863 | C14: E000000094 | D14: ES_Bellavista | E14: Estacion BellaVista | F14: COMPRA DE PINTURA PARA EL MTTO. DE LAS REJILLAS DE TRAMPAS DE LA ESTACION BELLAVISTA. (ENTREGAR EN LA ESTACION EL PAPALOTE, CON UN PAPEL QUE DIGA QUE ES DE BELLAVISTA). | G14: BELLAVISTA / PAPALOTE | H14: 2
A15: Petroplazas Corporativo | B15: B4765 | C15: SRV0005509 | D15: ES_Corporativo | E15: GASTOS GENERALES | F15: SERVICIO DE IMPRESION DE ETIQUETAS MAGNA Y PREMIUM PARA ESTACION SANTA MONICA. | G15: ES_Corporativo | H15: 0
A16: CEDIS Mazatlán | B16: A851A3268 | C16: SRV0000605 | D16: Concordia | E16: Aeropuerto 1 | F16: PAGO A FACT. 3268 POR SERVICIO DE CONSULTORIA Y ELABORACION DOCUMENTAL EN MATERIA DE LA STPS ESTACION HABAL, CARDONES, AEROPUERTO Y CONCORDIA, JUNIO 2026. PROGRAMAR A PAGO EL 11/06/2026 | G16: AEROPUERTO / CONCORDIA / CARDONES / HABAL | H16: 4
A17: CEDIS Culiacán | B17: AA43839 | C17: SRV0000461 | D17: CUAUHTEMOC | E17: REVOLUCION | F17: CORRESPONDE A LA FACTURA AA43839. SERVICIO DE IMPRESION DE CUPONERAS CITICINEMAS DE JUNIO 2026 DE ESTACION DOS VALLE, REVOLUCION Y CUAUHTEMOC. | G17: REVOLUCION / CUAUHTEMOC / DOS VALLES | H17: 3
A18: CEDIS Mazatlán | B18: 02FF93270 | C18: SRV0000606 | D18: Colosio | E18: Foresta | F18: CORRESPONDE A LA FACTURA 3270. CONSULTORIA Y ELABORACION DOCUMENTAL DE LA STPS DEL MES DE JUNIO 2026 ZONA MZT 3. | G18: ZONA MZT 3 | H18: 0
A19: CEDIS Mazatlán | B19: BAE1E3271 | C19: SRV0000607 | D19: Grijalva | E19: Juan Carrasco | F19: CORRESPONDE A LA FACTURA 3271. CONSULTORIA Y ELABORACION DOCUMENTAL DE LA STPS DEL MES DE JUNIO 2026 ZONA MZT 4. | G19: ZONA MZT 4 | H19: 0
A20: ALHUEY2 | B20: TME357624 | C20: E000000131 | D20: ALHUEY 2 | E20: ESTACION | F20: COMPRA DE ROLLO TERMICO (80X70) PARA DISPENSARIOS DE LA ESTACION ALHUEY 2. ENTREGAR EN: AUTOPISTA CULIACAN-LOS MOCHIS KM. 110.5, ALHUEY, ANGOSTURA, SINALOA, C.P. 81610. | G20: ALHUEY 2 / ALHUEY 1 | H20: 2
... A39: Petroplazas Corporativo | B39: CDDC671 | C39: SRV0005531 | D39: ES_Corporativo | E39: CC ADMINISTRACION | F39: PROYECTO DE CONSTRUCCION DE ESTACION COLON. CFDI I01 CONSTRUCCION | G39: ES_Corporativo | H39: 0
A40: CEDIS Mazatlán | B40: FGC4202 | C40: E000000467 | E40: Estatus Surtido | F40: FAVOR DE ENTREGAR EN CEDIS MAZATLAN CON ISABEL AL DOMICILIO AZALEA NO. 4901, COL. RICARDO FLORES MAGON, C.P. 82190, MAZATLAN, SINALOA. UNIFORMES MARCA PEMEX PARA STOCK DE CEDIS PARA ESTACIONES PLAYAS, JUAN CARRASCO, HABAS. | G40: CARRASCO / PLAYAS / LAS HABAS | H40: 3
A41: CEDIS Mazatlán | B41: FGC4201 | C41: E000000466 | E41: Estatus Surtido | F41: FAVOR DE ENTREGAR EN CEDIS MAZATLAN CON ISABEL AL DOMICILIO AZALEA NO. 4901, COL. RICARDO FLORES MAGON, C.P. 82190, MAZATLAN, SINALOA. UNIFORMES MARCA PEMEX PARA STOCK DE CEDIS PARA ESTACIONES PLAYAS, JUAN CARRASCO, HABAS. | G41: CARRASCO / PLAYAS / LAS HABAS | H41: 3
A42: CEDIS Mazatlán | B42: K19476 | C42: SRV0000610 | D42: Sabalo | E42: Marina | F42: CORRESPONDE A LA FACTURA K19476. SERVICIO DE SERVIDOR VIRTUAL MENSUAL RESPALDOS EN LA NUBE Y SERVIDOR DE ACCESO A CLIENTES PARA FACTURACION JUNIO 2026 DE ESTACIONES DE ZONA MZT. | G42: ZONA MZT | H42: 0
A43: CEDIS Culiacán | B43: 866f81908 | C43: E000000276 | E43: Estatus Surtido | F43: FAVOR DE ENTREGAR EN CEDIS MAZATLAN CON ISABEL. PLAYERA POLO AZUL MARINO M/L LOGO (REDPETROIL Y GOTA) PARA CEDIS CULIACAN ESTACIONES ZONA CLN, ANGOSTURA Y NORTE. | G43: ZONA CLN | H43: 0
A44: CEDIS Mazatlán | B44: K19474 | C44: SRV0000609 | D44: Flores Magon | E44: Foresta | F44: CORRESPONDE A LA FACTURA K19474. SERVICIO DE SERVIDOR VIRTUAL MENSUAL RESPALDOS EN LA NUBE Y SERVIDOR DE ACCESO A CLIENTES PARA FACTURACION JUNIO 2026 DE ESTACIONES DE ZONA MZT 3. | G44: ZONA MZT 3 | H44: 0
A45: CEDIS Mazatlán | B45: 1e81f1907 | C45: E000000468 | E45: Estatus Surtido | F45: FAVOR DE ENTREGAR EN CEDIS MAZATLAN CON ISABEL. PLAYERA POLO AZUL MARINO M/L LOGO (REDPETROIL Y GOTA) PARA STOCK DE CEDIS PARA ESTACIONES SABALO, AEROPUERTO, CONCORDIA, HABAL, 12 DE MAYO, FORESTA, URBIVILLA, ROSARIO Y ESCUINAPA. | G45: 12 DE MAYO / AEROPUERTO / ESCUINAPA / CONCORDIA / URBIVILLA / FORESTA / ROSARIO / SABALO / HABAL | H45: 9
A46: CEDIS Culiacán | B46: K19475 | C46: SRV0000465 | D46: CUAUHTEMOC | E46: ALAMOS | F46: CORRESPONDE A LA FACTURA K19475. SERVICIO DE SERVIDOR VIRTUAL MENSUAL RESPALDOS EN LA NUBE Y SERVIDOR DE ACCESO A CLIENTES PARA FACTURACION JUNIO 2026 DE ESTACIONES DE ZONA NORTE. | G46: ZONA NORTE | H46: 0
A47: CEDIS Culiacán | B47: E270E3272 | C47: SRV0000467 | D47: REVOLUCION | E47: ALAMOS | F47: CORRESPONDE A LA FACTURA 3272. CONSULTORIA Y ELABORACION DOCUMENTAL DE LA STPS DEL MES DE JUNIO 2026 ZONA NORTE. | G47: ZONA NORTE | H47: 0
A48: CEDIS Mazatlán | B48: K19478 | C48: SRV0000611 | D48: Cardones | E48: Aeropuerto 1 | F48: CORRESPONDE A LA FACTURA K19478. SERVICIO DE SERVIDOR VIRTUAL MENSUAL RESPALDOS EN LA NUBE Y SERVIDOR DE ACCESO A CLIENTES PARA FACTURACION JUNIO 2026 DE ESTACIONES DE ZONA MZT 2. | G48: ZONA MZT 2 | H48: 0
A49: CEDIS Culiacán | B49: K19472 | C49: SRV0000463 | D49: HUMAYA | E49: EL DIEZ | F49: CORRESPONDE A LA FACTURA K19472. SERVICIO DE SERVIDOR VIRTUAL MENSUAL RESPALDOS EN LA NUBE Y SERVIDOR DE ACCESO A CLIENTES PARA FACTURACION JUNIO 2026 DE ESTACIONES DE ZONA CLN. | G49: ZONA CLN | H49: 0
A50: CEDIS Mazatlán | B50: K19480 | C50: SRV0000613 | D50: Munich II | E50: Juan Carrasco | F50: CORRESPONDE A LA FACTURA K19480. SERVICIO DE SERVIDOR VIRTUAL MENSUAL RESPALDOS EN LA NUBE Y SERVIDOR DE ACCESO A CLIENTES PARA FACTURACION JUNIO 2026 DE ZONA MZT 4. | G50: ZONA MZT 4 | H50: 0
A51: CEDIS Mazatlán | B51: K19479 | C51: SRV0000612 | D51: Rosario | E51: Rosario | F51: CORRESPONDE A LA FACTURA K19479. SERVICIO DE SERVIDOR VIRTUAL MENSUAL RESPALDOS EN LA NUBE Y SERVIDOR DE ACCESO A CLIENTES PARA FACTURACION JUNIO 2026 DE ESTACIONES DE ESTACION ROSARIO Y ESCUINAPA. | G51: ESCUINAPA / ROSARIO | H51: 2
A52: CEDIS Mazatlán | B52: e0b2a250 | C52: SRV0000100 | D52: Santa Rosa | E52: Cerritos | F52: PAGO A FACT. 250 POR PUBLICIDAD EN DURO Y MACIZO ESTACION CERRITOS, HABAS, PLAYAS, REAL DEL VALLE, SABALO Y MARINA, JUNIO 2026. PROGRAMAR A PAGO EL 04/05/2026 | G52: REAL DEL VALLE / CERRITOS / SABALO / MARINA / PLAYAS / LAS HABAS | H52: 6
A53: CEDIS Mazatlán | B53: A1967512 | C53: SRV0000614 | D53: Playas Del Camaron | E53: Habas | F53: CORRESPONDE A LA FACTURA 1967512-A. SERVICIO DE PAQUETERIA DE ESTACIONES HABAS, PLAYAS Y JUAN CARRASCO. | G53: CARRASCO / PLAYAS / LAS HABAS | H53: 3
A54: CEDIS Culiacán | B54: K19473 | C54: SRV0000464 | D54: ALHUEY 2 | E54: ALHUEY 1 | F54: CORRESPONDE A LA FACTURA K19473. SERVICIO DE SERVIDOR VIRTUAL MENSUAL RESPALDOS EN LA NUBE Y SERVIDOR DE ACCESO A CLIENTES PARA FACTURACION JUNIO 2026 DE ESTACIONES DE ZONA ANGOSTURA. | G54: ZONA ANGOSTURA | H54: 0
A55: Gobernador | B55: K19477 | C55: SRV0000062 | D55: ES_GOBERNADOR | E55: Administracion | F55: CORRESPONDE A LA FACTURA K19477. SERVICIO DE SERVIDOR VIRTUAL MENSUAL RESPALDOS EN LA NUBE Y SERVIDOR DE ACCESO A CLIENTES PARA FACTURACION JUNIO 2026 DE ESTACIONES DE ZONA GOBERNADOR. | G55: GOBERNADOR / ZONA GOBERNADOR | H55: 1
A56: Petroplazas Corporativo | B56: I63251 | C56: SRV0005532 | D56: ES_Corporativo | E56: CC Administracion | F56: TIMBRES FISCALES PETROPLAZAS, JUNIO 2026 | G56: ES_Corporativo | H56: 0
A57: Petroplazas Corporativo | B57: MZT3949 | C57: SRV0005534 | D57: ES_Corporativo | E57: AUTOMOVIL AU-152 | F57: SERVICIO DE LOS 180,000 KM A VEHICULO VENTO AUR-152 A CARGO DE LIC. JUAN PEDRO ROUSSE GERENTE DE VENTAS DIVISION GASOLINERAS. | G57: AU-152 | H57: 0
... A66: CEDIS Mazatlán | B66: CD6A0825 | C66: SRV0000137 | D66: Munich II | E66: Cerritos | F66: Pago a fact. o-32940 por servicio de Publicidad en programa de radio Viva la Noticia Estación Cerritos, habas, marina, Sabalo, real del valle y playas. , marzo 2026. programar a pago el 12/03/2026 | G66: REAL DEL VALLE / CERRITOS / SABALO / MARINA / PLAYAS / LAS HABAS | H66: 6
A67: CEDIS Culiacán | B67: GZ0002716 | C67: E000000279 | E67: Estatus Surtido | F67: FAVOR DE ENTREGAR EN CEDIS MAZATLAN CON ISABEL. PLAYERA POLO AZUL MARINO M/L LOGO (REDPETROIL Y GOTA) PARA CEDIS CULIACAN ESTACIONES ZONA CLN, ANGOSTURA Y NORTE. | G67: ZONA CLN | H67: 0
A68: Petroplazas Corporativo | B68: F332 | C68: SRV0005539 | D68: ES_Corporativo | E68: CC GESTION DE TALENTO | F68: CORRESPONDE A LA FACTURA F332. CONSULTORIA EN RESPONSABILIDAD SOCIAL JUNIO 2026. | G68: ES_Corporativo | H68: 0
A69: ALHUEY1 | B69: FC26341 | C69: E000000206 | D69: ES_ALHUEY1 | E69: CC OPERACIONES | F69: COMPRA DE MANGUERA PARA DESCARGA DE COMBUSTIBLE DE LA ESTACION ALHUEY 1. ENTREGAR EN ALMACEN DE CAMPO EL DIEZ. | G69: ALHUEY 1 / EL DIEZ | H69: 2
A70: ALHUEY2 | B70: FC26342 | C70: E000000137 | E70: Estatus Surtido | F70: COMPRA DE 4 PISTOLAS PARA AGUA 1/4 NPT HEMBRA, PARA DISPENSARIOS DE LA ESTACION ALHUEY 2. (ENTREGAR EN ALMACEN DE REFACCIONES DE CAMPO EL DIEZ. | G70: ALHUEY 2 / EL DIEZ | H70: 2
A71: CEDIS Mazatlán | B71: GZ0002745 | C71: E000000503 | E71: Estatus Surtido | F71: FAVOR DE ENTREGAR EN CEDIS MAZATLAN CON ISABEL. PLAYERA Y BLUSAS POLO MAYORK FIT AZUL ROYAL LOGO ARCO PARA STOCK DE CEDIS MAZATLAN ESTACIONES (MARINA, CERRITOS, CARDONES). | G71: CERRITOS / CARDONES / MARINA | H71: 3
A72: Petroplazas Corporativo | B72: F536 | C72: SRV0005550 | D72: ES_Corporativo | E72: CC CONTABILIDAD | F72: CORRESPONED A LA FACTURA F536. SERVICIOS NOTARIALES Esc - 3700 000016-26 (80121704 - Servicios legales sobre contratos) | G72: ES_Corporativo | H72: 0
A73: Petroplazas Corporativo | B73: AJCP1281 | C73: SRV0005556 | D73: ES_Corporativo | E73: CC CONTABILIDAD | F73: CORRESPONDE A LA FACTURA AJCP1281. PRESTACION DE SERVICIO. | G73: ES_Corporativo | H73: 0
A74: Petroplazas Corporativo | B74: F558 | C74: SRV0005552 | D74: ES_Corporativo | E74: CC CONTABILIDAD | F74: CORRESPONDE A LA FACTURA F558. SERVICIOS NOTARIALES Esc - 3711 000027-26 (80121704 - Servicios legales sobre contratos) | G74: ES_Corporativo | H74: 0
A75: Petroplazas Corporativo | B75: EST8947995 | C75: SRV0005554 | D75: ES_Corporativo | E75: CC CONTABILIDAD | F75: SERVICIO TELMEX | G75: ES_Corporativo | H75: 0
A76: Petroplazas Corporativo | B76: MZT2747 | C76: SRV0005557 | D76: ES_Corporativo | E76: CC CONTABILIDAD | F76: CORRESPONDE A LA FACTURA MZT2747. PRESTACION DE SERVICIO. | G76: ES_Corporativo | H76: 0
A77: Petroplazas Corporativo | B77: AJCP1262 | C77: SRV0005555 | D77: ES_Corporativo | E77: CC CONTABILIDAD | F77: CORRESPONDE A LA FACTURA AJCP12. PRESTACION DE SERVICIO. | G77: ES_Corporativo | H77: 0
A78: Petroplazas Corporativo | B78: F560 | C78: SRV0005551 | D78: ES_Corporativo | E78: CC CONTABILIDAD | F78: CORRESPONDE A LA FACTURA F560. SERVICIOS NOTARIALES Esc - 3749 000066-26 (80121704 - Servicios legales sobre contratos) | G78: ES_Corporativo | H78: 0
A79: Petroplazas Corporativo | B79: B8893 | C79: SRV0005546 | D79: ES_Corporativo | E79: CC CONTABILIDAD | F79: CORRESPONDE A LA FACTURA B8893. 50% ESTUDIO DE PRECIOS DE TRANSFERENCIA 2025. 2/2 | G79: ES_Corporativo | H79: 0
A80: Petroplazas Corporativo | B80: FPBO83003 | C80: SRV0005481 | D80: ES_Corporativo | E80: CAMIONES Y TRANSPORTES | F80: Movimiento generado en automático por sistema. Proceso de Carga Masiva de Facturas | G80: ES_Corporativo | H80: 0
A81: Petroplazas Corporativo | B81: FMPC185433 | C81: SRV0005477 | D81: ES_Corporativo | E81: CAMIONES Y TRANSPORTES | F81: Movimiento generado en automático por sistema. Proceso de Carga Masiva de Facturas | G81: ES_Corporativo | H81: 0
A82: ALHUEY1 | B82: FSM2720 | C82: SRV0000061 | D82: ES_ALHUEY1 | E82: AUTOMOVIL AU-162 | F82: SERVICIO DE LOS 140,000 KM A VEHICULO MG5 2022 AU-162 A CARGO DE LIC. ALEJANDRO VAZQUEZ LGA. GERENTE DE ZONA ANGOSTURA | G82: ZONA ANGOSTURA | H82: 0
A83: Petroplazas Corporativo | B83: FPER69651 | C83: SRV0005478 | D83: ES_Corporativo | E83: CAMIONES Y TRANSPORTES | F83: Movimiento generado en automático por sistema. Proceso de Carga Masiva de Facturas | G83: ES_Corporativo | H83: 0
... A97: Petroplazas Corporativo | B97: FMAE120798 | C97: SRV0005465 | D97: ES_Corporativo | E97: CAMIONES Y TRANSPORTES | F97: Movimiento generado en automático por sistema. Proceso de Carga Masiva de Facturas | G97: ES_Corporativo | H97: 0
A98: PERICOS | B98: FC26275 | C98: E000000103 | E98: Estatus Surtido | F98: ** CORRECCION DE O.C. ** COMPRA DE REFACCIONES PARA STOCK DE LA ESTACION PERICOS. (ENTREGAR EN ALMACEN DE REFACCIONES DE CAMPO EL DIEZ). | G98: PERICOS / EL DIEZ | H98: 2
A99: El Diez | B99: MZT3911 | C99: SRV0000111 | D99: ES_El_Diez | E99: AUTOMOVIL AU-144 | F99: SERVICIO GENERAL DE AFINACION A UNIDAD, AU 144, CARGO DE RITO LEONEL LEON NIEBLA, JEFE DE OPERACIONES DE LAS ESTACIONES DE CLN. | G99: AU-144 | H99: 0
A100: Petroplazas Corporativo | B100: FDYA152975 | C100: SRV0005495 | D100: ES_Corporativo | E100: CAMIONES Y TRANSPORTES | F100: Movimiento generado en automático por sistema. Proceso de Carga Masiva de Facturas | G100: ES_Corporativo | H100: 0
A101: Petroplazas Corporativo | B101: LMFCR71871 | C101: SRV0005500 | D101: ES_Corporativo | E101: CAMIONES Y TRANSPORTES | F101: Movimiento generado en automático por sistema. Proceso de Carga Masiva de Facturas | G101: ES_Corporativo | H101: 0
A102: Petroplazas Corporativo | B102: FMEJ120814 | C102: SRV0005498 | D102: ES_Corporativo | E102: CAMIONES Y TRANSPORTES | F102: Movimiento generado en automático por sistema. Proceso de Carga Masiva de Facturas | G102: ES_Corporativo | H102: 0
A103: Petroplazas Corporativo | B103: FMHA172676 | C103: SRV0005497 | D103: ES_Corporativo | E103: CAMIONES Y TRANSPORTES | F103: Movimiento generado en automático por sistema. Proceso de Carga Masiva de Facturas | G103: ES_Corporativo | H103: 0
A104: Petroplazas Corporativo | B104: FFGA120438 | C104: SRV0005494 | D104: ES_Corporativo | E104: CAMIONES Y TRANSPORTES | F104: Movimiento generado en automático por sistema. Proceso de Carga Masiva de Facturas | G104: ES_Corporativo | H104: 0
A105: Petroplazas Corporativo | B105: FMCO45474 | C105: SRV0005493 | D105: ES_Corporativo | E105: CAMIONES Y TRANSPORTES | F105: Movimiento generado en automático por sistema. Proceso de Carga Masiva de Facturas | G105: ES_Corporativo | H105: 0
A106: Petroplazas Corporativo | B106: FCAA215568 | C106: SRV0005499 | D106: ES_Corporativo | E106: CAMIONES Y TRANSPORTES | F106: Movimiento generado en automático por sistema. Proceso de Carga Masiva de Facturas | G106: ES_Corporativo | H106: 0
A107: Petroplazas Corporativo | B107: FRAA143323 | C107: SRV0005492 | D107: ES_Corporativo | E107: CAMIONES Y TRANSPORTES | F107: Movimiento generado en automático por sistema. Proceso de Carga Masiva de Facturas | G107: ES_Corporativo | H107: 0
A108: Petroplazas Corporativo | B108: FMRV238946 | C108: SRV0005491 | D108: ES_Corporativo | E108: CAMIONES Y TRANSPORTES | F108: Movimiento generado en automático por sistema. Proceso de Carga Masiva de Facturas | G108: ES_Corporativo | H108: 0
A109: Petroplazas Corporativo | B109: FESA166654 | C109: SRV0005490 | D109: ES_Corporativo | E109: CAMIONES Y TRANSPORTES | F109: Movimiento generado en automático por sistema. Proceso de Carga Masiva de Facturas | G109: ES_Corporativo | H109: 0
A110: Petroplazas Corporativo | B110: FMCE182021 | C110: SRV0005496 | D110: ES_Corporativo | E110: CAMIONES Y TRANSPORTES | F110: Movimiento generado en automático por sistema. Proceso de Carga Masiva de Facturas | G110: ES_Corporativo | H110: 0
... A116: Petroplazas Corporativo | B116: A4875 | C116: SRV0005484 | D116: ES_Corporativo | E116: AUTOMOVIL - AU-035 | F116: Movimiento generado en automático por sistema. Proceso de Carga Masiva de Facturas | G116: ES_Corporativo | H116: 0

Sheet Distrib. Calculada
A1: Sucursal | B1: Factura | C1: Folio | D1: Grupo CC | E1: Zona / Estaciones Detectadas | F1: Total Factura (MX) | G1: Estación Distribuida | H1: % Distribución | I1: Monto Distribuido | J1: Cuenta contable
A2: Alamos | B2: A4860 | C2: SRV0000068 | D2: ES_Alamos | E2: AU-151 | F2: 249 | G2: ALAMOS | H2: 20.00% | I2: 49.8 | J2: =VLOOKUP(B2,'Datos Originales'!$D$1:$BC$462,36,FALSE) -> 50299040046
A3: Alamos | B3: A4860 | C3: SRV0000068 | D3: ES_Alamos | E3: AU-151 | F3: 249 | G3: FATIMA | H3: 20.00% | I3: 49.8 | J3: =VLOOKUP(B3,'Datos Originales'!$D$1:$BC$462,36,FALSE) -> 50299040046
A4: Alamos | B4: A4860 | C4: SRV0000068 | D4: ES_Alamos | E4: AU-151 | F4: 249 | G4: DOS VALLES | H4: 20.00% | I4: 49.8 | J4: =VLOOKUP(B4,'Datos Originales'!$D$1:$BC$462,36,FALSE) -> 50299040046
A5: Alamos | B5: A4860 | C5: SRV0000068 | D5: ES_Alamos | E5: AU-151 | F5: 249 | G5: REVOLUCION | H5: 20.00% | I5: 49.8 | J5: =VLOOKUP(B5,'Datos Originales'!$D$1:$BC$462,36,FALSE) -> 50299040046
A6: Alamos | B6: A4860 | C6: SRV0000068 | D6: ES_Alamos | E6: AU-151 | F6: 249 | G6: CUAHUTEMOC | H6: 20.00% | I6: 49.8 | J6: =VLOOKUP(B6,'Datos Originales'!$D$1:$BC$462,36,FALSE) -> 50299040046
A7: Petroplazas Corporativo | B7: 64F6E70 | C7: SRV0005503 | D7: ES_Corporativo | E7: ES_Corporativo | F7: 15724020 | G7: MARINA | H7: 2.32% | I7: 364797.27 | J7: =VLOOKUP(B7,'Datos Originales'!$D$1:$BC$462,36,FALSE) -> _CUA-DRE--000000
A8: Petroplazas Corporativo | B8: 64F6E70 | C8: SRV0005503 | D8: ES_Corporativo | E8: ES_Corporativo | F8: 15724020 | G8: SABALO | H8: 2.22% | I8: 349073.25 | J8: =VLOOKUP(B8,'Datos Originales'!$D$1:$BC$462,36,FALSE) -> _CUA-DRE--000000
A9: Petroplazas Corporativo | B9: 64F6E70 | C9: SRV0005503 | D9: ES_Corporativo | E9: ES_Corporativo | F9: 15724020 | G9: CERRITOS | H9: 2.22% | I9: 349073.25 | J9: =VLOOKUP(B9,'Datos Originales'!$D$1:$BC$462,36,FALSE) -> _CUA-DRE--000000
A10: Petroplazas Corporativo | B10: 64F6E70 | C10: SRV0005503 | D10: ES_Corporativo | E10: ES_Corporativo | F10: 15724020 | G10: REAL DEL VALLE | H10: 2.22% | I10: 349073.25 | J10: =VLOOKUP(B10,'Datos Originales'!$D$1:$BC$462,36,FALSE) -> _CUA-DRE--000000
A11: Petroplazas Corporativo | B11: 64F6E70 | C11: SRV0005503 | D11: ES_Corporativo | E11: ES_Corporativo | F11: 15724020 | G11: PLAYAS | H11: 2.22% | I11: 349073.25 | J11: =VLOOKUP(B11,'Datos Originales'!$D$1:$BC$462,36,FALSE) -> _CUA-DRE--000000
A12: Petroplazas Corporativo | B12: 64F6E70 | C12: SRV0005503 | D12: ES_Corporativo | E12: ES_Corporativo | F12: 15724020 | G12: HABAS | H12: 2.22% | I12: 349073.25 | J12: =VLOOKUP(B12,'Datos Originales'!$D$1:$BC$462,36,FALSE) -> _CUA-DRE--000000
A13: Petroplazas Corporativo | B13: 64F6E70 | C13: SRV0005503 | D13: ES_Corporativo | E13: ES_Corporativo | F13: 15724020 | G13: CARDONES | H13: 2.22% | I13: 349073.25 | J13: =VLOOKUP(B13,'Datos Originales'!$D$1:$BC$462,36,FALSE) -> _CUA-DRE--000000
... A96: Petroplazas Corporativo | B96: I40 | C96: SRV0005504 | D96: ES_Corporativo | E96: ES_Corporativo | F96: 10000 | G96: LA PAZ | H96: 2.22% | I96: 222 | J96: =VLOOKUP(B96,'Datos Originales'!$D$1:$BC$462,36,FALSE) -> 50299040021
A97: CEDIS Culiacán | B97: E018C998 | C97: E000000270 | E97: ZONA CLN | F97: 12145.48 | G97: DIEZ | H97: 10.00% | I97: 1214.55 | J97: =VLOOKUP(B97,'Datos Originales'!$D$1:$BC$462,36,FALSE) -> 20101021501
A98: CEDIS Culiacán | B98: E018C998 | C98: E000000270 | E98: ZONA CLN | F98: 12145.48 | G98: HUMAYA | H98: 8.20% | I98: 995.93 | J98: =VLOOKUP(B98,'Datos Originales'!$D$1:$BC$462,36,FALSE) -> 20101021501
A99: CEDIS Culiacán | B99: E018C998 | C99: E000000270 | E99: ZONA CLN | F99: 12145.48 | G99: BELLAVISTA | H99: 8.18% | I99: 993.5 | J99: =VLOOKUP(B99,'Datos Originales'!$D$1:$BC$462,36,FALSE) -> 20101021501
A100: CEDIS Culiacán | B100: E018C998 | C100: E000000270 | E100: ZONA CLN | F100: 12145.48 | G100: PAPALOTE | H100: 8.18% | I100: 993.5 | J100: =VLOOKUP(B100,'Datos Originales'!$D$1:$BC$462,36,FALSE) -> 20101021501
A101: CEDIS Culiacán | B101: E018C998 | C101: E000000270 | E101: ZONA CLN | F101: 12145.48 | G101: SAN PEDRO | H101: 8.18% | I101: 993.5 | J101: =VLOOKUP(B101,'Datos Originales'!$D$1:$BC$462,36,FALSE) -> 20101021501
A102: CEDIS Culiacán | B102: E018C998 | C102: E000000270 | E102: ZONA CLN | F102: 12145.48 | G102: HEROICO | H102: 8.18% | I102: 993.5 | J102: =VLOOKUP(B102,'Datos Originales'!$D$1:$BC$462,36,FALSE) -> 20101021501
A103: CEDIS Culiacán | B103: E018C998 | C103: E000000270 | E103: ZONA CLN | F103: 12145.48 | G103: MADERO | H103: 8.18% | I103: 993.5 | J103: =VLOOKUP(B103,'Datos Originales'!$D$1:$BC$462,36,FALSE) -> 20101021501
A104: CEDIS Culiacán | B104: E018C998 | C104: E000000270 | E104: ZONA CLN | F104: 12145.48 | G104: MALECON | H104: 8.18% | I104: 993.5 | J104: =VLOOKUP(B104,'Datos Originales'!$D$1:$BC$462,36,FALSE) -> 20101021501
A105: CEDIS Culiacán | B105: E018C998 | C105: E000000270 | E105: ZONA CLN | F105: 12145.48 | G105: OBREGON | H105: 8.18% | I105: 993.5 | J105: =VLOOKUP(B105,'Datos Originales'!$D$1:$BC$462,36,FALSE) -> 20101021501
A106: CEDIS Culiacán | B106: E018C998 | C106: E000000270 | E106: ZONA CLN | F106: 12145.48 | G106: PATRIA | H106: 8.18% | I106: 993.5 | J106: =VLOOKUP(B106,'Datos Originales'!$D$1:$BC$462,36,FALSE) -> 20101021501
A107: CEDIS Culiacán | B107: E018C998 | C107: E000000270 | E107: ZONA CLN | F107: 12145.48 | G107: PERICOS | H107: 8.18% | I107: 993.5 | J107: =VLOOKUP(B107,'Datos Originales'!$D$1:$BC$462,36,FALSE) -> 20101021501
A108: CEDIS Culiacán | B108: E018C998 | C108: E000000270 | E108: ZONA CLN | F108: 12145.48 | G108: PERICOS CENTRO | H108: 8.18% | I108: 993.5 | J108: =VLOOKUP(B108,'Datos Originales'!$D$1:$BC$462,36,FALSE) -> 20101021501
... A120: CEDIS Culiacán | B120: B0C2F997 | C120: E000000271 | E120: ZONA CLN | F120: 11536.8 | G120: PERICOS CENTRO | H120: 8.18% | I120: 943.71 | J120: =VLOOKUP(B120,'Datos Originales'!$D$1:$BC$462,36,FALSE) -> 20101021501
A121: Revolucion | B121: A1549 | C121: E000000153 | D121: ES_Revolucion | E121: REVOLUCION / COLOSIO | F121: 2040 | G121: REVOLUCION | H121: 50.00% | I121: 1020 | J121: =VLOOKUP(B121,'Datos Originales'!$D$1:$BC$462,36,FALSE) -> 20101021501
A122: Revolucion | B122: A1549 | C122: E000000153 | D122: ES_Revolucion | E122: REVOLUCION / COLOSIO | F122: 2040 | G122: COLOSIO | H122: 50.00% | I122: 1020 | J122: =VLOOKUP(B122,'Datos Originales'!$D$1:$BC$462,36,FALSE) -> 20101021501
A123: CEDIS Mazatlán | B123: F68961 | C123: E000000462 | E123: 12 DE MAYO / AEROPUERTO / ESCUINAPA / CONCORDIA / URBIVILLA / GRIJALVA / FORESTA / ROSARIO / SABALO / HABAL | F123: 3440 | G123: 12 DE MAYO | H123: 10.00% | I123: 344 | J123: =VLOOKUP(B123,'Datos Originales'!$D$1:$BC$462,36,FALSE) -> 20101021501
A124: CEDIS Mazatlán | B124: F68961 | C124: E000000462 | E124: 12 DE MAYO / AEROPUERTO / ESCUINAPA / CONCORDIA / URBIVILLA / GRIJALVA / FORESTA / ROSARIO / SABALO / HABAL | F124: 3440 | G124: AEROPUERTO | H124: 10.00% | I124: 344 | J124: =VLOOKUP(B124,'Datos Originales'!$D$1:$BC$462,36,FALSE) -> 20101021501
A125: CEDIS Mazatlán | B125: F68961 | C125: E000000462 | E125: 12 DE MAYO / AEROPUERTO / ESCUINAPA / CONCORDIA / URBIVILLA / GRIJALVA / FORESTA / ROSARIO / SABALO / HABAL | F125: 3440 | G125: ESCUINAPA | H125: 10.00% | I125: 344 | J125: =VLOOKUP(B125,'Datos Originales'!$D$1:$BC$462,36,FALSE) -> 20101021501
A126: CEDIS Mazatlán | B126: F68961 | C126: E000000462 | E126: 12 DE MAYO / AEROPUERTO / ESCUINAPA / CONCORDIA / URBIVILLA / GRIJALVA / FORESTA / ROSARIO / SABALO / HABAL | F126: 3440 | G126: CONCORDIA | H126: 10.00% | I126: 344 | J126: =VLOOKUP(B126,'Datos Originales'!$D$1:$BC$462,36,FALSE) -> 20101021501
A127: CEDIS Mazatlán | B127: F68961 | C127: E000000462 | E127: 12 DE MAYO / AEROPUERTO / ESCUINAPA / CONCORDIA / URBIVILLA / GRIJALVA / FORESTA / ROSARIO / SABALO / HABAL | F127: 3440 | G127: URBIVILLA | H127: 10.00% | I127: 344 | J127: =VLOOKUP(B127,'Datos Originales'!$D$1:$BC$462,36,FALSE) -> 20101021501
A128: CEDIS Mazatlán | B128: F68961 | C128: E000000462 | E128: 12 DE MAYO / AEROPUERTO / ESCUINAPA / CONCORDIA / URBIVILLA / GRIJALVA / FORESTA / ROSARIO / SABALO / HABAL | F128: 3440 | G128: GRIJALVA | H128: 10.00% | I128: 344 | J128: =VLOOKUP(B128,'Datos Originales'!$D$1:$BC$462,36,FALSE) -> 20101021501
A129: CEDIS Mazatlán | B129: F68961 | C129: E000000462 | E129: 12 DE MAYO / AEROPUERTO / ESCUINAPA / CONCORDIA / URBIVILLA / GRIJALVA / FORESTA / ROSARIO / SABALO / HABAL | F129: 3440 | G129: FORESTA | H129: 10.00% | I129: 344 | J129: =VLOOKUP(B129,'Datos Originales'!$D$1:$BC$462,36,FALSE) -> 20101021501
A130: CEDIS Mazatlán | B130: F68961 | C130: E000000462 | E130: 12 DE MAYO / AEROPUERTO / ESCUINAPA / CONCORDIA / URBIVILLA / GRIJALVA / FORESTA / ROSARIO / SABALO / HABAL | F130: 3440 | G130: ROSARIO | H130: 10.00% | I130: 344 | J130: =VLOOKUP(B130,'Datos Originales'!$D$1:$BC$462,36,FALSE) -> 20101021501
A131: CEDIS Mazatlán | B131: F68961 | C131: E000000462 | E131: 12 DE MAYO / AEROPUERTO / ESCUINAPA / CONCORDIA / URBIVILLA / GRIJALVA / FORESTA / ROSARIO / SABALO / HABAL | F131: 3440 | G131: SABALO | H131: 10.00% | I131: 344 | J131: =VLOOKUP(B131,'Datos Originales'!$D$1:$BC$462,36,FALSE) -> 20101021501
A132: CEDIS Mazatlán | B132: F68961 | C132: E000000462 | E132: 12 DE MAYO / AEROPUERTO / ESCUINAPA / CONCORDIA / URBIVILLA / GRIJALVA / FORESTA / ROSARIO / SABALO / HABAL | F132: 3440 | G132: HABAL | H132: 10.00% | I132: 344 | J132: =VLOOKUP(B132,'Datos Originales'!$D$1:$BC$462,36,FALSE) -> 20101021501
A133: Alamos | B133: FDF0430176 | C133: E000000128 | D133: CC Empleados | E133: ZONA NORTE | F133: 549 | G133: ALAMOS | H133: 20.00% | I133: 109.8 | J133: =VLOOKUP(B133,'Datos Originales'!$D$1:$BC$462,36,FALSE) -> 20101021501
A134: Alamos | B134: FDF0430176 | C134: E000000128 | D134: CC Empleados | E134: ZONA NORTE | F134: 549 | G134: FATIMA | H134: 20.00% | I134: 109.8 | J134: =VLOOKUP(B134,'Datos Originales'!$D$1:$BC$462,36,FALSE) -> 20101021501
A135: Alamos | B135: FDF0430176 | C135: E000000128 | D135: CC Empleados | E135: ZONA NORTE | F135: 549 | G135: DOS VALLES | H135: 20.00% | I135: 109.8 | J135: =VLOOKUP(B135,'Datos Originales'!$D$1:$BC$462,36,FALSE) -> 20101021501
A136: Alamos | B136: FDF0430176 | C136: E000000128 | D136: CC Empleados | E136: ZONA NORTE | F136: 549 | G136: REVOLUCION | H136: 20.00% | I136: 109.8 | J136: =VLOOKUP(B136,'Datos Originales'!$D$1:$BC$462,36,FALSE) -> 20101021501
A137: Alamos | B137: FDF0430176 | C137: E000000128 | D137: CC Empleados | E137: ZONA NORTE | F137: 549 | G137: CUAHUTEMOC | H137: 20.00% | I137: 109.8 | J137: =VLOOKUP(B137,'Datos Originales'!$D$1:$BC$462,36,FALSE) -> 20101021501
A138: Petroplazas Corporativo | B138: 2C6A1 | C138: SRV0005508 | D138: ES_Corporativo | E138: ES_Corporativo | F138: 3200 | G138: MARINA | H138: 2.32% | I138: 74.24 | J138: =VLOOKUP(B138,'Datos Originales'!$D$1:$BC$462,36,FALSE) -> 50299040042
A139: Petroplazas Corporativo | B139: 2C6A1 | C139: SRV0005508 | D139: ES_Corporativo | E139: ES_Corporativo | F139: 3200 | G139: SABALO | H139: 2.22% | I139: 71.04 | J139: =VLOOKUP(B139,'Datos Originales'!$D$1:$BC$462,36,FALSE) -> 50299040042
A140: Petroplazas Corporativo | B140: 2C6A1 | C140: SRV0005508 | D140: ES_Corporativo | E140: ES_Corporativo | F140: 3200 | G140: CERRITOS | H140: 2.22% | I140: 71.04 | J140: =VLOOKUP(B140,'Datos Originales'!$D$1:$BC$462,36,FALSE) -> 50299040042
A141: Petroplazas Corporativo | B141: 2C6A1 | C141: SRV0005508 | D141: ES_Corporativo | E141: ES_Corporativo | F141: 3200 | G141: REAL DEL VALLE | H141: 2.22% | I141: 71.04 | J141: =VLOOKUP(B141,'Datos Originales'!$D$1:$BC$462,36,FALSE) -> 50299040042
A142: Petroplazas Corporativo | B142: 2C6A1 | C142: SRV0005508 | D142: ES_Corporativo | E142: ES_Corporativo | F142: 3200 | G142: PLAYAS | H142: 2.22% | I142: 71.04 | J142: =VLOOKUP(B142,'Datos Originales'!$D$1:$BC$462,36,FALSE) -> 50299040042
A143: Petroplazas Corporativo | B143: 2C6A1 | C143: SRV0005508 | D143: ES_Corporativo | E143: ES_Corporativo | F143: 3200 | G143: HABAS | H143: 2.22% | I143: 71.04 | J143: =VLOOKUP(B143,'Datos Originales'!$D$1:$BC$462,36,FALSE) -> 50299040042
A144: Petroplazas Corporativo | B144: 2C6A1 | C144: SRV0005508 | D144: ES_Corporativo | E144: ES_Corporativo | F144: 3200 | G144: CARDONES | H144: 2.22% | I144: 71.04 | J144: =VLOOKUP(B144,'Datos Originales'!$D$1:$BC$462,36,FALSE) -> 50299040042
... A1109: Petroplazas Corporativo | B1109: CDDC671 | C1109: SRV0005531 | D1109: ES_Corporativo | E1109: ES_Corporativo | F1109: 15724020 | G1109: LA PAZ | H1109: 2.22% | I1109: 349073.25 | J1109: =VLOOKUP(B1109,'Datos Originales'!$D$1:$BC$462,36,FALSE) -> _CUA-DRE--000000
A1110: CEDIS Mazatlán | B1110: FGC4202 | C1110: E000000467 | E1110: CARRASCO / PLAYAS / LAS HABAS | F1110: 17214 | G1110: CARRASCO | H1110: 33.33% | I1110: 5738 | J1110: =VLOOKUP(B1110,'Datos Originales'!$D$1:$BC$462,36,FALSE) -> 20101021501
A1111: CEDIS Mazatlán | B1111: FGC4202 | C1111: E000000467 | E1111: CARRASCO / PLAYAS / LAS HABAS | F1111: 17214 | G1111: PLAYAS | H1111: 33.33% | I1111: 5738 | J1111: =VLOOKUP(B1111,'Datos Originales'!$D$1:$BC$462,36,FALSE) -> 20101021501
A1112: CEDIS Mazatlán | B1112: FGC4202 | C1112: E000000467 | E1112: CARRASCO / PLAYAS / LAS HABAS | F1112: 17214 | G1112: LAS HABAS | H1112: 33.33% | I1112: 5738 | J1112: =VLOOKUP(B1112,'Datos Originales'!$D$1:$BC$462,36,FALSE) -> 20101021501
A1113: CEDIS Mazatlán | B1113: FGC4201 | C1113: E000000466 | E1113: CARRASCO / PLAYAS / LAS HABAS | F1113: 17136 | G1113: CARRASCO | H1113: 33.33% | I1113: 5712 | J1113: =VLOOKUP(B1113,'Datos Originales'!$D$1:$BC$462,36,FALSE) -> 50299040025
A1114: CEDIS Mazatlán | B1114: FGC4201 | C1114: E000000466 | E1114: CARRASCO / PLAYAS / LAS HABAS | F1114: 17136 | G1114: PLAYAS | H1114: 33.33% | I1114: 5712 | J1114: =VLOOKUP(B1114,'Datos Originales'!$D$1:$BC$462,36,FALSE) -> 50299040025
A1115: CEDIS Mazatlán | B1115: FGC4201 | C1115: E000000466 | E1115: CARRASCO / PLAYAS / LAS HABAS | F1115: 17136 | G1115: LAS HABAS | H1115: 33.33% | I1115: 5712 | J1115: =VLOOKUP(B1115,'Datos Originales'!$D$1:$BC$462,36,FALSE) -> 50299040025
A1116: CEDIS Mazatlán | B1116: K19476 | C1116: SRV0000610 | D1116: Sabalo | E1116: ZONA MZT | F1116: 2124 | G1116: MARINA | H1116: 5.00% | I1116: 106.2 | J1116: =VLOOKUP(B1116,'Datos Originales'!$D$1:$BC$462,36,FALSE) -> 50299030002
A1117: CEDIS Mazatlán | B1117: K19476 | C1117: SRV0000610 | D1117: Sabalo | E1117: ZONA MZT | F1117: 2124 | G1117: SABALO | H1117: 5.00% | I1117: 106.2 | J1117: =VLOOKUP(B1117,'Datos Originales'!$D$1:$BC$462,36,FALSE) -> 50299030002
A1118: CEDIS Mazatlán | B1118: K19476 | C1118: SRV0000610 | D1118: Sabalo | E1118: ZONA MZT | F1118: 2124 | G1118: CERRITOS | H1118: 5.00% | I1118: 106.2 | J1118: =VLOOKUP(B1118,'Datos Originales'!$D$1:$BC$462,36,FALSE) -> 50299030002
A1119: CEDIS Mazatlán | B1119: K19476 | C1119: SRV0000610 | D1119: Sabalo | E1119: ZONA MZT | F1119: 2124 | G1119: REAL DEL VALLE | H1119: 5.00% | I1119: 106.2 | J1119: =VLOOKUP(B1119,'Datos Originales'!$D$1:$BC$462,36,FALSE) -> 50299030002
A1120: CEDIS Mazatlán | B1120: K19476 | C1120: SRV0000610 | D1120: Sabalo | E1120: ZONA MZT | F1120: 2124 | G1120: PLAYAS | H1120: 5.00% | I1120: 106.2 | J1120: =VLOOKUP(B1120,'Datos Originales'!$D$1:$BC$462,36,FALSE) -> 50299030002
A1121: CEDIS Mazatlán | B1121: K19476 | C1121: SRV0000610 | D1121: Sabalo | E1121: ZONA MZT | F1121: 2124 | G1121: HABAS | H1121: 5.00% | I1121: 106.2 | J1121: =VLOOKUP(B1121,'Datos Originales'!$D$1:$BC$462,36,FALSE) -> 50299030002
A1122: CEDIS Mazatlán | B1122: K19476 | C1122: SRV0000610 | D1122: Sabalo | E1122: ZONA MZT | F1122: 2124 | G1122: CARDONES | H1122: 5.00% | I1122: 106.2 | J1122: =VLOOKUP(B1122,'Datos Originales'!$D$1:$BC$462,36,FALSE) -> 50299030002
A1123: CEDIS Mazatlán | B1123: K19476 | C1123: SRV0000610 | D1123: Sabalo | E1123: ZONA MZT | F1123: 2124 | G1123: HABAL | H1123: 5.00% | I1123: 106.2 | J1123: =VLOOKUP(B1123,'Datos Originales'!$D$1:$BC$462,36,FALSE) -> 50299030002
A1124: CEDIS Mazatlán | B1124: K19476 | C1124: SRV0000610 | D1124: Sabalo | E1124: ZONA MZT | F1124: 2124 | G1124: AEROPUERTO | H1124: 5.00% | I1124: 106.2 | J1124: =VLOOKUP(B1124,'Datos Originales'!$D$1:$BC$462,36,FALSE) -> 50299030002
A1125: CEDIS Mazatlán | B1125: K19476 | C1125: SRV0000610 | D1125: Sabalo | E1125: ZONA MZT | F1125: 2124 | G1125: CONCORDIA | H1125: 5.00% | I1125: 106.2 | J1125: =VLOOKUP(B1125,'Datos Originales'!$D$1:$BC$462,36,FALSE) -> 50299030002
A1126: CEDIS Mazatlán | B1126: K19476 | C1126: SRV0000610 | D1126: Sabalo | E1126: ZONA MZT | F1126: 2124 | G1126: FORESTA | H1126: 5.00% | I1126: 106.2 | J1126: =VLOOKUP(B1126,'Datos Originales'!$D$1:$BC$462,36,FALSE) -> 50299030002
A1127: CEDIS Mazatlán | B1127: K19476 | C1127: SRV0000610 | D1127: Sabalo | E1127: ZONA MZT | F1127: 2124 | G1127: FLORES MAGON | H1127: 5.00% | I1127: 106.2 | J1127: =VLOOKUP(B1127,'Datos Originales'!$D$1:$BC$462,36,FALSE) -> 50299030002
... A1135: CEDIS Mazatlán | B1135: K19476 | C1135: SRV0000610 | D1135: Sabalo | E1135: ZONA MZT | F1135: 2124 | G1135: CARRASCO | H1135: 5.00% | I1135: 106.2 | J1135: =VLOOKUP(B1135,'Datos Originales'!$D$1:$BC$462,36,FALSE) -> 50299030002
A1136: CEDIS Culiacán | B1136: 866f81908 | C1136: E000000276 | E1136: ZONA CLN | F1136: 7200 | G1136: DIEZ | H1136: 10.00% | I1136: 720 | J1136: =VLOOKUP(B1136,'Datos Originales'!$D$1:$BC$462,36,FALSE) -> 20101021501
A1137: CEDIS Culiacán | B1137: 866f81908 | C1137: E000000276 | E1137: ZONA CLN | F1137: 7200 | G1137: HUMAYA | H1137: 8.20% | I1137: 590.4 | J1137: =VLOOKUP(B1137,'Datos Originales'!$D$1:$BC$462,36,FALSE) -> 20101021501
A1138: CEDIS Culiacán | B1138: 866f81908 | C1138: E000000276 | E1138: ZONA CLN | F1138: 7200 | G1138: BELLAVISTA | H1138: 8.18% | I1138: 588.96 | J1138: =VLOOKUP(B1138,'Datos Originales'!$D$1:$BC$462,36,FALSE) -> 20101021501
A1139: CEDIS Culiacán | B1139: 866f81908 | C1139: E000000276 | E1139: ZONA CLN | F1139: 7200 | G1139: PAPALOTE | H1139: 8.18% | I1139: 588.96 | J1139: =VLOOKUP(B1139,'Datos Originales'!$D$1:$BC$462,36,FALSE) -> 20101021501
A1140: CEDIS Culiacán | B1140: 866f81908 | C1140: E000000276 | E1140: ZONA CLN | F1140: 7200 | G1140: SAN PEDRO | H1140: 8.18% | I1140: 588.96 | J1140: =VLOOKUP(B1140,'Datos Originales'!$D$1:$BC$462,36,FALSE) -> 20101021501
A1141: CEDIS Culiacán | B1141: 866f81908 | C1141: E000000276 | E1141: ZONA CLN | F1141: 7200 | G1141: HEROICO | H1141: 8.18% | I1141: 588.96 | J1141: =VLOOKUP(B1141,'Datos Originales'!$D$1:$BC$462,36,FALSE) -> 20101021501
A1142: CEDIS Culiacán | B1142: 866f81908 | C1142: E000000276 | E1142: ZONA CLN | F1142: 7200 | G1142: MADERO | H1142: 8.18% | I1142: 588.96 | J1142: =VLOOKUP(B1142,'Datos Originales'!$D$1:$BC$462,36,FALSE) -> 20101021501
A1143: CEDIS Culiacán | B1143: 866f81908 | C1143: E000000276 | E1143: ZONA CLN | F1143: 7200 | G1143: MALECON | H1143: 8.18% | I1143: 588.96 | J1143: =VLOOKUP(B1143,'Datos Originales'!$D$1:$BC$462,36,FALSE) -> 20101021501
A1144: CEDIS Culiacán | B1144: 866f81908 | C1144: E000000276 | E1144: ZONA CLN | F1144: 7200 | G1144: OBREGON | H1144: 8.18% | I1144: 588.96 | J1144: =VLOOKUP(B1144,'Datos Originales'!$D$1:$BC$462,36,FALSE) -> 20101021501
A1145: CEDIS Culiacán | B1145: 866f81908 | C1145: E000000276 | E1145: ZONA CLN | F1145: 7200 | G1145: PATRIA | H1145: 8.18% | I1145: 588.96 | J1145: =VLOOKUP(B1145,'Datos Originales'!$D$1:$BC$462,36,FALSE) -> 20101021501
A1146: CEDIS Culiacán | B1146: 866f81908 | C1146: E000000276 | E1146: ZONA CLN | F1146: 7200 | G1146: PERICOS | H1146: 8.18% | I1146: 588.96 | J1146: =VLOOKUP(B1146,'Datos Originales'!$D$1:$BC$462,36,FALSE) -> 20101021501
A1147: CEDIS Culiacán | B1147: 866f81908 | C1147: E000000276 | E1147: ZONA CLN | F1147: 7200 | G1147: PERICOS CENTRO | H1147: 8.18% | I1147: 588.96 | J1147: =VLOOKUP(B1147,'Datos Originales'!$D$1:$BC$462,36,FALSE) -> 20101021501
A1148: CEDIS Mazatlán | B1148: K19474 | C1148: SRV0000609 | D1148: Flores Magon | E1148: ZONA MZT 3 | F1148: 2124 | G1148: FORESTA | H1148: 14.32% | I1148: 304.16 | J1148: =VLOOKUP(B1148,'Datos Originales'!$D$1:$BC$462,36,FALSE) -> 50299030002
A1149: CEDIS Mazatlán | B1149: K19474 | C1149: SRV0000609 | D1149: Flores Magon | E1149: ZONA MZT 3 | F1149: 2124 | G1149: FLORES MAGON | H1149: 14.28% | I1149: 303.31 | J1149: =VLOOKUP(B1149,'Datos Originales'!$D$1:$BC$462,36,FALSE) -> 50299030002
A1150: CEDIS Mazatlán | B1150: K19474 | C1150: SRV0000609 | D1150: Flores Magon | E1150: ZONA MZT 3 | F1150: 2124 | G1150: 12 DE MAYO | H1150: 14.28% | I1150: 303.31 | J1150: =VLOOKUP(B1150,'Datos Originales'!$D$1:$BC$462,36,FALSE) -> 50299030002
A1151: CEDIS Mazatlán | B1151: K19474 | C1151: SRV0000609 | D1151: Flores Magon | E1151: ZONA MZT 3 | F1151: 2124 | G1151: URBIVILLA | H1151: 14.28% | I1151: 303.31 | J1151: =VLOOKUP(B1151,'Datos Originales'!$D$1:$BC$462,36,FALSE) -> 50299030002
A1152: CEDIS Mazatlán | B1152: K19474 | C1152: SRV0000609 | D1152: Flores Magon | E1152: ZONA MZT 3 | F1152: 2124 | G1152: COLOSIO | H1152: 14.28% | I1152: 303.31 | J1152: =VLOOKUP(B1152,'Datos Originales'!$D$1:$BC$462,36,FALSE) -> 50299030002
A1153: CEDIS Mazatlán | B1153: K19474 | C1153: SRV0000609 | D1153: Flores Magon | E1153: ZONA MZT 3 | F1153: 2124 | G1153: SANTA ROSA | H1153: 14.28% | I1153: 303.31 | J1153: =VLOOKUP(B1153,'Datos Originales'!$D$1:$BC$462,36,FALSE) -> 50299030002
A1154: CEDIS Mazatlán | B1154: K19474 | C1154: SRV0000609 | D1154: Flores Magon | E1154: ZONA MZT 3 | F1154: 2124 | G1154: EL CONCHI | H1154: 14.28% | I1154: 303.31 | J1154: =VLOOKUP(B1154,'Datos Originales'!$D$1:$BC$462,36,FALSE) -> 50299030002
A1155: CEDIS Mazatlán | B1155: 1e81f1907 | C1155: E000000468 | E1155: 12 DE MAYO / AEROPUERTO / ESCUINAPA / CONCORDIA / URBIVILLA / FORESTA / ROSARIO / SABALO / HABAL | F1155: 10600 | G1155: 12 DE MAYO | H1155: 11.11% | I1155: 1177.78 | J1155: =VLOOKUP(B1155,'Datos Originales'!$D$1:$BC$462,36,FALSE) -> 20101021501
A1156: CEDIS Mazatlán | B1156: 1e81f1907 | C1156: E000000468 | E1156: 12 DE MAYO / AEROPUERTO / ESCUINAPA / CONCORDIA / URBIVILLA / FORESTA / ROSARIO / SABALO / HABAL | F1156: 10600 | G1156: AEROPUERTO | H1156: 11.11% | I1156: 1177.78 | J1156: =VLOOKUP(B1156,'Datos Originales'!$D$1:$BC$462,36,FALSE) -> 20101021501
A1157: CEDIS Mazatlán | B1157: 1e81f1907 | C1157: E000000468 | E1157: 12 DE MAYO / AEROPUERTO / ESCUINAPA / CONCORDIA / URBIVILLA / FORESTA / ROSARIO / SABALO / HABAL | F1157: 10600 | G1157: ESCUINAPA | H1157: 11.11% | I1157: 1177.78 | J1157: =VLOOKUP(B1157,'Datos Originales'!$D$1:$BC$462,36,FALSE) -> 20101021501
A1158: CEDIS Mazatlán | B1158: 1e81f1907 | C1158: E000000468 | E1158: 12 DE MAYO / AEROPUERTO / ESCUINAPA / CONCORDIA / URBIVILLA / FORESTA / ROSARIO / SABALO / HABAL | F1158: 10600 | G1158: CONCORDIA | H1158: 11.11% | I1158: 1177.78 | J1158: =VLOOKUP(B1158,'Datos Originales'!$D$1:$BC$462,36,FALSE) -> 20101021501
A1159: CEDIS Mazatlán | B1159: 1e81f1907 | C1159: E000000468 | E1159: 12 DE MAYO / AEROPUERTO / ESCUINAPA / CONCORDIA / URBIVILLA / FORESTA / ROSARIO / SABALO / HABAL | F1159: 10600 | G1159: URBIVILLA | H1159: 11.11% | I1159: 1177.78 | J1159: =VLOOKUP(B1159,'Datos Originales'!$D$1:$BC$462,36,FALSE) -> 20101021501
A1160: CEDIS Mazatlán | B1160: 1e81f1907 | C1160: E000000468 | E1160: 12 DE MAYO / AEROPUERTO / ESCUINAPA / CONCORDIA / URBIVILLA / FORESTA / ROSARIO / SABALO / HABAL | F1160: 10600 | G1160: FORESTA | H1160: 11.11% | I1160: 1177.78 | J1160: =VLOOKUP(B1160,'Datos Originales'!$D$1:$BC$462,36,FALSE) -> 20101021501
A1161: CEDIS Mazatlán | B1161: 1e81f1907 | C1161: E000000468 | E1161: 12 DE MAYO / AEROPUERTO / ESCUINAPA / CONCORDIA / URBIVILLA / FORESTA / ROSARIO / SABALO / HABAL | F1161: 10600 | G1161: ROSARIO | H1161: 11.11% | I1161: 1177.78 | J1161: =VLOOKUP(B1161,'Datos Originales'!$D$1:$BC$462,36,FALSE) -> 20101021501
A1162: CEDIS Mazatlán | B1162: 1e81f1907 | C1162: E000000468 | E1162: 12 DE MAYO / AEROPUERTO / ESCUINAPA / CONCORDIA / URBIVILLA / FORESTA / ROSARIO / SABALO / HABAL | F1162: 10600 | G1162: SABALO | H1162: 11.11% | I1162: 1177.78 | J1162: =VLOOKUP(B1162,'Datos Originales'!$D$1:$BC$462,36,FALSE) -> 20101021501
A1163: CEDIS Mazatlán | B1163: 1e81f1907 | C1163: E000000468 | E1163: 12 DE MAYO / AEROPUERTO / ESCUINAPA / CONCORDIA / URBIVILLA / FORESTA / ROSARIO / SABALO / HABAL | F1163: 10600 | G1163: HABAL | H1163: 11.11% | I1163: 1177.78 | J1163: =VLOOKUP(B1163,'Datos Originales'!$D$1:$BC$462,36,FALSE) -> 20101021501
A1164: CEDIS Culiacán | B1164: K19475 | C1164: SRV0000465 | D1164: CUAUHTEMOC | E1164: ZONA NORTE | F1164: 1770 | G1164: ALAMOS | H1164: 20.00% | I1164: 354 | J1164: =VLOOKUP(B1164,'Datos Originales'!$D$1:$BC$462,36,FALSE) -> 50299030002
...
